Workbook

Sheet Codebook
A1: XR systematic mapping – extraction codebook for RQ5–RQ7
A3: Research questions
A4: RQ5. In which education levels, subject areas and countries/regions have XR studies on engagement, motivation and satisfaction been conducted?
A5: RQ6. What is the direction, strength and consistency of reported XR effects on learner engagement, motivation and satisfaction, and do they differ by education level, subject area and device type?
A6: RQ7. What is the methodological quality and design rigor of the included studies?
A8: How RQ6 is answered: each study is coded + / 0 / − / Mixed per outcome ("direction"); strength = statistical support, effect size and rigor of the studies behind each direction; consistency = share of measuring studies that agree, computed across studies on the Evidence Map sheet (not coded per paper).
A9: Quality appraisal: Mixed Methods Appraisal Tool (MMAT) 2018, Hong QN et al. Two screening questions, then 5 category-specific criteria; score = number met (0–5).
A10: MMAT item ratings are entered on the "MMAT Appraisal" sheet; the MMAT score and "Overall rigor" in Sheet1 update automatically. For mixed-methods studies the component that provides the RQ6 evidence is appraised. Where a construct fits more than one outcome, the code follows the definitions below (e.g., SAM emotional valence = emotional engagement; enjoyment/interest = motivation; satisfaction/preference/reuse = satisfaction).
A12: RQ | B12: Column in Sheet1 | C12: Definition / allowed values
A13: RQ5 | B13: AR: Country (study site) | C13: Country where the learners were studied (not author affiliation). Multi-country → list all.
A14: RQ5 | B14: AS: Region | C14: Continent derived from country: Africa / Asia / Europe / North America / South America / Oceania / Multi-country.
A15: RQ5 | B15: AT: Education level (ISCED 2011) | C15: Pre-primary / Primary / Lower secondary / Upper secondary / Secondary (unspecified) / Mixed K-12 / Mixed (school-age + adults) / Higher education / Mixed (secondary + post-secondary) / Informal / general public / Not reported.
A16: RQ5 | B16: AU: Learner population | C16: Who provided the data: typical learners, SEN learners (state condition), teachers as evaluators, general public.
A17: RQ5 | B17: AV: Subject area (ISCED-F 2013 broad field) | C17: Broad field of education & training (UNESCO ISCED-F 2013). "Generic / multi-subject" for cross-curricular or life-skills content.
A18: RQ5 | B18: AW: Subject (specific) | C18: Specific topic as reported by the study.
A19: RQ6 | B19: AX: XR type | C19: VR / AR / MR / VR + AR / VR (360°) / non-immersive variants. Record what learners actually used.
A20: RQ6 | B20: AY: Device category | C20: HMD (immersive) / Handheld (mobile/tablet) / Desktop / CAVE or projection / Web-based / None (mock-up) / Not reported. Used as the device-type moderator for RQ6.
A21: RQ6 | B21: AZ: Device (specific) | C21: Hardware/platform as reported.
A22: RQ6 | B22: BA: Comparison condition | C22: None / Traditional teaching / Non-immersive digital / Other XR / Traditional + non-immersive.
A23: RQ6 | B23: BB: Engagement effect | C23: + positive / 0 no difference / − negative / Mixed / Unclear (measured but direction not reported) / Not measured. Engagement = behavioural, cognitive or emotional involvement (participation, attention, flow, concentration, active discussion).
... A43: Admin | B43: BV: Verification flags | C43: Open issues for the full-text pass.

Sheet Evidence Map
A1: Evidence map – every count is a live formula on Sheet1
A2: Sets: Mapping corpus = all studies except retracted (E1). Empirical = Core + Sensitivity. Core = basic-education learners with E/M/S data (primary synthesis).
A4: Table 0. Eligibility flow for RQ5–RQ7
A5: Set | B5: Studies
A6: Mapping corpus (RQ1–RQ4 published set) | B6: =COUNTA(Sheet1!$A$2:$A$200) -> 45
A7: Excluded – E1 retracted | B7: =COUNTIFS(Sheet1!$BT$2:$BT$200,"E1*") -> 1
A8: Mapping corpus used for RQ5 | B8: =B6-B7 -> 44
A9: Excluded – E2 no learner data | B9: =COUNTIFS(Sheet1!$BT$2:$BT$200,"E2*") -> 8
A10: Excluded – E3 no E/M/S outcome measured | B10: =COUNTIFS(Sheet1!$BT$2:$BT$200,"E3*") -> 1
A11: Excluded – E4 teacher-only data | B11: =COUNTIFS(Sheet1!$BT$2:$BT$200,"E4*") -> 2
A12: Excluded – E5 no real XR exposure | B12: =COUNTIFS(Sheet1!$BT$2:$BT$200,"E5*") -> 1
A13: Empirical studies (RQ7 appraisal) | B13: =COUNTIFS(Sheet1!$BS$2:$BS$200,"Core")+COUNTIFS(Sheet1!$BS$2:$BS$200,"Sensitivity") -> 32
A14: Sensitivity (outside basic education) | B14: =COUNTIFS(Sheet1!$BS$2:$BS$200,"Sensitivity") -> 11
A15: Core synthesis set (RQ6) | B15: =COUNTIFS(Sheet1!$BS$2:$BS$200,"Core") -> 21
A17: Table 6a. RQ6 – Direction and consistency of effects, CORE set (basic education)
A18: Outcome | B18: + | C18: Mixed | D18: Unclear | E18: 0 | F18: − | G18: Studies measuring | H18: % positive (consistency) | I18: + from Moderate/High-rigor
A19: Engagement | B19: =COUNTIFS(Sheet1!$BB$2:$BB$200,"+",Sheet1!$BS$2:$BS$200,"Core") -> 7 | C19: =COUNTIFS(Sheet1!$BB$2:$BB$200,"Mixed",Sheet1!$BS$2:$BS$200,"Core") -> 1 | D19: =COUNTIFS(Sheet1!$BB$2:$BB$200,"Unclear",Sheet1!$BS$2:$BS$200,"Core") -> 1 | E19: =COUNTIFS(Sheet1!$BB$2:$BB$200,"0",Sheet1!$BS$2:$BS$200,"Core") -> 0 | F19: =COUNTIFS(Sheet1!$BB$2:$BB$200,"−",Sheet1!$BS$2:$BS$200,"Core") -> 0 | G19: =SUM(B19:F19) -> 9 | H19: =IF(G19=0,"-",B19/G19) -> 0.77777778 | I19: =COUNTIFS(Sheet1!$BB$2:$BB$200,"+",Sheet1!$BS$2:$BS$200,"Core",Sheet1!$BP$2:$BP$200,"Moderate")+COUNTIFS(Sheet1!$BB$2:$BB$200,"+",Sheet1!$BS$2:$BS$200,"Core",Sheet1!$BP$2:$BP$200,"High") -> 1
A20: Motivation | B20: =COUNTIFS(Sheet1!$BC$2:$BC$200,"+",Sheet1!$BS$2:$BS$200,"Core") -> 15 | C20: =COUNTIFS(Sheet1!$BC$2:$BC$200,"Mixed",Sheet1!$BS$2:$BS$200,"Core") -> 0 | D20: =COUNTIFS(Sheet1!$BC$2:$BC$200,"Unclear",Sheet1!$BS$2:$BS$200,"Core") -> 0 | E20: =COUNTIFS(Sheet1!$BC$2:$BC$200,"0",Sheet1!$BS$2:$BS$200,"Core") -> 0 | F20: =COUNTIFS(Sheet1!$BC$2:$BC$200,"−",Sheet1!$BS$2:$BS$200,"Core") -> 0 | G20: =SUM(B20:F20) -> 15 | H20: =IF(G20=0,"-",B20/G20) -> 1 | I20: =COUNTIFS(Sheet1!$BC$2:$BC$200,"+",Sheet1!$BS$2:$BS$200,"Core",Sheet1!$BP$2:$BP$200,"Moderate")+COUNTIFS(Sheet1!$BC$2:$BC$200,"+",Sheet1!$BS$2:$BS$200,"Core",Sheet1!$BP$2:$BP$200,"High") -> 3
A21: Satisfaction | B21: =COUNTIFS(Sheet1!$BD$2:$BD$200,"+",Sheet1!$BS$2:$BS$200,"Core") -> 13 | C21: =COUNTIFS(Sheet1!$BD$2:$BD$200,"Mixed",Sheet1!$BS$2:$BS$200,"Core") -> 0 | D21: =COUNTIFS(Sheet1!$BD$2:$BD$200,"Unclear",Sheet1!$BS$2:$BS$200,"Core") -> 1 | E21: =COUNTIFS(Sheet1!$BD$2:$BD$200,"0",Sheet1!$BS$2:$BS$200,"Core") -> 0 | F21: =COUNTIFS(Sheet1!$BD$2:$BD$200,"−",Sheet1!$BS$2:$BS$200,"Core") -> 0 | G21: =SUM(B21:F21) -> 14 | H21: =IF(G21=0,"-",B21/G21) -> 0.92857143 | I21: =COUNTIFS(Sheet1!$BD$2:$BD$200,"+",Sheet1!$BS$2:$BS$200,"Core",Sheet1!$BP$2:$BP$200,"Moderate")+COUNTIFS(Sheet1!$BD$2:$BD$200,"+",Sheet1!$BS$2:$BS$200,"Core",Sheet1!$BP$2:$BP$200,"High") -> 2
A23: Table 6b. RQ6 – Direction and consistency, ALL empirical studies (Core + Sensitivity)
A24: Outcome | B24: + | C24: Mixed | D24: Unclear | E24: 0 | F24: − | G24: Studies measuring | H24: % positive (consistency) | I24: + from Moderate/High-rigor
A25: Engagement | B25: =(COUNTIFS(Sheet1!$BB$2:$BB$200,"+",Sheet1!$BS$2:$BS$200,"Core")+COUNTIFS(Sheet1!$BB$2:$BB$200,"+",Sheet1!$BS$2:$BS$200,"Sensitivity")) -> 11 | C25: =(COUNTIFS(Sheet1!$BB$2:$BB$200,"Mixed",Sheet1!$BS$2:$BS$200,"Core")+COUNTIFS(Sheet1!$BB$2:$BB$200,"Mixed",Sheet1!$BS$2:$BS$200,"Sensitivity")) -> 1 | D25: =(COUNTIFS(Sheet1!$BB$2:$BB$200,"Unclear",Sheet1!$BS$2:$BS$200,"Core")+COUNTIFS(Sheet1!$BB$2:$BB$200,"Unclear",Sheet1!$BS$2:$BS$200,"Sensitivity")) -> 1 | E25: =(COUNTIFS(Sheet1!$BB$2:$BB$200,"0",Sheet1!$BS$2:$BS$200,"Core")+COUNTIFS(Sheet1!$BB$2:$BB$200,"0",Sheet1!$BS$2:$BS$200,"Sensitivity")) -> 0 | F25: =(COUNTIFS(Sheet1!$BB$2:$BB$200,"−",Sheet1!$BS$2:$BS$200,"Core")+COUNTIFS(Sheet1!$BB$2:$BB$200,"−",Sheet1!$BS$2:$BS$200,"Sensitivity")) -> 0 | G25: =SUM(B25:F25) -> 13 | H25: =IF(G25=0,"-",B25/G25) -> 0.84615385 | I25: =COUNTIFS(Sheet1!$BB$2:$BB$200,"+",Sheet1!$BS$2:$BS$200,"<>Excluded",Sheet1!$BP$2:$BP$200,"Moderate")+COUNTIFS(Sheet1!$BB$2:$BB$200,"+",Sheet1!$BS$2:$BS$200,"<>Excluded",Sheet1!$BP$2:$BP$200,"High") -> 1
A26: Motivation | B26: =(COUNTIFS(Sheet1!$BC$2:$BC$200,"+",Sheet1!$BS$2:$BS$200,"Core")+COUNTIFS(Sheet1!$BC$2:$BC$200,"+",Sheet1!$BS$2:$BS$200,"Sensitivity")) -> 22 | C26: =(COUNTIFS(Sheet1!$BC$2:$BC$200,"Mixed",Sheet1!$BS$2:$BS$200,"Core")+COUNTIFS(Sheet1!$BC$2:$BC$200,"Mixed",Sheet1!$BS$2:$BS$200,"Sensitivity")) -> 1 | D26: =(COUNTIFS(Sheet1!$BC$2:$BC$200,"Unclear",Sheet1!$BS$2:$BS$200,"Core")+COUNTIFS(Sheet1!$BC$2:$BC$200,"Unclear",Sheet1!$BS$2:$BS$200,"Sensitivity")) -> 1 | E26: =(COUNTIFS(Sheet1!$BC$2:$BC$200,"0",Sheet1!$BS$2:$BS$200,"Core")+COUNTIFS(Sheet1!$BC$2:$BC$200,"0",Sheet1!$BS$2:$BS$200,"Sensitivity")) -> 0 | F26: =(COUNTIFS(Sheet1!$BC$2:$BC$200,"−",Sheet1!$BS$2:$BS$200,"Core")+COUNTIFS(Sheet1!$BC$2:$BC$200,"−",Sheet1!$BS$2:$BS$200,"Sensitivity")) -> 0 | G26: =SUM(B26:F26) -> 24 | H26: =IF(G26=0,"-",B26/G26) -> 0.91666667 | I26: =COUNTIFS(Sheet1!$BC$2:$BC$200,"+",Sheet1!$BS$2:$BS$200,"<>Excluded",Sheet1!$BP$2:$BP$200,"Moderate")+COUNTIFS(Sheet1!$BC$2:$BC$200,"+",Sheet1!$BS$2:$BS$200,"<>Excluded",Sheet1!$BP$2:$BP$200,"High") -> 4
A27: Satisfaction | B27: =(COUNTIFS(Sheet1!$BD$2:$BD$200,"+",Sheet1!$BS$2:$BS$200,"Core")+COUNTIFS(Sheet1!$BD$2:$BD$200,"+",Sheet1!$BS$2:$BS$200,"Sensitivity")) -> 21 | C27: =(COUNTIFS(Sheet1!$BD$2:$BD$200,"Mixed",Sheet1!$BS$2:$BS$200,"Core")+COUNTIFS(Sheet1!$BD$2:$BD$200,"Mixed",Sheet1!$BS$2:$BS$200,"Sensitivity")) -> 0 | D27: =(COUNTIFS(Sheet1!$BD$2:$BD$200,"Unclear",Sheet1!$BS$2:$BS$200,"Core")+COUNTIFS(Sheet1!$BD$2:$BD$200,"Unclear",Sheet1!$BS$2:$BS$200,"Sensitivity")) -> 1 | E27: =(COUNTIFS(Sheet1!$BD$2:$BD$200,"0",Sheet1!$BS$2:$BS$200,"Core")+COUNTIFS(Sheet1!$BD$2:$BD$200,"0",Sheet1!$BS$2:$BS$200,"Sensitivity")) -> 0 | F27: =(COUNTIFS(Sheet1!$BD$2:$BD$200,"−",Sheet1!$BS$2:$BS$200,"Core")+COUNTIFS(Sheet1!$BD$2:$BD$200,"−",Sheet1!$BS$2:$BS$200,"Sensitivity")) -> 0 | G27: =SUM(B27:F27) -> 22 | H27: =IF(G27=0,"-",B27/G27) -> 0.95454545 | I27: =COUNTIFS(Sheet1!$BD$2:$BD$200,"+",Sheet1!$BS$2:$BS$200,"<>Excluded",Sheet1!$BP$2:$BP$200,"Moderate")+COUNTIFS(Sheet1!$BD$2:$BD$200,"+",Sheet1!$BS$2:$BS$200,"<>Excluded",Sheet1!$BP$2:$BP$200,"High") -> 4
A29: RQ6 (Core set). Effects by education level [positive / measured]
A30: education level | B30: Core studies | C30: Engagement + | D30: Engagement measured | E30: Motivation + | F30: Motivation measured | G30: Satisfaction + | H30: Satisfaction measured
A31: Primary | B31: =COUNTIFS(Sheet1!$AT$2:$AT$200,A31,Sheet1!$BS$2:$BS$200,"Core") -> 4 | C31: =COUNTIFS(Sheet1!$AT$2:$AT$200,A31,Sheet1!$BS$2:$BS$200,"Core",Sheet1!$BB$2:$BB$200,"+") -> 1 | D31: =COUNTIFS(Sheet1!$AT$2:$AT$200,A31,Sheet1!$BS$2:$BS$200,"Core",Sheet1!$BB$2:$BB$200,"<>Not measured",Sheet1!$BB$2:$BB$200,"<>") -> 1 | E31: =COUNTIFS(Sheet1!$AT$2:$AT$200,A31,Sheet1!$BS$2:$BS$200,"Core",Sheet1!$BC$2:$BC$200,"+") -> 4 | F31: =COUNTIFS(Sheet1!$AT$2:$AT$200,A31,Sheet1!$BS$2:$BS$200,"Core",Sheet1!$BC$2:$BC$200,"<>Not measured",Sheet1!$BC$2:$BC$200,"<>") -> 4 | G31: =COUNTIFS(Sheet1!$AT$2:$AT$200,A31,Sheet1!$BS$2:$BS$200,"Core",Sheet1!$BD$2:$BD$200,"+") -> 3 | H31: =COUNTIFS(Sheet1!$AT$2:$AT$200,A31,Sheet1!$BS$2:$BS$200,"Core",Sheet1!$BD$2:$BD$200,"<>Not measured",Sheet1!$BD$2:$BD$200,"<>") -> 3
A32: Lower secondary | B32: =COUNTIFS(Sheet1!$AT$2:$AT$200,A32,Sheet1!$BS$2:$BS$200,"Core") -> 4 | C32: =COUNTIFS(Sheet1!$AT$2:$AT$200,A32,Sheet1!$BS$2:$BS$200,"Core",Sheet1!$BB$2:$BB$200,"+") -> 1 | D32: =COUNTIFS(Sheet1!$AT$2:$AT$200,A32,Sheet1!$BS$2:$BS$200,"Core",Sheet1!$BB$2:$BB$200,"<>Not measured",Sheet1!$BB$2:$BB$200,"<>") -> 2 | E32: =COUNTIFS(Sheet1!$AT$2:$AT$200,A32,Sheet1!$BS$2:$BS$200,"Core",Sheet1!$BC$2:$BC$200,"+") -> 3 | F32: =COUNTIFS(Sheet1!$AT$2:$AT$200,A32,Sheet1!$BS$2:$BS$200,"Core",Sheet1!$BC$2:$BC$200,"<>Not measured",Sheet1!$BC$2:$BC$200,"<>") -> 3 | G32: =COUNTIFS(Sheet1!$AT$2:$AT$200,A32,Sheet1!$BS$2:$BS$200,"Core",Sheet1!$BD$2:$BD$200,"+") -> 1 | H32: =COUNTIFS(Sheet1!$AT$2:$AT$200,A32,Sheet1!$BS$2:$BS$200,"Core",Sheet1!$BD$2:$BD$200,"<>Not measured",Sheet1!$BD$2:$BD$200,"<>") -> 2
A33: Upper secondary | B33: =COUNTIFS(Sheet1!$AT$2:$AT$200,A33,Sheet1!$BS$2:$BS$200,"Core") -> 2 | C33: =COUNTIFS(Sheet1!$AT$2:$AT$200,A33,Sheet1!$BS$2:$BS$200,"Core",Sheet1!$BB$2:$BB$200,"+") -> 0 | D33: =COUNTIFS(Sheet1!$AT$2:$AT$200,A33,Sheet1!$BS$2:$BS$200,"Core",Sheet1!$BB$2:$BB$200,"<>Not measured",Sheet1!$BB$2:$BB$200,"<>") -> 0 | E33: =COUNTIFS(Sheet1!$AT$2:$AT$200,A33,Sheet1!$BS$2:$BS$200,"Core",Sheet1!$BC$2:$BC$200,"+") -> 1 | F33: =COUNTIFS(Sheet1!$AT$2:$AT$200,A33,Sheet1!$BS$2:$BS$200,"Core",Sheet1!$BC$2:$BC$200,"<>Not measured",Sheet1!$BC$2:$BC$200,"<>") -> 1 | G33: =COUNTIFS(Sheet1!$AT$2:$AT$200,A33,Sheet1!$BS$2:$BS$200,"Core",Sheet1!$BD$2:$BD$200,"+") -> 1 | H33: =COUNTIFS(Sheet1!$AT$2:$AT$200,A33,Sheet1!$BS$2:$BS$200,"Core",Sheet1!$BD$2:$BD$200,"<>Not measured",Sheet1!$BD$2:$BD$200,"<>") -> 1
A34: Secondary (unspecified) | B34: =COUNTIFS(Sheet1!$AT$2:$AT$200,A34,Sheet1!$BS$2:$BS$200,"Core") -> 3 | C34: =COUNTIFS(Sheet1!$AT$2:$AT$200,A34,Sheet1!$BS$2:$BS$200,"Core",Sheet1!$BB$2:$BB$200,"+") -> 1 | D34: =COUNTIFS(Sheet1!$AT$2:$AT$200,A34,Sheet1!$BS$2:$BS$200,"Core",Sheet1!$BB$2:$BB$200,"<>Not measured",Sheet1!$BB$2:$BB$200,"<>") -> 2 | E34: =COUNTIFS(Sheet1!$AT$2:$AT$200,A34,Sheet1!$BS$2:$BS$200,"Core",Sheet1!$BC$2:$BC$200,"+") -> 2 | F34: =COUNTIFS(Sheet1!$AT$2:$AT$200,A34,Sheet1!$BS$2:$BS$200,"Core",Sheet1!$BC$2:$BC$200,"<>Not measured",Sheet1!$BC$2:$BC$200,"<>") -> 2 | G34: =COUNTIFS(Sheet1!$AT$2:$AT$200,A34,Sheet1!$BS$2:$BS$200,"Core",Sheet1!$BD$2:$BD$200,"+") -> 3 | H34: =COUNTIFS(Sheet1!$AT$2:$AT$200,A34,Sheet1!$BS$2:$BS$200,"Core",Sheet1!$BD$2:$BD$200,"<>Not measured",Sheet1!$BD$2:$BD$200,"<>") -> 3
A35: Mixed K-12 | B35: =COUNTIFS(Sheet1!$AT$2:$AT$200,A35,Sheet1!$BS$2:$BS$200,"Core") -> 4 | C35: =COUNTIFS(Sheet1!$AT$2:$AT$200,A35,Sheet1!$BS$2:$BS$200,"Core",Sheet1!$BB$2:$BB$200,"+") -> 3 | D35: =COUNTIFS(Sheet1!$AT$2:$AT$200,A35,Sheet1!$BS$2:$BS$200,"Core",Sheet1!$BB$2:$BB$200,"<>Not measured",Sheet1!$BB$2:$BB$200,"<>") -> 3 | E35: =COUNTIFS(Sheet1!$AT$2:$AT$200,A35,Sheet1!$BS$2:$BS$200,"Core",Sheet1!$BC$2:$BC$200,"+") -> 2 | F35: =COUNTIFS(Sheet1!$AT$2:$AT$200,A35,Sheet1!$BS$2:$BS$200,"Core",Sheet1!$BC$2:$BC$200,"<>Not measured",Sheet1!$BC$2:$BC$200,"<>") -> 2 | G35: =COUNTIFS(Sheet1!$AT$2:$AT$200,A35,Sheet1!$BS$2:$BS$200,"Core",Sheet1!$BD$2:$BD$200,"+") -> 1 | H35: =COUNTIFS(Sheet1!$AT$2:$AT$200,A35,Sheet1!$BS$2:$BS$200,"Core",Sheet1!$BD$2:$BD$200,"<>Not measured",Sheet1!$BD$2:$BD$200,"<>") -> 1
A36: Mixed (school-age + adults) | B36: =COUNTIFS(Sheet1!$AT$2:$AT$200,A36,Sheet1!$BS$2:$BS$200,"Core") -> 1 | C36: =COUNTIFS(Sheet1!$AT$2:$AT$200,A36,Sheet1!$BS$2:$BS$200,"Core",Sheet1!$BB$2:$BB$200,"+") -> 0 | D36: =COUNTIFS(Sheet1!$AT$2:$AT$200,A36,Sheet1!$BS$2:$BS$200,"Core",Sheet1!$BB$2:$BB$200,"<>Not measured",Sheet1!$BB$2:$BB$200,"<>") -> 0 | E36: =COUNTIFS(Sheet1!$AT$2:$AT$200,A36,Sheet1!$BS$2:$BS$200,"Core",Sheet1!$BC$2:$BC$200,"+") -> 0 | F36: =COUNTIFS(Sheet1!$AT$2:$AT$200,A36,Sheet1!$BS$2:$BS$200,"Core",Sheet1!$BC$2:$BC$200,"<>Not measured",Sheet1!$BC$2:$BC$200,"<>") -> 0 | G36: =COUNTIFS(Sheet1!$AT$2:$AT$200,A36,Sheet1!$BS$2:$BS$200,"Core",Sheet1!$BD$2:$BD$200,"+") -> 1 | H36: =COUNTIFS(Sheet1!$AT$2:$AT$200,A36,Sheet1!$BS$2:$BS$200,"Core",Sheet1!$BD$2:$BD$200,"<>Not measured",Sheet1!$BD$2:$BD$200,"<>") -> 1
A37: Mixed (secondary + post-secondary) | B37: =COUNTIFS(Sheet1!$AT$2:$AT$200,A37,Sheet1!$BS$2:$BS$200,"Core") -> 2 | C37: =COUNTIFS(Sheet1!$AT$2:$AT$200,A37,Sheet1!$BS$2:$BS$200,"Core",Sheet1!$BB$2:$BB$200,"+") -> 1 | D37: =COUNTIFS(Sheet1!$AT$2:$AT$200,A37,Sheet1!$BS$2:$BS$200,"Core",Sheet1!$BB$2:$BB$200,"<>Not measured",Sheet1!$BB$2:$BB$200,"<>") -> 1 | E37: =COUNTIFS(Sheet1!$AT$2:$AT$200,A37,Sheet1!$BS$2:$BS$200,"Core",Sheet1!$BC$2:$BC$200,"+") -> 2 | F37: =COUNTIFS(Sheet1!$AT$2:$AT$200,A37,Sheet1!$BS$2:$BS$200,"Core",Sheet1!$BC$2:$BC$200,"<>Not measured",Sheet1!$BC$2:$BC$200,"<>") -> 2 | G37: =COUNTIFS(Sheet1!$AT$2:$AT$200,A37,Sheet1!$BS$2:$BS$200,"Core",Sheet1!$BD$2:$BD$200,"+") -> 2 | H37: =COUNTIFS(Sheet1!$AT$2:$AT$200,A37,Sheet1!$BS$2:$BS$200,"Core",Sheet1!$BD$2:$BD$200,"<>Not measured",Sheet1!$BD$2:$BD$200,"<>") -> 2
A38: Not reported | B38: =COUNTIFS(Sheet1!$AT$2:$AT$200,A38,Sheet1!$BS$2:$BS$200,"Core") -> 1 | C38: =COUNTIFS(Sheet1!$AT$2:$AT$200,A38,Sheet1!$BS$2:$BS$200,"Core",Sheet1!$BB$2:$BB$200,"+") -> 0 | D38: =COUNTIFS(Sheet1!$AT$2:$AT$200,A38,Sheet1!$BS$2:$BS$200,"Core",Sheet1!$BB$2:$BB$200,"<>Not measured",Sheet1!$BB$2:$BB$200,"<>") -> 0 | E38: =COUNTIFS(Sheet1!$AT$2:$AT$200,A38,Sheet1!$BS$2:$BS$200,"Core",Sheet1!$BC$2:$BC$200,"+") -> 1 | F38: =COUNTIFS(Sheet1!$AT$2:$AT$200,A38,Sheet1!$BS$2:$BS$200,"Core",Sheet1!$BC$2:$BC$200,"<>Not measured",Sheet1!$BC$2:$BC$200,"<>") -> 1 | G38: =COUNTIFS(Sheet1!$AT$2:$AT$200,A38,Sheet1!$BS$2:$BS$200,"Core",Sheet1!$BD$2:$BD$200,"+") -> 1 | H38: =COUNTIFS(Sheet1!$AT$2:$AT$200,A38,Sheet1!$BS$2:$BS$200,"Core",Sheet1!$BD$2:$BD$200,"<>Not measured",Sheet1!$BD$2:$BD$200,"<>") -> 1
A40: RQ6 (Core set). Effects by device category [positive / measured]
A41: device category | B41: Core studies | C41: Engagement + | D41: Engagement measured | E41: Motivation + | F41: Motivation measured | G41: Satisfaction + | H41: Satisfaction measured
A42: HMD (immersive) | B42: =COUNTIFS(Sheet1!$AY$2:$AY$200,A42,Sheet1!$BS$2:$BS$200,"Core") -> 10 | C42: =COUNTIFS(Sheet1!$AY$2:$AY$200,A42,Sheet1!$BS$2:$BS$200,"Core",Sheet1!$BB$2:$BB$200,"+") -> 5 | D42: =COUNTIFS(Sheet1!$AY$2:$AY$200,A42,Sheet1!$BS$2:$BS$200,"Core",Sheet1!$BB$2:$BB$200,"<>Not measured",Sheet1!$BB$2:$BB$200,"<>") -> 5 | E42: =COUNTIFS(Sheet1!$AY$2:$AY$200,A42,Sheet1!$BS$2:$BS$200,"Core",Sheet1!$BC$2:$BC$200,"+") -> 8 | F42: =COUNTIFS(Sheet1!$AY$2:$AY$200,A42,Sheet1!$BS$2:$BS$200,"Core",Sheet1!$BC$2:$BC$200,"<>Not measured",Sheet1!$BC$2:$BC$200,"<>") -> 8 | G42: =COUNTIFS(Sheet1!$AY$2:$AY$200,A42,Sheet1!$BS$2:$BS$200,"Core",Sheet1!$BD$2:$BD$200,"+") -> 6 | H42: =COUNTIFS(Sheet1!$AY$2:$AY$200,A42,Sheet1!$BS$2:$BS$200,"Core",Sheet1!$BD$2:$BD$200,"<>Not measured",Sheet1!$BD$2:$BD$200,"<>") -> 6
A43: Handheld (mobile/tablet) | B43: =COUNTIFS(Sheet1!$AY$2:$AY$200,A43,Sheet1!$BS$2:$BS$200,"Core") -> 2 | C43: =COUNTIFS(Sheet1!$AY$2:$AY$200,A43,Sheet1!$BS$2:$BS$200,"Core",Sheet1!$BB$2:$BB$200,"+") -> 0 | D43: =COUNTIFS(Sheet1!$AY$2:$AY$200,A43,Sheet1!$BS$2:$BS$200,"Core",Sheet1!$BB$2:$BB$200,"<>Not measured",Sheet1!$BB$2:$BB$200,"<>") -> 0 | E43: =COUNTIFS(Sheet1!$AY$2:$AY$200,A43,Sheet1!$BS$2:$BS$200,"Core",Sheet1!$BC$2:$BC$200,"+") -> 1 | F43: =COUNTIFS(Sheet1!$AY$2:$AY$200,A43,Sheet1!$BS$2:$BS$200,"Core",Sheet1!$BC$2:$BC$200,"<>Not measured",Sheet1!$BC$2:$BC$200,"<>") -> 1 | G43: =COUNTIFS(Sheet1!$AY$2:$AY$200,A43,Sheet1!$BS$2:$BS$200,"Core",Sheet1!$BD$2:$BD$200,"+") -> 2 | H43: =COUNTIFS(Sheet1!$AY$2:$AY$200,A43,Sheet1!$BS$2:$BS$200,"Core",Sheet1!$BD$2:$BD$200,"<>Not measured",Sheet1!$BD$2:$BD$200,"<>") -> 2
A44: Desktop | B44: =COUNTIFS(Sheet1!$AY$2:$AY$200,A44,Sheet1!$BS$2:$BS$200,"Core") -> 4 | C44: =COUNTIFS(Sheet1!$AY$2:$AY$200,A44,Sheet1!$BS$2:$BS$200,"Core",Sheet1!$BB$2:$BB$200,"+") -> 0 | D44: =COUNTIFS(Sheet1!$AY$2:$AY$200,A44,Sheet1!$BS$2:$BS$200,"Core",Sheet1!$BB$2:$BB$200,"<>Not measured",Sheet1!$BB$2:$BB$200,"<>") -> 1 | E44: =COUNTIFS(Sheet1!$AY$2:$AY$200,A44,Sheet1!$BS$2:$BS$200,"Core",Sheet1!$BC$2:$BC$200,"+") -> 3 | F44: =COUNTIFS(Sheet1!$AY$2:$AY$200,A44,Sheet1!$BS$2:$BS$200,"Core",Sheet1!$BC$2:$BC$200,"<>Not measured",Sheet1!$BC$2:$BC$200,"<>") -> 3 | G44: =COUNTIFS(Sheet1!$AY$2:$AY$200,A44,Sheet1!$BS$2:$BS$200,"Core",Sheet1!$BD$2:$BD$200,"+") -> 3 | H44: =COUNTIFS(Sheet1!$AY$2:$AY$200,A44,Sheet1!$BS$2:$BS$200,"Core",Sheet1!$BD$2:$BD$200,"<>Not measured",Sheet1!$BD$2:$BD$200,"<>") -> 3
A45: CAVE / projection | B45: =COUNTIFS(Sheet1!$AY$2:$AY$200,A45,Sheet1!$BS$2:$BS$200,"Core") -> 2 | C45: =COUNTIFS(Sheet1!$AY$2:$AY$200,A45,Sheet1!$BS$2:$BS$200,"Core",Sheet1!$BB$2:$BB$200,"+") -> 2 | D45: =COUNTIFS(Sheet1!$AY$2:$AY$200,A45,Sheet1!$BS$2:$BS$200,"Core",Sheet1!$BB$2:$BB$200,"<>Not measured",Sheet1!$BB$2:$BB$200,"<>") -> 2 | E45: =COUNTIFS(Sheet1!$AY$2:$AY$200,A45,Sheet1!$BS$2:$BS$200,"Core",Sheet1!$BC$2:$BC$200,"+") -> 1 | F45: =COUNTIFS(Sheet1!$AY$2:$AY$200,A45,Sheet1!$BS$2:$BS$200,"Core",Sheet1!$BC$2:$BC$200,"<>Not measured",Sheet1!$BC$2:$BC$200,"<>") -> 1 | G45: =COUNTIFS(Sheet1!$AY$2:$AY$200,A45,Sheet1!$BS$2:$BS$200,"Core",Sheet1!$BD$2:$BD$200,"+") -> 0 | H45: =COUNTIFS(Sheet1!$AY$2:$AY$200,A45,Sheet1!$BS$2:$BS$200,"Core",Sheet1!$BD$2:$BD$200,"<>Not measured",Sheet1!$BD$2:$BD$200,"<>") -> 0
A46: Web-based | B46: =COUNTIFS(Sheet1!$AY$2:$AY$200,A46,Sheet1!$BS$2:$BS$200,"Core") -> 0 | C46: =COUNTIFS(Sheet1!$AY$2:$AY$200,A46,Sheet1!$BS$2:$BS$200,"Core",Sheet1!$BB$2:$BB$200,"+") -> 0 | D46: =COUNTIFS(Sheet1!$AY$2:$AY$200,A46,Sheet1!$BS$2:$BS$200,"Core",Sheet1!$BB$2:$BB$200,"<>Not measured",Sheet1!$BB$2:$BB$200,"<>") -> 0 | E46: =COUNTIFS(Sheet1!$AY$2:$AY$200,A46,Sheet1!$BS$2:$BS$200,"Core",Sheet1!$BC$2:$BC$200,"+") -> 0 | F46: =COUNTIFS(Sheet1!$AY$2:$AY$200,A46,Sheet1!$BS$2:$BS$200,"Core",Sheet1!$BC$2:$BC$200,"<>Not measured",Sheet1!$BC$2:$BC$200,"<>") -> 0 | G46: =COUNTIFS(Sheet1!$AY$2:$AY$200,A46,Sheet1!$BS$2:$BS$200,"Core",Sheet1!$BD$2:$BD$200,"+") -> 0 | H46: =COUNTIFS(Sheet1!$AY$2:$AY$200,A46,Sheet1!$BS$2:$BS$200,"Core",Sheet1!$BD$2:$BD$200,"<>Not measured",Sheet1!$BD$2:$BD$200,"<>") -> 0
A48: RQ6 (Core set). Effects by subject area (ISCED-F) [positive / measured]
A49: subject area (ISCED-F) | B49: Core studies | C49: Engagement + | D49: Engagement measured | E49: Motivation + | F49: Motivation measured | G49: Satisfaction + | H49: Satisfaction measured
A50: Arts & humanities (history/heritage) | B50: =COUNTIFS(Sheet1!$AV$2:$AV$200,A50,Sheet1!$BS$2:$BS$200,"Core") -> 2 | C50: =COUNTIFS(Sheet1!$AV$2:$AV$200,A50,Sheet1!$BS$2:$BS$200,"Core",Sheet1!$BB$2:$BB$200,"+") -> 0 | D50: =COUNTIFS(Sheet1!$AV$2:$AV$200,A50,Sheet1!$BS$2:$BS$200,"Core",Sheet1!$BB$2:$BB$200,"<>Not measured",Sheet1!$BB$2:$BB$200,"<>") -> 0 | E50: =COUNTIFS(Sheet1!$AV$2:$AV$200,A50,Sheet1!$BS$2:$BS$200,"Core",Sheet1!$BC$2:$BC$200,"+") -> 1 | F50: =COUNTIFS(Sheet1!$AV$2:$AV$200,A50,Sheet1!$BS$2:$BS$200,"Core",Sheet1!$BC$2:$BC$200,"<>Not measured",Sheet1!$BC$2:$BC$200,"<>") -> 1 | G50: =COUNTIFS(Sheet1!$AV$2:$AV$200,A50,Sheet1!$BS$2:$BS$200,"Core",Sheet1!$BD$2:$BD$200,"+") -> 2 | H50: =COUNTIFS(Sheet1!$AV$2:$AV$200,A50,Sheet1!$BS$2:$BS$200,"Core",Sheet1!$BD$2:$BD$200,"<>Not measured",Sheet1!$BD$2:$BD$200,"<>") -> 2
A51: Arts & humanities (languages) | B51: =COUNTIFS(Sheet1!$AV$2:$AV$200,A51,Sheet1!$BS$2:$BS$200,"Core") -> 1 | C51: =COUNTIFS(Sheet1!$AV$2:$AV$200,A51,Sheet1!$BS$2:$BS$200,"Core",Sheet1!$BB$2:$BB$200,"+") -> 0 | D51: =COUNTIFS(Sheet1!$AV$2:$AV$200,A51,Sheet1!$BS$2:$BS$200,"Core",Sheet1!$BB$2:$BB$200,"<>Not measured",Sheet1!$BB$2:$BB$200,"<>") -> 0 | E51: =COUNTIFS(Sheet1!$AV$2:$AV$200,A51,Sheet1!$BS$2:$BS$200,"Core",Sheet1!$BC$2:$BC$200,"+") -> 1 | F51: =COUNTIFS(Sheet1!$AV$2:$AV$200,A51,Sheet1!$BS$2:$BS$200,"Core",Sheet1!$BC$2:$BC$200,"<>Not measured",Sheet1!$BC$2:$BC$200,"<>") -> 1 | G51: =COUNTIFS(Sheet1!$AV$2:$AV$200,A51,Sheet1!$BS$2:$BS$200,"Core",Sheet1!$BD$2:$BD$200,"+") -> 0 | H51: =COUNTIFS(Sheet1!$AV$2:$AV$200,A51,Sheet1!$BS$2:$BS$200,"Core",Sheet1!$BD$2:$BD$200,"<>Not measured",Sheet1!$BD$2:$BD$200,"<>") -> 0
A52: Arts & humanities (religion) | B52: =COUNTIFS(Sheet1!$AV$2:$AV$200,A52,Sheet1!$BS$2:$BS$200,"Core") -> 1 | C52: =COUNTIFS(Sheet1!$AV$2:$AV$200,A52,Sheet1!$BS$2:$BS$200,"Core",Sheet1!$BB$2:$BB$200,"+") -> 0 | D52: =COUNTIFS(Sheet1!$AV$2:$AV$200,A52,Sheet1!$BS$2:$BS$200,"Core",Sheet1!$BB$2:$BB$200,"<>Not measured",Sheet1!$BB$2:$BB$200,"<>") -> 0 | E52: =COUNTIFS(Sheet1!$AV$2:$AV$200,A52,Sheet1!$BS$2:$BS$200,"Core",Sheet1!$BC$2:$BC$200,"+") -> 0 | F52: =COUNTIFS(Sheet1!$AV$2:$AV$200,A52,Sheet1!$BS$2:$BS$200,"Core",Sheet1!$BC$2:$BC$200,"<>Not measured",Sheet1!$BC$2:$BC$200,"<>") -> 0 | G52: =COUNTIFS(Sheet1!$AV$2:$AV$200,A52,Sheet1!$BS$2:$BS$200,"Core",Sheet1!$BD$2:$BD$200,"+") -> 1 | H52: =COUNTIFS(Sheet1!$AV$2:$AV$200,A52,Sheet1!$BS$2:$BS$200,"Core",Sheet1!$BD$2:$BD$200,"<>Not measured",Sheet1!$BD$2:$BD$200,"<>") -> 1
A53: Generic / multi-subject | B53: =COUNTIFS(Sheet1!$AV$2:$AV$200,A53,Sheet1!$BS$2:$BS$200,"Core") -> 3 | C53: =COUNTIFS(Sheet1!$AV$2:$AV$200,A53,Sheet1!$BS$2:$BS$200,"Core",Sheet1!$BB$2:$BB$200,"+") -> 0 | D53: =COUNTIFS(Sheet1!$AV$2:$AV$200,A53,Sheet1!$BS$2:$BS$200,"Core",Sheet1!$BB$2:$BB$200,"<>Not measured",Sheet1!$BB$2:$BB$200,"<>") -> 1 | E53: =COUNTIFS(Sheet1!$AV$2:$AV$200,A53,Sheet1!$BS$2:$BS$200,"Core",Sheet1!$BC$2:$BC$200,"+") -> 2 | F53: =COUNTIFS(Sheet1!$AV$2:$AV$200,A53,Sheet1!$BS$2:$BS$200,"Core",Sheet1!$BC$2:$BC$200,"<>Not measured",Sheet1!$BC$2:$BC$200,"<>") -> 2 | G53: =COUNTIFS(Sheet1!$AV$2:$AV$200,A53,Sheet1!$BS$2:$BS$200,"Core",Sheet1!$BD$2:$BD$200,"+") -> 3 | H53: =COUNTIFS(Sheet1!$AV$2:$AV$200,A53,Sheet1!$BS$2:$BS$200,"Core",Sheet1!$BD$2:$BD$200,"<>Not measured",Sheet1!$BD$2:$BD$200,"<>") -> 3
A54: Generic programmes (literacy) | B54: =COUNTIFS(Sheet1!$AV$2:$AV$200,A54,Sheet1!$BS$2:$BS$200,"Core") -> 1 | C54: =COUNTIFS(Sheet1!$AV$2:$AV$200,A54,Sheet1!$BS$2:$BS$200,"Core",Sheet1!$BB$2:$BB$200,"+") -> 1 | D54: =COUNTIFS(Sheet1!$AV$2:$AV$200,A54,Sheet1!$BS$2:$BS$200,"Core",Sheet1!$BB$2:$BB$200,"<>Not measured",Sheet1!$BB$2:$BB$200,"<>") -> 1 | E54: =COUNTIFS(Sheet1!$AV$2:$AV$200,A54,Sheet1!$BS$2:$BS$200,"Core",Sheet1!$BC$2:$BC$200,"+") -> 0 | F54: =COUNTIFS(Sheet1!$AV$2:$AV$200,A54,Sheet1!$BS$2:$BS$200,"Core",Sheet1!$BC$2:$BC$200,"<>Not measured",Sheet1!$BC$2:$BC$200,"<>") -> 0 | G54: =COUNTIFS(Sheet1!$AV$2:$AV$200,A54,Sheet1!$BS$2:$BS$200,"Core",Sheet1!$BD$2:$BD$200,"+") -> 0 | H54: =COUNTIFS(Sheet1!$AV$2:$AV$200,A54,Sheet1!$BS$2:$BS$200,"Core",Sheet1!$BD$2:$BD$200,"<>Not measured",Sheet1!$BD$2:$BD$200,"<>") -> 0
A55: ICT | B55: =COUNTIFS(Sheet1!$AV$2:$AV$200,A55,Sheet1!$BS$2:$BS$200,"Core") -> 2 | C55: =COUNTIFS(Sheet1!$AV$2:$AV$200,A55,Sheet1!$BS$2:$BS$200,"Core",Sheet1!$BB$2:$BB$200,"+") -> 0 | D55: =COUNTIFS(Sheet1!$AV$2:$AV$200,A55,Sheet1!$BS$2:$BS$200,"Core",Sheet1!$BB$2:$BB$200,"<>Not measured",Sheet1!$BB$2:$BB$200,"<>") -> 0 | E55: =COUNTIFS(Sheet1!$AV$2:$AV$200,A55,Sheet1!$BS$2:$BS$200,"Core",Sheet1!$BC$2:$BC$200,"+") -> 1 | F55: =COUNTIFS(Sheet1!$AV$2:$AV$200,A55,Sheet1!$BS$2:$BS$200,"Core",Sheet1!$BC$2:$BC$200,"<>Not measured",Sheet1!$BC$2:$BC$200,"<>") -> 1 | G55: =COUNTIFS(Sheet1!$AV$2:$AV$200,A55,Sheet1!$BS$2:$BS$200,"Core",Sheet1!$BD$2:$BD$200,"+") -> 2 | H55: =COUNTIFS(Sheet1!$AV$2:$AV$200,A55,Sheet1!$BS$2:$BS$200,"Core",Sheet1!$BD$2:$BD$200,"<>Not measured",Sheet1!$BD$2:$BD$200,"<>") -> 2
A56: Natural sciences, mathematics & statistics | B56: =COUNTIFS(Sheet1!$AV$2:$AV$200,A56,Sheet1!$BS$2:$BS$200,"Core") -> 10 | C56: =COUNTIFS(Sheet1!$AV$2:$AV$200,A56,Sheet1!$BS$2:$BS$200,"Core",Sheet1!$BB$2:$BB$200,"+") -> 5 | D56: =COUNTIFS(Sheet1!$AV$2:$AV$200,A56,Sheet1!$BS$2:$BS$200,"Core",Sheet1!$BB$2:$BB$200,"<>Not measured",Sheet1!$BB$2:$BB$200,"<>") -> 6 | E56: =COUNTIFS(Sheet1!$AV$2:$AV$200,A56,Sheet1!$BS$2:$BS$200,"Core",Sheet1!$BC$2:$BC$200,"+") -> 9 | F56: =COUNTIFS(Sheet1!$AV$2:$AV$200,A56,Sheet1!$BS$2:$BS$200,"Core",Sheet1!$BC$2:$BC$200,"<>Not measured",Sheet1!$BC$2:$BC$200,"<>") -> 9 | G56: =COUNTIFS(Sheet1!$AV$2:$AV$200,A56,Sheet1!$BS$2:$BS$200,"Core",Sheet1!$BD$2:$BD$200,"+") -> 4 | H56: =COUNTIFS(Sheet1!$AV$2:$AV$200,A56,Sheet1!$BS$2:$BS$200,"Core",Sheet1!$BD$2:$BD$200,"<>Not measured",Sheet1!$BD$2:$BD$200,"<>") -> 5
A57: Social sciences, journalism & information | B57: =COUNTIFS(Sheet1!$AV$2:$AV$200,A57,Sheet1!$BS$2:$BS$200,"Core") -> 1 | C57: =COUNTIFS(Sheet1!$AV$2:$AV$200,A57,Sheet1!$BS$2:$BS$200,"Core",Sheet1!$BB$2:$BB$200,"+") -> 1 | D57: =COUNTIFS(Sheet1!$AV$2:$AV$200,A57,Sheet1!$BS$2:$BS$200,"Core",Sheet1!$BB$2:$BB$200,"<>Not measured",Sheet1!$BB$2:$BB$200,"<>") -> 1 | E57: =COUNTIFS(Sheet1!$AV$2:$AV$200,A57,Sheet1!$BS$2:$BS$200,"Core",Sheet1!$BC$2:$BC$200,"+") -> 1 | F57: =COUNTIFS(Sheet1!$AV$2:$AV$200,A57,Sheet1!$BS$2:$BS$200,"Core",Sheet1!$BC$2:$BC$200,"<>Not measured",Sheet1!$BC$2:$BC$200,"<>") -> 1 | G57: =COUNTIFS(Sheet1!$AV$2:$AV$200,A57,Sheet1!$BS$2:$BS$200,"Core",Sheet1!$BD$2:$BD$200,"+") -> 1 | H57: =COUNTIFS(Sheet1!$AV$2:$AV$200,A57,Sheet1!$BS$2:$BS$200,"Core",Sheet1!$BD$2:$BD$200,"<>Not measured",Sheet1!$BD$2:$BD$200,"<>") -> 1
A59: Table 5a. RQ5 – Studies by region
A60: Category | B60: Mapping corpus (n = 44) | C60: Core set (n = 21)
A61: Asia | B61: =(COUNTIFS(Sheet1!$AS$2:$AS$200,"Asia")-COUNTIFS(Sheet1!$AS$2:$AS$200,"Asia",Sheet1!$BV$2:$BV$200,"*RETRACTED*")) -> 22 | C61: =COUNTIFS(Sheet1!$AS$2:$AS$200,"Asia",Sheet1!$BS$2:$BS$200,"Core") -> 11
A62: Europe | B62: =(COUNTIFS(Sheet1!$AS$2:$AS$200,"Europe")-COUNTIFS(Sheet1!$AS$2:$AS$200,"Europe",Sheet1!$BV$2:$BV$200,"*RETRACTED*")) -> 8 | C62: =COUNTIFS(Sheet1!$AS$2:$AS$200,"Europe",Sheet1!$BS$2:$BS$200,"Core") -> 3
A63: North America | B63: =(COUNTIFS(Sheet1!$AS$2:$AS$200,"North America")-COUNTIFS(Sheet1!$AS$2:$AS$200,"North America",Sheet1!$BV$2:$BV$200,"*RETRACTED*")) -> 10 | C63: =COUNTIFS(Sheet1!$AS$2:$AS$200,"North America",Sheet1!$BS$2:$BS$200,"Core") -> 4
A64: South America | B64: =(COUNTIFS(Sheet1!$AS$2:$AS$200,"South America")-COUNTIFS(Sheet1!$AS$2:$AS$200,"South America",Sheet1!$BV$2:$BV$200,"*RETRACTED*")) -> 2 | C64: =COUNTIFS(Sheet1!$AS$2:$AS$200,"South America",Sheet1!$BS$2:$BS$200,"Core") -> 1
A65: Africa | B65: =(COUNTIFS(Sheet1!$AS$2:$AS$200,"Africa")-COUNTIFS(Sheet1!$AS$2:$AS$200,"Africa",Sheet1!$BV$2:$BV$200,"*RETRACTED*")) -> 1 | C65: =COUNTIFS(Sheet1!$AS$2:$AS$200,"Africa",Sheet1!$BS$2:$BS$200,"Core") -> 1
A66: Oceania | B66: =(COUNTIFS(Sheet1!$AS$2:$AS$200,"Oceania")-COUNTIFS(Sheet1!$AS$2:$AS$200,"Oceania",Sheet1!$BV$2:$BV$200,"*RETRACTED*")) -> 1 | C66: =COUNTIFS(Sheet1!$AS$2:$AS$200,"Oceania",Sheet1!$BS$2:$BS$200,"Core") -> 1
A67: Total | B67: =SUM(B61:B66) -> 44 | C67: =SUM(C61:C66) -> 21
A69: Table 5b. RQ5 – Studies by country
A70: Category | B70: Mapping corpus (n = 44) | C70: Core set (n = 21)
A71: USA | B71: =(COUNTIFS(Sheet1!$AR$2:$AR$200,"USA")-COUNTIFS(Sheet1!$AR$2:$AR$200,"USA",Sheet1!$BV$2:$BV$200,"*RETRACTED*")) -> 7 | C71: =COUNTIFS(Sheet1!$AR$2:$AR$200,"USA",Sheet1!$BS$2:$BS$200,"Core") -> 3
A72: China | B72: =(COUNTIFS(Sheet1!$AR$2:$AR$200,"China")-COUNTIFS(Sheet1!$AR$2:$AR$200,"China",Sheet1!$BV$2:$BV$200,"*RETRACTED*")) -> 4 | C72: =COUNTIFS(Sheet1!$AR$2:$AR$200,"China",Sheet1!$BS$2:$BS$200,"Core") -> 1
A73: Indonesia | B73: =(COUNTIFS(Sheet1!$AR$2:$AR$200,"Indonesia")-COUNTIFS(Sheet1!$AR$2:$AR$200,"Indonesia",Sheet1!$BV$2:$BV$200,"*RETRACTED*")) -> 4 | C73: =COUNTIFS(Sheet1!$AR$2:$AR$200,"Indonesia",Sheet1!$BS$2:$BS$200,"Core") -> 3
A74: Malaysia | B74: =(COUNTIFS(Sheet1!$AR$2:$AR$200,"Malaysia")-COUNTIFS(Sheet1!$AR$2:$AR$200,"Malaysia",Sheet1!$BV$2:$BV$200,"*RETRACTED*")) -> 4 | C74: =COUNTIFS(Sheet1!$AR$2:$AR$200,"Malaysia",Sheet1!$BS$2:$BS$200,"Core") -> 2
A75: India | B75: =(COUNTIFS(Sheet1!$AR$2:$AR$200,"India")-COUNTIFS(Sheet1!$AR$2:$AR$200,"India",Sheet1!$BV$2:$BV$200,"*RETRACTED*")) -> 3 | C75: =COUNTIFS(Sheet1!$AR$2:$AR$200,"India",Sheet1!$BS$2:$BS$200,"Core") -> 1
A76: Canada | B76: =(COUNTIFS(Sheet1!$AR$2:$AR$200,"Canada")-COUNTIFS(Sheet1!$AR$2:$AR$200,"Canada",Sheet1!$BV$2:$BV$200,"*RETRACTED*")) -> 2 | C76: =COUNTIFS(Sheet1!$AR$2:$AR$200,"Canada",Sheet1!$BS$2:$BS$200,"Core") -> 0
A77: Italy | B77: =(COUNTIFS(Sheet1!$AR$2:$AR$200,"Italy")-COUNTIFS(Sheet1!$AR$2:$AR$200,"Italy",Sheet1!$BV$2:$BV$200,"*RETRACTED*")) -> 2 | C77: =COUNTIFS(Sheet1!$AR$2:$AR$200,"Italy",Sheet1!$BS$2:$BS$200,"Core") -> 1
A78: Taiwan | B78: =(COUNTIFS(Sheet1!$AR$2:$AR$200,"Taiwan")-COUNTIFS(Sheet1!$AR$2:$AR$200,"Taiwan",Sheet1!$BV$2:$BV$200,"*RETRACTED*")) -> 2 | C78: =COUNTIFS(Sheet1!$AR$2:$AR$200,"Taiwan",Sheet1!$BS$2:$BS$200,"Core") -> 2
A79: Argentina | B79: =(COUNTIFS(Sheet1!$AR$2:$AR$200,"Argentina")-COUNTIFS(Sheet1!$AR$2:$AR$200,"Argentina",Sheet1!$BV$2:$BV$200,"*RETRACTED*")) -> 1 | C79: =COUNTIFS(Sheet1!$AR$2:$AR$200,"Argentina",Sheet1!$BS$2:$BS$200,"Core") -> 1
A80: Australia | B80: =(COUNTIFS(Sheet1!$AR$2:$AR$200,"Australia")-COUNTIFS(Sheet1!$AR$2:$AR$200,"Australia",Sheet1!$BV$2:$BV$200,"*RETRACTED*")) -> 1 | C80: =COUNTIFS(Sheet1!$AR$2:$AR$200,"Australia",Sheet1!$BS$2:$BS$200,"Core") -> 1
A81: Belgium | B81: =(COUNTIFS(Sheet1!$AR$2:$AR$200,"Belgium")-COUNTIFS(Sheet1!$AR$2:$AR$200,"Belgium",Sheet1!$BV$2:$BV$200,"*RETRACTED*")) -> 1 | C81: =COUNTIFS(Sheet1!$AR$2:$AR$200,"Belgium",Sheet1!$BS$2:$BS$200,"Core") -> 0
A82: Colombia | B82: =(COUNTIFS(Sheet1!$AR$2:$AR$200,"Colombia")-COUNTIFS(Sheet1!$AR$2:$AR$200,"Colombia",Sheet1!$BV$2:$BV$200,"*RETRACTED*")) -> 1 | C82: =COUNTIFS(Sheet1!$AR$2:$AR$200,"Colombia",Sheet1!$BS$2:$BS$200,"Core") -> 0
A83: France | B83: =(COUNTIFS(Sheet1!$AR$2:$AR$200,"France")-COUNTIFS(Sheet1!$AR$2:$AR$200,"France",Sheet1!$BV$2:$BV$200,"*RETRACTED*")) -> 1 | C83: =COUNTIFS(Sheet1!$AR$2:$AR$200,"France",Sheet1!$BS$2:$BS$200,"Core") -> 1
A84: Kazakhstan | B84: =(COUNTIFS(Sheet1!$AR$2:$AR$200,"Kazakhstan")-COUNTIFS(Sheet1!$AR$2:$AR$200,"Kazakhstan",Sheet1!$BV$2:$BV$200,"*RETRACTED*")) -> 1 | C84: =COUNTIFS(Sheet1!$AR$2:$AR$200,"Kazakhstan",Sheet1!$BS$2:$BS$200,"Core") -> 1
A85: Mexico | B85: =(COUNTIFS(Sheet1!$AR$2:$AR$200,"Mexico")-COUNTIFS(Sheet1!$AR$2:$AR$200,"Mexico",Sheet1!$BV$2:$BV$200,"*RETRACTED*")) -> 1 | C85: =COUNTIFS(Sheet1!$AR$2:$AR$200,"Mexico",Sheet1!$BS$2:$BS$200,"Core") -> 1
A86: Norway | B86: =(COUNTIFS(Sheet1!$AR$2:$AR$200,"Norway")-COUNTIFS(Sheet1!$AR$2:$AR$200,"Norway",Sheet1!$BV$2:$BV$200,"*RETRACTED*")) -> 1 | C86: =COUNTIFS(Sheet1!$AR$2:$AR$200,"Norway",Sheet1!$BS$2:$BS$200,"Core") -> 0
A87: Poland | B87: =(COUNTIFS(Sheet1!$AR$2:$AR$200,"Poland")-COUNTIFS(Sheet1!$AR$2:$AR$200,"Poland",Sheet1!$BV$2:$BV$200,"*RETRACTED*")) -> 1 | C87: =COUNTIFS(Sheet1!$AR$2:$AR$200,"Poland",Sheet1!$BS$2:$BS$200,"Core") -> 0
A88: Romania | B88: =(COUNTIFS(Sheet1!$AR$2:$AR$200,"Romania")-COUNTIFS(Sheet1!$AR$2:$AR$200,"Romania",Sheet1!$BV$2:$BV$200,"*RETRACTED*")) -> 1 | C88: =COUNTIFS(Sheet1!$AR$2:$AR$200,"Romania",Sheet1!$BS$2:$BS$200,"Core") -> 0
A89: South Africa | B89: =(COUNTIFS(Sheet1!$AR$2:$AR$200,"South Africa")-COUNTIFS(Sheet1!$AR$2:$AR$200,"South Africa",Sheet1!$BV$2:$BV$200,"*RETRACTED*")) -> 1 | C89: =COUNTIFS(Sheet1!$AR$2:$AR$200,"South Africa",Sheet1!$BS$2:$BS$200,"Core") -> 1
A90: Spain | B90: =(COUNTIFS(Sheet1!$AR$2:$AR$200,"Spain")-COUNTIFS(Sheet1!$AR$2:$AR$200,"Spain",Sheet1!$BV$2:$BV$200,"*RETRACTED*")) -> 1 | C90: =COUNTIFS(Sheet1!$AR$2:$AR$200,"Spain",Sheet1!$BS$2:$BS$200,"Core") -> 1
A91: Thailand | B91: =(COUNTIFS(Sheet1!$AR$2:$AR$200,"Thailand")-COUNTIFS(Sheet1!$AR$2:$AR$200,"Thailand",Sheet1!$BV$2:$BV$200,"*RETRACTED*")) -> 1 | C91: =COUNTIFS(Sheet1!$AR$2:$AR$200,"Thailand",Sheet1!$BS$2:$BS$200,"Core") -> 0
A92: Turkey | B92: =(COUNTIFS(Sheet1!$AR$2:$AR$200,"Turkey")-COUNTIFS(Sheet1!$AR$2:$AR$200,"Turkey",Sheet1!$BV$2:$BV$200,"*RETRACTED*")) -> 1 | C92: =COUNTIFS(Sheet1!$AR$2:$AR$200,"Turkey",Sheet1!$BS$2:$BS$200,"Core") -> 0
A93: United Arab Emirates | B93: =(COUNTIFS(Sheet1!$AR$2:$AR$200,"United Arab Emirates")-COUNTIFS(Sheet1!$AR$2:$AR$200,"United Arab Emirates",Sheet1!$BV$2:$BV$200,"*RETRACTED*")) -> 1 | C93: =COUNTIFS(Sheet1!$AR$2:$AR$200,"United Arab Emirates",Sheet1!$BS$2:$BS$200,"Core") -> 1
A94: Vietnam | B94: =(COUNTIFS(Sheet1!$AR$2:$AR$200,"Vietnam")-COUNTIFS(Sheet1!$AR$2:$AR$200,"Vietnam",Sheet1!$BV$2:$BV$200,"*RETRACTED*")) -> 1 | C94: =COUNTIFS(Sheet1!$AR$2:$AR$200,"Vietnam",Sheet1!$BS$2:$BS$200,"Core") -> 0
A95: Total | B95: =SUM(B71:B94) -> 44 | C95: =SUM(C71:C94) -> 21
A97: Table 5c. RQ5 – Studies by education level (ISCED 2011)
A98: Category | B98: Mapping corpus (n = 44) | C98: Core set (n = 21)
A99: Pre-primary | B99: =(COUNTIFS(Sheet1!$AT$2:$AT$200,"Pre-primary")-COUNTIFS(Sheet1!$AT$2:$AT$200,"Pre-primary",Sheet1!$BV$2:$BV$200,"*RETRACTED*")) -> 1 | C99: =COUNTIFS(Sheet1!$AT$2:$AT$200,"Pre-primary",Sheet1!$BS$2:$BS$200,"Core") -> 0
A100: Primary | B100: =(COUNTIFS(Sheet1!$AT$2:$AT$200,"Primary")-COUNTIFS(Sheet1!$AT$2:$AT$200,"Primary",Sheet1!$BV$2:$BV$200,"*RETRACTED*")) -> 4 | C100: =COUNTIFS(Sheet1!$AT$2:$AT$200,"Primary",Sheet1!$BS$2:$BS$200,"Core") -> 4
A101: Lower secondary | B101: =(COUNTIFS(Sheet1!$AT$2:$AT$200,"Lower secondary")-COUNTIFS(Sheet1!$AT$2:$AT$200,"Lower secondary",Sheet1!$BV$2:$BV$200,"*RETRACTED*")) -> 5 | C101: =COUNTIFS(Sheet1!$AT$2:$AT$200,"Lower secondary",Sheet1!$BS$2:$BS$200,"Core") -> 4
A102: Upper secondary | B102: =(COUNTIFS(Sheet1!$AT$2:$AT$200,"Upper secondary")-COUNTIFS(Sheet1!$AT$2:$AT$200,"Upper secondary",Sheet1!$BV$2:$BV$200,"*RETRACTED*")) -> 3 | C102: =COUNTIFS(Sheet1!$AT$2:$AT$200,"Upper secondary",Sheet1!$BS$2:$BS$200,"Core") -> 2
A103: Secondary (unspecified) | B103: =(COUNTIFS(Sheet1!$AT$2:$AT$200,"Secondary (unspecified)")-COUNTIFS(Sheet1!$AT$2:$AT$200,"Secondary (unspecified)",Sheet1!$BV$2:$BV$200,"*RETRACTED*")) -> 3 | C103: =COUNTIFS(Sheet1!$AT$2:$AT$200,"Secondary (unspecified)",Sheet1!$BS$2:$BS$200,"Core") -> 3
A104: Mixed K-12 | B104: =(COUNTIFS(Sheet1!$AT$2:$AT$200,"Mixed K-12")-COUNTIFS(Sheet1!$AT$2:$AT$200,"Mixed K-12",Sheet1!$BV$2:$BV$200,"*RETRACTED*")) -> 4 | C104: =COUNTIFS(Sheet1!$AT$2:$AT$200,"Mixed K-12",Sheet1!$BS$2:$BS$200,"Core") -> 4
A105: Mixed (school-age + adults) | B105: =(COUNTIFS(Sheet1!$AT$2:$AT$200,"Mixed (school-age + adults)")-COUNTIFS(Sheet1!$AT$2:$AT$200,"Mixed (school-age + adults)",Sheet1!$BV$2:$BV$200,"*RETRACTED*")) -> 1 | C105: =COUNTIFS(Sheet1!$AT$2:$AT$200,"Mixed (school-age + adults)",Sheet1!$BS$2:$BS$200,"Core") -> 1
A106: Mixed (secondary + post-secondary) | B106: =(COUNTIFS(Sheet1!$AT$2:$AT$200,"Mixed (secondary + post-secondary)")-COUNTIFS(Sheet1!$AT$2:$AT$200,"Mixed (secondary + post-secondary)",Sheet1!$BV$2:$BV$200,"*RETRACTED*")) -> 4 | C106: =COUNTIFS(Sheet1!$AT$2:$AT$200,"Mixed (secondary + post-secondary)",Sheet1!$BS$2:$BS$200,"Core") -> 2
A107: Higher education | B107: =(COUNTIFS(Sheet1!$AT$2:$AT$200,"Higher education")-COUNTIFS(Sheet1!$AT$2:$AT$200,"Higher education",Sheet1!$BV$2:$BV$200,"*RETRACTED*")) -> 10 | C107: =COUNTIFS(Sheet1!$AT$2:$AT$200,"Higher education",Sheet1!$BS$2:$BS$200,"Core") -> 0
A108: Informal / general public | B108: =(COUNTIFS(Sheet1!$AT$2:$AT$200,"Informal / general public")-COUNTIFS(Sheet1!$AT$2:$AT$200,"Informal / general public",Sheet1!$BV$2:$BV$200,"*RETRACTED*")) -> 3 | C108: =COUNTIFS(Sheet1!$AT$2:$AT$200,"Informal / general public",Sheet1!$BS$2:$BS$200,"Core") -> 0
A109: Not reported | B109: =(COUNTIFS(Sheet1!$AT$2:$AT$200,"Not reported")-COUNTIFS(Sheet1!$AT$2:$AT$200,"Not reported",Sheet1!$BV$2:$BV$200,"*RETRACTED*")) -> 6 | C109: =COUNTIFS(Sheet1!$AT$2:$AT$200,"Not reported",Sheet1!$BS$2:$BS$200,"Core") -> 1
...

Sheet Charts
A1: Figures for RQ5–RQ7 (native Excel charts linked to the Evidence Map sheet – they update automatically)

Sheet MMAT Appraisal
A1: New num | B1: Title | C1: MMAT category | D1: S1 Clear research questions? | E1: S2 Data address the RQs? | F1: Criterion 1 | G1: Criterion 2 | H1: Criterion 3 | I1: Criterion 4 | J1: Criterion 5 | K1: Score (Yes count) | L1: Rationale
A2: 1 | B2: Transforming Secondary School Chemistry Learning with Virtual Reality | C2: Quantitative descriptive | D2: Yes | E2: Yes | F2: Yes | G2: Can't tell | H2: No | I2: Can't tell | J2: Yes | K2: =IF(OR(D2<>"Yes",E2<>"Yes"),"",COUNTIF(F2:J2,"Yes")) -> 2 | L2: 4.1 students from one chemistry class = target group; 4.2 single class, convenience; 4.3 SUS items modified without re-validation; 4.4 response rate not reported; 4.5 descriptive SUS scoring appropriate.
A3: 2 | B3: Development of an immersive virtual reality system for learning about plants in primary education: evaluation of teachers’ perceptions and learners’ flow experiences and learning attitudes | C3: Quantitative descriptive | D3: Yes | E3: Yes | F3: Yes | G3: Can't tell | H3: Yes | I3: Can't tell | J3: Yes | K3: =IF(OR(D3<>"Yes",E3<>"Yes"),"",COUNTIF(F3:J3,"Yes")) -> 3 | L3: Student survey component appraised. 4.1 grade-5 pupils = target; 4.2 recruitment/school not described; 4.3 adapted validated scales with α reported (control α = .54 low); 4.4 completion not reported; 4.5 RM-ANOVA + regression appropriate.
A4: 3 | B4: PlutoAR: a scalable marker-based augmented reality application for interactive and inclusive education | C4: Quantitative descriptive | D4: Yes | E4: Yes | F4: No | G4: No | H4: Can't tell | I4: Can't tell | J4: Yes | K4: =IF(OR(D4<>"Yes",E4<>"Yes"),"",COUNTIF(F4:J4,"Yes")) -> 1 | L4: 4.1 convenience sample at school visits and public events, ages 10–45 pooled; 4.2 not representative of K-10 target; 4.3 SUS standard but satisfaction is single item; 4.4 not reported; 4.5 descriptive appropriate.
A5: 4 | B5: Inclusive Learning through Immersive Virtual Reality and Semantic Embodied Conversational Agent: A case study in children with autism; [Aprendizaje Inclusivo mediante Realidad Virtual Inmersiva y Agente Conversacional Semántico Encarnado: Un caso de estudio en niños con autismo] | C5: Quantitative descriptive | D5: Yes | E5: Yes | F5: Yes | G5: No | H5: Can't tell | I5: Can't tell | J5: Yes | K5: =IF(OR(D5<>"Yes",E5<>"Yes"),"",COUNTIF(F5:J5,"Yes")) -> 2 | L5: 4.1 children with autism = target; 4.2 snowball via one parent network, n = 10; 4.3 adapted SAM, parent-administered test without baseline; 4.4 not reported; 4.5 descriptive appropriate.
A6: 5 | B6: Evaluation User Acceptance of Mobile Virtual Reality Application for English Learning | C6: Quantitative descriptive | D6: Yes | E6: Yes | F6: Yes | G6: Can't tell | H6: Can't tell | I6: Can't tell | J6: Yes | K6: =IF(OR(D6<>"Yes",E6<>"Yes"),"",COUNTIF(F6:J6,"Yes")) -> 2 | L6: 4.1 high-school English learners = target; 4.2 sampling not described; 4.3 adopted TAM items, enjoyment/motivation single items, no reliability; 4.4 not reported; 4.5 descriptive appropriate.
A7: 6 | B7: Implementation of Prototype Environment of Virtual Reality Platform for Virtual Lab (Use case of ESL) | C7: Not appraisable (no empirical learner study) | D7: No | E7: No | K7: =IF(OR(D7<>"Yes",E7<>"Yes"),"",COUNTIF(F7:J7,"Yes")) | L7: Technical latency test only; no learner data.
A8: 7 | B8: Comparison and enhancement of VR water cycle guide applications | C8: Quantitative descriptive | D8: Yes | E8: Yes | F8: Can't tell | G8: Can't tell | H8: No | I8: Can't tell | J8: Can't tell | K8: =IF(OR(D8<>"Yes",E8<>"Yes"),"",COUNTIF(F8:J8,"Yes")) -> 0 | L8: 4.1/4.2 'multiple schools', no sampling or N; 4.3 author-made yes/no items; 4.4 not reported; 4.5 only bar-chart percentages without N.
A9: 8 | B9: User Interface for an Immersive Virtual Reality Greenhouse for Training Precision Agriculture | C9: Not appraisable (no empirical learner study) | D9: Yes | E9: No | K9: =IF(OR(D9<>"Yes",E9<>"Yes"),"",COUNTIF(F9:J9,"Yes")) | L9: Design paper; no user evaluation.
A10: 9 | B10: Work-in-Progress-GeoForge: Integrating Virtual Reality and a Personalized Website to Foster Collaboration in Middle School Science | C10: Qualitative | D10: Yes | E10: Yes | F10: Yes | G10: Yes | H10: Can't tell | I10: Yes | J10: Yes | K10: =IF(OR(D10<>"Yes",E10<>"Yes"),"",COUNTIF(F10:J10,"Yes")) -> 4 | L10: Engagement evidence from teacher interviews (qualitative component appraised). 1.3 coded by a single rater; quotes support interpretation.
A11: 10 | B11: An integrated VR/AR framework for user-centric interactive experience of cultural heritage: The ArkaeVision project | C11: Quantitative descriptive | D11: Yes | E11: Yes | F11: Yes | G11: Can't tell | H11: No | I11: Yes | J11: Yes | K11: =IF(OR(D11<>"Yes",E11<>"Yes"),"",COUNTIF(F11:J11,"Yes")) -> 3 | L11: 4.1 museum visitors = target public; 4.2 opportunistic visitors, mostly adults; 4.3 author-made questionnaire, no psychometrics; 4.4 few refusals, complete forms; 4.5 descriptive %.
A12: 11 | B12: Development of practical tasks in physics with elements of augmented reality for secondary educational institutions | C12: Quantitative descriptive | D12: Yes | E12: Yes | F12: Yes | G12: Can't tell | H12: No | I12: Can't tell | J12: No | K12: =IF(OR(D12<>"Yes",E12<>"Yes"),"",COUNTIF(F12:J12,"Yes")) -> 1 | L12: 4.3 single question; 4.5 reported percentages impossible for n = 20.
A13: 12 | B13: Virtual Reality in Music Education: A Qualitative User Study of HarmosphereVR | C13: Qualitative | D13: Yes | E13: Yes | F13: Yes | G13: Can't tell | H13: Can't tell | I13: Yes | J13: Can't tell | K13: =IF(OR(D13<>"Yes",E13<>"Yes"),"",COUNTIF(F13:J13,"Yes")) -> 2 | L13: Observation notes, reaction cards and interviews; analysis ('thematic clusters') only briefly described; quotes support claims; snowball sample of 6.
A14: 13 | B14: Research on the Impact of Interactive Experience and Perceived Value on User Satisfaction in VR Education | C14: Quantitative descriptive | D14: Yes | E14: Yes | F14: Yes | G14: Yes | H14: Yes | I14: Can't tell | J14: No | K14: =IF(OR(D14<>"Yes",E14<>"Yes"),"",COUNTIF(F14:J14,"Yes")) -> 3 | L14: 4.2 random selection from 17 classes; 4.3 α and CFA reported; 4.4 distributed/collected numbers inconsistent; 4.5 hypothesised paths never reported.
A15: 14 | B15: Usability Study of GenAI for English Learning in VR | C15: Quantitative descriptive | D15: Yes | E15: Yes | F15: Yes | G15: No | H15: Yes | I15: Can't tell | J15: Yes | K15: =IF(OR(D15<>"Yes",E15<>"Yes"),"",COUNTIF(F15:J15,"Yes")) -> 3 | L15: 4.2 purposive n = 7; 4.3 standard SUS; 4.5 SUS scoring appropriate.
A16: 15 | B16: StellarScape: Explore the Solar System with AR Cube | C16: Not appraisable (no empirical learner study) | D16: Yes | E16: No | K16: =IF(OR(D16<>"Yes",E16<>"Yes"),"",COUNTIF(F16:J16,"Yes")) | L16: Development paper; no evaluation.
A17: 16 | B17: CuriosityXR: Context-aware Education Experiences with Mixed Reality and Conversation AI | C17: Quantitative non-randomised | D17: Yes | E17: Yes | F17: No | G17: No | H17: Can't tell | I17: No | J17: Can't tell | K17: =IF(OR(D17<>"Yes",E17<>"Yes"),"",COUNTIF(F17:J17,"Yes")) -> 0 | L17: 3.1 six university participants; 3.2 ratings from transcription notes, no validated measure; 3.3 not reported; 3.4 fixed order MR→laptop, no control of order/prior knowledge; 3.5 not described.
A18: 17 | B18: Cross-Reality Interaction and Collaboration in Museums, Education, and Rehabilitation | C18: Quantitative non-randomised | D18: Yes | E18: Yes | F18: No | G18: Yes | H18: Yes | I18: Can't tell | J18: Yes | K18: =IF(OR(D18<>"Yes",E18<>"Yes"),"",COUNTIF(F18:J18,"Yes")) -> 3 | L18: 3.1 six young adults, not target learners; 3.2 standard SUS/UEQ-S; 3.3 all 36 sets collected; 3.4 order/role effects not described; 3.5 sessions as planned.
A19: 18 | B19: Shrink or grow the kids? Scale cognition in an immersive virtual environment for K-12 summer camp | C19: Quantitative descriptive | D19: Yes | E19: Yes | F19: Yes | G19: Can't tell | H19: No | I19: Yes | J19: Yes | K19: =IF(OR(D19<>"Yes",E19<>"Yes"),"",COUNTIF(F19:J19,"Yes")) -> 3 | L19: 4.2 summer-camp attendees; 4.3 single author-made items; 4.4 all 69 responded; 4.5 descriptive %.
A20: 19 | B20: WEBARIO: A Web based Portal with Revolutionary Virtual Classroom and Augmented Reality Integration for Enhanced Learning | C20: Not appraisable (no empirical learner study) | D20: Yes | E20: No | K20: =IF(OR(D20<>"Yes",E20<>"Yes"),"",COUNTIF(F20:J20,"Yes")) | L20: Development paper; no evaluation.
A21: 20 | B21: Virtual learner experience (VLX): A new dimension of virtual reality environments for the assessment of knowledge transfer | C21: Quantitative descriptive | D21: Yes | E21: Yes | F21: Yes | G21: No | H21: Can't tell | I21: Can't tell | J21: Yes | K21: =IF(OR(D21<>"Yes",E21<>"Yes"),"",COUNTIF(F21:J21,"Yes")) -> 2 | L21: 4.2 convenience sample of 10; 4.3 author-made Likert items, no psychometrics; 4.4 some items not answered by all; 4.5 descriptive means.
A22: 21 | B22: GIS-BASED EDUCATIONAL GAME THROUGH LOW-COST VIRTUAL TOUR EXPERIENCE Khan Game | C22: Not appraisable (no empirical learner study) | D22: Yes | E22: No | K22: =IF(OR(D22<>"Yes",E22<>"Yes"),"",COUNTIF(F22:J22,"Yes")) | L22: Playtest mentioned but no results reported.
A23: 22 | B23: The Application of Scientific Games by Artificial Intelligence in Preschool Education under the Smart City | C23: Not appraisable (no empirical learner study) | D23: No | E23: No | K23: =IF(OR(D23<>"Yes",E23<>"Yes"),"",COUNTIF(F23:J23,"Yes")) | L23: Retracted article – not appraised.
A24: 23 | B24: arPcTECHture' - a gamified educational 3D virtual world for introductory concepts in computer architecture | C24: Quantitative descriptive | D24: Yes | E24: Yes | F24: Yes | G24: No | H24: Yes | I24: No | J24: Yes | K24: =IF(OR(D24<>"Yes",E24<>"Yes"),"",COUNTIF(F24:J24,"Yes")) -> 3 | L24: 4.3 standard UEQ, translated per guidelines; 4.4 12 of 200 responded (6%); 4.5 UEQ tool and benchmark appropriate.
A25: 24 | B25: TEACHING EARTH SYSTEMS BEYOND THE CLASSROOM: DEVELOPING A MIXED REALITY (XR) SANDBOX | C25: Not appraisable (no empirical learner study) | D25: Yes | E25: No | K25: =IF(OR(D25<>"Yes",E25<>"Yes"),"",COUNTIF(F25:J25,"Yes")) | L25: No user data received.
A26: 25 | B26: Fantastic voyage 2021: Using interactive VR storytelling to explain targeted COVID-19 vaccine delivery to antigen-presenting cells | C26: Not appraisable (no empirical learner study) | D26: Yes | E26: No | K26: =IF(OR(D26<>"Yes",E26<>"Yes"),"",COUNTIF(F26:J26,"Yes")) | L26: Design paper; no evaluation.
A27: 26 | B27: Design and implementation of a virtual reality insects learning system with its user experience evaluation | C27: Quantitative descriptive | D27: Yes | E27: Yes | F27: Yes | G27: Can't tell | H27: Yes | I27: Can't tell | J27: Yes | K27: =IF(OR(D27<>"Yes",E27<>"Yes"),"",COUNTIF(F27:J27,"Yes")) -> 3 | L27: 4.3 adapted scales with α ≥ .74 (but load items worded as ease); 4.4 completion not reported (gift incentive); 4.5 descriptive + correlations appropriate.
A28: 27 | B28: Virtual reality for deeper learning: An exemplar from high school science | C28: Qualitative | D28: Yes | E28: Yes | F28: Yes | G28: Yes | H28: Can't tell | I28: Yes | J28: Can't tell | K28: =IF(OR(D28<>"Yes",E28<>"Yes"),"",COUNTIF(F28:J28,"Yes")) -> 3 | L28: Rich video/work-sample data; exemplar purposively selected as most successful case, analysis process not detailed.
A29: 28 | B29: Virtual simulation for history education | C29: Not appraisable (no empirical learner study) | D29: Yes | E29: No | K29: =IF(OR(D29<>"Yes",E29<>"Yes"),"",COUNTIF(F29:J29,"Yes")) | L29: Practice description; no data.
A30: 29 | B30: Teach Me a Story: An Augmented Reality Application for Teaching History in Middle School | C30: Quantitative non-randomised | D30: Yes | E30: Yes | F30: Can't tell | G30: No | H30: Yes | I30: No | J30: Yes | K30: =IF(OR(D30<>"Yes",E30<>"Yes"),"",COUNTIF(F30:J30,"Yes")) -> 2 | L30: 3.2 author-made 4-point items, comparison with 'expected' time not measured; 3.3 all 26 completed; 3.4 no control of confounders; 3.5 lesson delivered as planned.
A31: 30 | B31: An immersive virtual reality learning environment with CFD simulations: Unveiling the Virtual Garage concept | C31: Quantitative descriptive | D31: Yes | E31: Yes | F31: Yes | G31: Can't tell | H31: Yes | I31: Yes | J31: Yes | K31: =IF(OR(D31<>"Yes",E31<>"Yes"),"",COUNTIF(F31:J31,"Yes")) -> 4 | L31: 4.3 SUS, UEQ, NASA-TLX, SSQ standard; 4.4 no drop-outs; 4.5 appropriate non-parametric tests.
A32: 31 | B32: Gamified Virtual Reality for Computational Thinking | C32: Quantitative non-randomised | D32: Yes | E32: Yes | F32: Can't tell | G32: Yes | H32: Yes | I32: Yes | J32: Yes | K32: =IF(OR(D32<>"Yes",E32<>"Yes"),"",COUNTIF(F32:J32,"Yes")) -> 4 | L32: 3.1 interns + adults, n = 8; 3.2 standard UEQ and presence scale; 3.3 all completed; 3.4 pseudorandom order, task pre-explained; 3.5 as planned.
A33: 32 | B33: Sustainability in Elementary School: The Prototype and Evaluation of XR-based Learning to Achieve Quality Education | C33: Quantitative descriptive | D33: Yes | E33: Yes | F33: Yes | G33: No | H33: Yes | I33: Can't tell | J33: Yes | K33: =IF(OR(D33<>"Yes",E33<>"Yes"),"",COUNTIF(F33:J33,"Yes")) -> 3 | L33: 4.2 purposive, one private school; 4.3 standard UEQ; 4.4 50 → 40 after cleaning; 4.5 UEQ tool.
A34: 33 | B34: Virtual Reality-Based Traffic Sign Education for Early Childhood | C34: Quantitative descriptive | D34: Yes | E34: Yes | F34: Yes | G34: Can't tell | H34: No | I34: Can't tell | J34: Yes | K34: =IF(OR(D34<>"Yes",E34<>"Yes"),"",COUNTIF(F34:J34,"Yes")) -> 2 | L34: 4.3 single author-made rating items with 4–7-year-olds; 4.5 descriptive counts.
A35: 34 | B35: A new intelligent VR biological learning system based on natural interaction | C35: Quantitative non-randomised | D35: Yes | E35: Yes | F35: Can't tell | G35: No | H35: Can't tell | I35: No | J35: Can't tell | K35: =IF(OR(D35<>"Yes",E35<>"Yes"),"",COUNTIF(F35:J35,"Yes")) -> 0 | L35: Participants undescribed; author-made questionnaire; order and confounders not addressed; procedure unclear.
A36: 35 | B36: Exploring User Experience and Usability in a Metaverse Learning Environment for Students: A Usability Study of the Artificial Intelligence, Innovation, and Society (AIIS) | C36: Quantitative descriptive | D36: Yes | E36: Yes | F36: Yes | G36: No | H36: Yes | I36: Can't tell | J36: Yes | K36: =IF(OR(D36<>"Yes",E36<>"Yes"),"",COUNTIF(F36:J36,"Yes")) -> 3 | L36: 4.2 social-media recruitment; 4.3 standard GEQ; 4.5 descriptive means.
A37: 36 | B37: Exploring Prehistoric Era in Virtual Reality Walkthrough | C37: Quantitative descriptive | D37: Yes | E37: Yes | F37: Can't tell | G37: Can't tell | H37: No | I37: No | J37: No | K37: =IF(OR(D37<>"Yes",E37<>"Yes"),"",COUNTIF(F37:J37,"Yes")) -> 0 | L37: N not stated; author-made acceptance items; item counts differ (missing responses); reported % inconsistent with figure.
A38: 37 | B38: Chemisim: A Web-based VR Simulator for Chemistry Experiments | C38: Quantitative descriptive | D38: Yes | E38: Yes | F38: No | G38: No | H38: No | I38: Can't tell | J38: Yes | K38: =IF(OR(D38<>"Yes",E38<>"Yes"),"",COUNTIF(F38:J38,"Yes")) -> 1 | L38: Intended for high-school students but tested with university students/professors; author-made ratings; descriptive means.
A39: 38 | B39: Multidisciplinary Virtual Environments for Kids with ADHD: A Pilot Study | C39: Quantitative non-randomised | D39: Yes | E39: Yes | F39: Yes | G39: No | H39: Yes | I39: No | J39: Can't tell | K39: =IF(OR(D39<>"Yes",E39<>"Yes"),"",COUNTIF(F39:J39,"Yes")) -> 2 | L39: 3.1 children with ADHD = target; 3.2 post-test α = .68, teacher-rated; 3.3 all 5 completed; 3.4 no control; 3.5 exposure not described.
A40: 39 | B40: vSocial: a cloud-based system for social virtual reality learning environment applications in special education | C40: Quantitative non-randomised | D40: Yes | E40: Yes | F40: No | G40: No | H40: Can't tell | I40: Yes | J40: Can't tell | K40: =IF(OR(D40<>"Yes",E40<>"Yes"),"",COUNTIF(F40:J40,"Yes")) -> 1 | L40: 3.1 comparison run with college students, not ASD youth; 3.2 author-made survey; 3.4 order randomised; others not reported.
A41: 40 | B41: The design of recognition system of children basic activities based on virtual reality | C41: Not appraisable (no empirical learner study) | D41: Yes | E41: No | K41: =IF(OR(D41<>"Yes",E41<>"Yes"),"",COUNTIF(F41:J41,"Yes")) | L41: Teacher-only evaluation.
A42: 41 | B42: Determining design requirements for AR physics education applications | C42: Not appraisable (no empirical learner study) | D42: Yes | E42: No | K42: =IF(OR(D42<>"Yes",E42<>"Yes"),"",COUNTIF(F42:J42,"Yes")) | L42: Teacher interviews only; no learner data.
A43: 42 | B43: Implementation of the framework to heritage education supported in augmented reality | C43: Quantitative descriptive | D43: Yes | E43: Yes | F43: Yes | G43: Can't tell | H43: Can't tell | I43: Can't tell | J43: Yes | K43: =IF(OR(D43<>"Yes",E43<>"Yes"),"",COUNTIF(F43:J43,"Yes")) -> 2 | L43: 4.2 sample size calculated but sampling method unclear; 4.3 8 items selected from ARCS instrument without re-validation; 4.5 descriptive statistics.
A44: 43 | B44: Evaluation of user interface satisfaction for virtual umrah among secondary school students | C44: Quantitative descriptive | D44: Yes | E44: Yes | F44: Yes | G44: Can't tell | H44: Can't tell | I44: Can't tell | J44: Yes | K44: =IF(OR(D44<>"Yes",E44<>"Yes"),"",COUNTIF(F44:J44,"Yes")) -> 2 | L44: 4.3 QUIS is standard but applied after a demonstration, not hands-on use; 4.5 descriptive means.
A45: 44 | B45: Discounted prototyping of virtual reality solutions for science education | C45: Not appraisable (no empirical learner study) | D45: Yes | E45: No | K45: =IF(OR(D45<>"Yes",E45<>"Yes"),"",COUNTIF(F45:J45,"Yes")) | L45: No XR exposure (paper mock-up); 2 learners.
A46: 45 | B46: Developing mixed reality educational applications: The virtual touch toolkit | C46: Quantitative non-randomised | D46: Yes | E46: Yes | F46: Can't tell | G46: Can't tell | H46: Can't tell | I46: No | J46: Can't tell | K46: =IF(OR(D46<>"Yes",E46<>"Yes"),"",COUNTIF(F46:J46,"Yes")) -> 0 | L46: Sample sizes, group allocation and instruments not reported; no statistics.
A62: MMAT 2018 criteria by category (Hong QN et al., Mixed Methods Appraisal Tool, version 2018, Canadian IP registration 1148552). Ratings: Yes / No / Can't tell. For mixed-methods studies, the component that supplies the RQ6 evidence is appraised and this is stated in the rationale.
A63: Qualitative | F63: 1.1 Qualitative approach appropriate? | G63: 1.2 Data collection adequate? | H63: 1.3 Findings adequately derived from data? | I63: 1.4 Interpretation substantiated by data? | J63: 1.5 Coherence between data, analysis, interpretation?
A64: Quantitative RCT | F64: 2.1 Randomisation appropriate? | G64: 2.2 Groups comparable at baseline? | H64: 2.3 Complete outcome data? | I64: 2.4 Assessors blinded? | J64: 2.5 Adherence to intervention?
A65: Quantitative non-randomised | F65: 3.1 Participants representative of target population? | G65: 3.2 Measurements appropriate (outcome & intervention)? | H65: 3.3 Complete outcome data? | I65: 3.4 Confounders accounted for? | J65: 3.5 Intervention administered as intended?
A66: Quantitative descriptive | F66: 4.1 Sampling strategy relevant to RQ? | G66: 4.2 Sample representative of target population? | H66: 4.3 Measurements appropriate? | I66: 4.4 Risk of nonresponse bias low? | J66: 4.5 Statistical analysis appropriate?
A67: Mixed methods | F67: 5.1 Rationale for mixed methods adequate? | G67: 5.2 Components effectively integrated? | H67: 5.3 Integration outputs interpreted? | I67: 5.4 Divergences addressed? | J67: 5.5 Components meet their quality criteria?

Sheet Sheet1
A1: New num | C1: Authors | D1: Author full names | E1: Author(s) ID | F1: Title | G1: Year | H1: Source title | I1: Cited by | J1: DOI | K1: Link | L1: Affiliations | M1: Authors with affiliations | N1: Abstract | O1: Author Keywords | P1: Index Keywords | Q1: Publisher | R1: Language of Original Document | S1: Document Type | T1: Publication Stage | U1: Open Access | V1: Source | W1: Status | X1: Reason | Y1: Degree level | Z1: Who 1 | AA1: Who 2 | AB1: Note 1 | AC1: Note 2 | AD1: RQ1 | AE1: RQ2 | AF1: RQ3 | AG1: RQ2 | AH1: RQ4 | AL1: Focus | AM1: Who checked GPT Feedback | AN1: Note 1 | AO1: Who Re checked GPT Feedback | AP1: Main Author | AQ1: Main Author Email | AR1: RQ5 – Country (study site) | AS1: RQ5 – Region | AT1: RQ5 – Education level (ISCED 2011) | AU1: RQ5 – Learner population | AV1: RQ5 – Subject area (ISCED-F 2013 broad field) | AW1: RQ5 – Subject (specific) | AX1: RQ6 – XR type | AY1: RQ6 – Device category | AZ1: RQ6 – Device (specific) | BA1: RQ6 – Comparison condition | BB1: RQ6 – Engagement effect | BC1: RQ6 – Motivation effect | BD1: RQ6 – Satisfaction effect | BE1: RQ6 – Other reported outcomes | BF1: RQ6 – Statistical support | BG1: RQ6 – Effect size | BH1: RQ6 – Instrument(s) | BI1: RQ6 – Instrument validated? | BJ1: RQ7 – Study design | BK1: RQ7 – Design class | BL1: RQ7 – MMAT category | BM1: RQ7 – Sample size (N) | BN1: RQ7 – Exposure (duration) | BO1: RQ7 – MMAT score (0–5) | BP1: RQ7 – Overall rigor (auto) | BQ1: RQ7 – Adverse effects / limitations reported | BR1: RQ7 – Adverse-effect reporting | BS1: Synthesis set | BT1: Eligibility reason | BU1: Extraction status | BV1: Verification flags
A2: 1 | C2: Chew C.S.; Zafarin M.N.S.; Zain N.H.M.; Aminuddin R.; Tan T.G.; Chin K.O. | D2: Chew, Chiou Sheng (57206205702); Zafarin, Muhammad Nabil Shah (59664996100); Zain, Nurul Hidayah Mat (59664977600); Aminuddin, Raihah (57189037041); Tan, Tse Guan (57226387853); Chin, Kim On (59484027400) | E2: 57206205702; 59664996100; 59664977600; 57189037041; 57226387853; 59484027400 | F2: Transforming Secondary School Chemistry Learning with Virtual Reality | G2: 2024 | H2: 2024 IEEE 22nd Student Conference on Research and Development, SCOReD 2024 | I2: 0 | J2: 10.1109/SCOReD64708.2024.10872679 | K2: https://www.scopus.com/inward/record.uri?eid=2-s2.0-85219552594&doi=10.1109%2fSCOReD64708.2024.10872679&partnerID=40&md5=187cbbb42c76a164a4f1ddcf9e3eaf41 | L2: Universiti Teknologi MARA Melaka Branch, College of Computing, Informatics and Mathematics, Jasin Campus, Melaka, Malaysia; Universiti Malaysia Kelantan, Faculty of Creative Technology and Heritage, Malaysia; Universiti Malaysia Sabah, Faculty of Computing and Informatics, Sabah, Malaysia | M2: Chew C.S., Universiti Teknologi MARA Melaka Branch, College of Computing, Informatics and Mathematics, Jasin Campus, Melaka, Malaysia; Zafarin M.N.S., Universiti Teknologi MARA Melaka Branch, College of Computing, Informatics and Mathematics, Jasin Campus, Melaka, Malaysia; Zain N.H.M., Universiti Teknologi MARA Melaka Branch, College of Computing, Informatics and Mathematics, Jasin Campus, Melaka, Malaysia; Aminuddin R., Universiti Teknologi MARA Melaka Branch, College of Computing, Informatics and Mathematics, Jasin Campus, Melaka, Malaysia; Tan T.G., Universiti Malaysia Kelantan, Faculty of Creative Technology and Heritage, Malaysia; Chin K.O., Universiti Malaysia Sabah, Faculty of Computing and Informatics, Sabah, Malaysia | N2: In secondary schools, traditional chemistry instruction often depends on lecture-based approaches and occasional hands-on experiments, which may limit students' grasp of complex concepts like chemical reactions and molecular behaviour. This study addresses the need for enhanced educational tools by introducing a Virtual Reality (VR) application designed to enrich chemistry learning through immersive, interactive experiences. The VR tool allows students to simulate chemical reactions with adjustable parameters, such as temperature and concentration, enabling safe, hands-on exploration of complex processes. Usability was assessed among 30 secondary school students in Malaysia using the System Usability Scale (SUS), a standardized measure that gauges user experience across factors like functionality and ease of use. Findings showed a strong average SUS score of 91.25, indicating high usability and positive engagement from users. These results suggest that incorporating VR into the chemistry curriculum can help make challenging topics more accessible and engaging, supporting the modernization of science education. Future studies will look to expand the sample size and investigate additional chemistry topics to validate the tool's educational benefits further. © 2024 IEEE. | O2: Chemistry; Immersive learning; Secondary education; Virtual reality | P2: Complexation; Adjustable parameters; Educational tools; Immersive; Immersive learning; Molecular behavior; Reaction behavior; Secondary education; Secondary schools; System usability; Virtual reality tools; Students | Q2: Institute of Electrical and Electronics Engineers Inc. | R2: English | S2: Conference paper | T2: Final | V2: Scopus | W2: Accepted | X2: Relevant | Y2: Basic education | Z2: Ahsan | AA2: Lamarck | AC2: Check | AD2: Device used: Oculus Quest 2 standalone VR headset​ Type of XR: Fully immersive Virtual Reality (VR) (interactive 3D environment) | AE2: System Usability Scale (SUS)​: 10-question survey evaluating ease of use, efficiency, and satisfaction. | AF2: Students: Found VR easy to use and highly engaging​ Helped with understanding difficult concepts like reaction rates. No mention of negative effects like motion sickness in this study​ Teachers: Not directly evaluated here, but VR was framed as a helpful complement to traditional methods​ | AG2: Metric: SUS Score (System Usability Scale)​ Method:SUS processed by: Reversing odd questions, adjusting even questions. Summing and scaling to 0–100. Result: Average SUS Score: 91.25, indicating excellent usability​ | AH2: Software/Platform: Unity for VR environment development​ Hardware: Oculus Quest 2 headset​ Instructional design: ADDIE model (Analysis, Design, Development, Implementation, Evaluation) for systematic educational tool creation​ | AL2: STEM | AM2: Ahsan | AN2: Check | AO2: Lamarck | AR2: Malaysia | AS2: Asia | AT2: Upper secondary | AU2: Typical learners (age 16) | AV2: Natural sciences, mathematics & statistics | AW2: Chemistry (chemical reactions) | AX2: VR | AY2: HMD (immersive) | AZ2: HMD – standalone | BA2: None | BB2: Not measured | BC2: Not measured | BD2: Not measured | BE2: Usability only: SUS = 91.25. Authors state engagement and learning were NOT evaluated | BF2: Descriptive only | BG2: Not reported | BH2: SUS (items modified by authors) | BI2: Adapted | BJ2: Single-group post-test only | BK2: Single group, post-test only | BL2: Quantitative descriptive | BM2: 30 students (age 16; 60% F) | BN2: Single session (duration NR) | BO2: =IF(COUNTIF('MMAT Appraisal'!$A$2:$A$60,A2)=0,"",INDEX('MMAT Appraisal'!$K$2:$K$60,MATCH(A2,'MMAT Appraisal'!$A$2:$A$60,0))) -> 2 | BP2: =IF(OR(BF2="No empirical data",ISNUMBER(SEARCH("RETRACTED",BV2))),"Not rated",IF(AND(ISNUMBER(BO2),BO2<=2),"Low",IF(AND(OR(BJ2="RCT",BJ2="Quasi-experimental with control"),LEFT(BF2,11)="Inferential",OR(BI2="Yes",BI2="Partly"),OR(BO2="",BO2>=4)),"High",IF(OR(BA2<>"None",LEFT(BF2,11)="Inferential"),"Moderate","Low")))) -> Low | BQ2: Not reported | BR2: Not reported | BS2: Excluded | BT2: E3: No engagement, motivation or satisfaction outcome measured (usability only; authors state engagement was not evaluated) | BU2: Verified (full text) | BV2: Abstract claims 'positive engagement', but the paper says engagement was not evaluated – no E/M/S evidence
A3: 2 | C3: Cheng K.-H. | D3: Cheng, Kun-Hung (37461088800) | E3: 37461088800 | F3: Development of an immersive virtual reality system for learning about plants in primary education: evaluation of teachers’ perceptions and learners’ flow experiences and learning attitudes | G3: 2024 | H3: Educational Technology Research and Development | I3: 6 | J3: 10.1007/s11423-023-10300-6 | K3: https://www.scopus.com/inward/record.uri?eid=2-s2.0-85174240307&doi=10.1007%2fs11423-023-10300-6&partnerID=40&md5=d42e39e94437a741283692aedd7cf464 | L3: Graduate Institute of Library & amp; Information Science, National Chung Hsing University, 145 Xingda Rd., South District, Taichung, 402, Taiwan; Innovation and Development Center of Sustainable Agriculture, National Chung Hsing University, Taichung, Taiwan | M3: Cheng K.-H., Graduate Institute of Library & amp; Information Science, National Chung Hsing University, 145 Xingda Rd., South District, Taichung, 402, Taiwan, Innovation and Development Center of Sustainable Agriculture, National Chung Hsing University, Taichung, Taiwan | N3: This study aimed to establish a fully 3D modeled immersive virtual reality (IVR) system for primary school students learning about plants and evaluate teachers’ perceptions of the usage of the system and pupils’ flow experiences and learning attitudes. There were 5 teachers with expertise in science and IVR experience who were first interviewed to understand their consideration of the limitations of teaching about plants in the classroom. The framework and script of the learning content for the IVR system, as well as the user interface and function were then comprehensively described. Another 10 teachers were invited to evaluate the appropriateness of the system for fifth-grade students to learn about plants. These teachers generally expressed positive attitudes towards exploiting the IVR system for their teaching. Moreover, there were 37 fifth-grade students contributed to the evaluation of the system. The results indicated that the IVR system was capable of offering the pupils perceptions of antecedences to achieve flow such as task challenge, clear goal, instant feedback, well control, and playability, and aroused their flow experiences, particularly regarding autotelic experience and concentration. This study also verified the relationships between the pupils’ flow experiences and learning attitudes. The crucial roles of flow perceptions including playability, challenge, and autotelic experience in the pupils’ learning attitudes were further identified. According to the results of the evaluation from the teachers’ and students’ perspectives, several practical and academic implications of this study are proposed. © Association for Educational Communications and Technology 2023. | O3: Attitude; Flow experience; Instructional design; Science learning; Virtual reality | Q3: Springer | R3: English | S3: Article | T3: Final | V3: Scopus | W3: Accepted | X3: Relevant | Y3: Basic education | Z3: Ahsan | AA3: Lamarck | AC3: Check | AD3: Device used: Standalone VR Headset: Gear VR with controller​ Type of XR: Fully 3D modeled immersive virtual reality (IVR) — not 360° photos. Environment: Custom Unity-based 3D environments with interactive elements​ | AE3: Surveys: Flow Scale for Games (FSG) (adapted) — measuring flow antecedents and flow experiences​ . Learning Attitude Survey — measuring ease of use, usefulness, affection (negative feelings), and intention​ . Interviews: Teachers interviewed after trials regarding usability, suitability, and willingness to use | AF3: Students: Increased concentration, intrinsic enjoyment (autotelic experience), and positive attitudes. Minor issues: moderate time distortion, mild self-consciousness, but mostly positive​ . Teachers: Mostly positive (seeing VR as beneficial), but some discomfort (motion sickness, getting used to panoramic vision) and concerns about time demands | AG3: Metrics for Students: Flow antecedents: challenge, goal clarity, feedback, control, playability. Flow experiences: concentration, time distortion, autotelic experience (enjoyment), loss of self-consciousness​ . Learning attitudes: ease of use, usefulness, affection (anxiety/boredom), intention to reuse​ . Statistical Analyses: Repeated-measures ANOVA and Stepwise Regression Analysis | AH3: Software/Platform: Unity (game engine) for VR environment development​ . Maya for 3D modeling and animation​ . Oculus Mobile SDK for VR integration​ . Hardware: Gear VR headset + Controller​ . Instructional design method: ADDIE model (Analysis, Design, Development, Implementation, Evaluation) | AL3: STEM | AM3: Joao | AN3: Check | AO3: Pedro | AR3: Taiwan | AS3: Asia | AT3: Primary | AU3: Typical learners (grade 5) + teachers | AV3: Natural sciences, mathematics & statistics | AW3: Biology (plants), grade 5 | AX3: VR | AY3: HMD (immersive) | AZ3: HMD – mobile (Gear VR) | BA3: None | BB3: + | BC3: + | BD3: Not measured | BE3: Concentration M = 4.38, autotelic enjoyment M = 4.49, intention to reuse M = 4.54 (/5); low anxiety/boredom M = 1.80 | BF3: Inferential, no effect size | BG3: No XR-vs-control ES (single group); R² = .14–.48 for flow → attitude regressions | BH3: Flow Scale for Games (Kiili 2006, adapted; subscale α = .54–.82, overall .90); learning-attitude survey (adapted; α = .73) | BI3: Adapted | BJ3: Mixed methods (single group) | BK3: Single group, mixed methods / DBR | BL3: Quantitative descriptive | BM3: 37 grade-5 students (19 M, 18 F); 10 teachers (+5 interviewed in analysis phase) | BN3: Single session, 15–20 min | BO3: =IF(COUNTIF('MMAT Appraisal'!$A$2:$A$60,A3)=0,"",INDEX('MMAT Appraisal'!$K$2:$K$60,MATCH(A3,'MMAT Appraisal'!$A$2:$A$60,0))) -> 3 | BP3: =IF(OR(BF3="No empirical data",ISNUMBER(SEARCH("RETRACTED",BV3))),"Not rated",IF(AND(ISNUMBER(BO3),BO3<=2),"Low",IF(AND(OR(BJ3="RCT",BJ3="Quasi-experimental with control"),LEFT(BF3,11)="Inferential",OR(BI3="Yes",BI3="Partly"),OR(BO3="",BO3>=4)),"High",IF(OR(BA3<>"None",LEFT(BF3,11)="Inferential"),"Moderate","Low")))) -> Moderate | BQ3: Teachers: loss of spatial sense, one case of motion sickness; none reported for students | BR3: Cybersickness / physical discomfort reported | BS3: Core | BT3: Basic-education learners with empirical E/M/S data | BU3: Verified (full text) | BV3: Mixed-methods study; MMAT applied to the student survey component that gives the RQ6 evidence
A4: 3 | C4: Dash A.K.; Behera S.K.; Dogra D.P. | D4: Dash, Ajaya Kumar (56723571400); Behera, Santosh Kumar (57220715678); Dogra, Debi Prosad (35408975400) | E4: 56723571400; 57220715678; 35408975400 | F4: PlutoAR: a scalable marker-based augmented reality application for interactive and inclusive education | G4: 2024 | H4: Multimedia Tools and Applications | I4: 1 | J4: 10.1007/s11042-023-17756-x | K4: https://www.scopus.com/inward/record.uri?eid=2-s2.0-85179311876&doi=10.1007%2fs11042-023-17756-x&partnerID=40&md5=1173b72cd0c5cc55d1d20e7a1500440b | L4: Department of CSE, International Institute of Information Technology Bhubaneswar, Gothapatna, Odisha, Bhubaneswar, 751003, India; School of Electrical Sciences, Indian Institute of Technology Bhubaneswar, Argul, Odisha, Khordha, 752050, India; Department of CSE, National Institute of Technology, Kerala, Calicut, 673601, India | M4: Dash A.K., Department of CSE, International Institute of Information Technology Bhubaneswar, Gothapatna, Odisha, Bhubaneswar, 751003, India, School of Electrical Sciences, Indian Institute of Technology Bhubaneswar, Argul, Odisha, Khordha, 752050, India; Behera S.K., Department of CSE, National Institute of Technology, Kerala, Calicut, 673601, India; Dogra D.P., School of Electrical Sciences, Indian Institute of Technology Bhubaneswar, Argul, Odisha, Khordha, 752050, India | N4: Various studies have suggested that computational thinking needs to be highlighted as one of the essential abilities and it should be taught in the standard K-10 curriculum. However, the standard K-10 curriculum does not always contain accessible technology that uses interactive teaching methods and efficient analytical skill development. Also, most practical computational thinking applications that are being created seem to be complex and expensive for educational settings. In this work, we introduce PlutoAR, a marker-based augmented reality (AR) interpreter that is scalable, inexpensive, portable, and can be used as a platform for kids to enhance their skills in an inclusive way. PlutoAR incorporates AR through an interactive toolkit to give students the experiences of both the real and virtual worlds, overcoming the limitations of traditional and non-interactive setups. With the help of technology-based solutions, this effort intends to enable students from all demographic groups to engage in the learning process, regardless of their level of competence. The PlutoAR mobile application presently runs on any Android device with a camera. It creates inbuilt AR experiences like stories, basic elementary mathematics, navigating mazes utilising conditional loops to solve them, and the intuition of gravity. The usability of the PutoAR application is verified by performing the qualitative and quantitative analysis through user feedback. The application seems to be acceptable by users with a System Usability Scale (SUS) score of more than 80. In future, we intend to provide flexibility to the user for adding new content inside the application whenever needed and to promote AR-based collaboration among the students. © The Author(s), under exclusive licence to Springer Science+Business Media, LLC, part of Springer Nature 2023. | O4: Augmented reality; K-10 education; Smart learning application; User interfaces | P4: Augmented reality; Curricula; Learning systems; Students; Virtual reality; Analytical skills; Augmented reality applications; Computational thinkings; Essential abilities; Inclusive education; Interactive education; K-10 education; Skills development; Smart learning application; Teaching methods; User interfaces | Q4: Springer | R4: English | S4: Article | T4: Final | V4: Scopus | W4: Accepted | X4: Relevant | Y4: Basic education | Z4: Ahsan | AA4: Lamarck | AC4: Check | AD4: Device used: Any Android mobile device with a camera​ . Type of XR: Marker-based Augmented Reality (AR), not full VR or Cave​ | AE4: System Usability Scale (SUS)​ : Standard 10-question SUS survey (Likert scale 1–5). Custom Survey Questions for qualitative analysis​ : Evaluated ease of use, understanding concepts, visualization quality, 3D object quality, portability, overall experience. | AF4: Students: Reported high motivation, ease of use, better visualization of concepts​ . Encouraged exploration, algorithmic thinking, and problem-solving. Teachers: Reported better engagement, especially in special needs students​ | AG4: Metrics: SUS Score (System Usability Scale). Cronbach’s alpha to validate survey consistency (α = 0.770, "acceptable")​ . Results: Average SUS score: ~83–86 depending on age group, meaning excellent usability​ | AH4: oftware/Platform: Unity 3D for AR app development​ . Vuforia Engine for marker-based AR​ . Android Studio for mobile app deployment​ . Hardware: Android smartphones/tablets. Markers: Special printed tiles ("DreamKit") placed on a Launchpad (A4 paper) to trigger 3D AR content​ | AL4: STEM | AM4: Lamarck | AN4: Check | AO4: Ahsan | AR4: India | AS4: Asia | AT4: Mixed (school-age + adults) | AU4: School visitors & event participants aged 10–45 (70% aged 10–15) | AV4: ICT | AW4: Computational thinking; elementary maths & science facts | AX4: AR | AY4: Handheld (mobile/tablet) | AZ4: Mobile/tablet – marker-based AR | BA4: None | BB4: Not measured | BC4: Not measured | BD4: + | BE4: Overall experience rated ≥ 7/10 by ~85%; ease of use ≥ 7/10 by ~80%; SUS ≈ 83 (age 10–15), 'excellent' across age groups | BF4: Descriptive only | BG4: Not reported | BH4: Author-made 6-item survey (α = .77); SUS (standard) | BI4: Partly | BJ4: Single-group post-test only | BK4: Single group, post-test only | BL4: Quantitative descriptive | BM4: 415 participants (289 aged 10–15) | BN4: Demonstration sessions (duration NR) | BO4: =IF(COUNTIF('MMAT Appraisal'!$A$2:$A$60,A4)=0,"",INDEX('MMAT Appraisal'!$K$2:$K$60,MATCH(A4,'MMAT Appraisal'!$A$2:$A$60,0))) -> 1 | BP4: =IF(OR(BF4="No empirical data",ISNUMBER(SEARCH("RETRACTED",BV4))),"Not rated",IF(AND(ISNUMBER(BO4),BO4<=2),"Low",IF(AND(OR(BJ4="RCT",BJ4="Quasi-experimental with control"),LEFT(BF4,11)="Inferential",OR(BI4="Yes",BI4="Partly"),OR(BO4="",BO4>=4)),"High",IF(OR(BA4<>"None",LEFT(BF4,11)="Inferential"),"Moderate","Low")))) -> Low | BQ4: None reported; marker dependency noted | BR4: Explicitly none observed | BS4: Core | BT4: Basic-education learners with empirical E/M/S data | BU4: Verified (full text) | BV4: Children and adults pooled; SEN school visit is anecdotal observation only; engagement/motivation claimed but not measured
A5: 4 | C5: Alvarado Y.; Guerrero R.; Serón F. | D5: Alvarado, Yoselie (57193159663); Guerrero, Roberto (53663722000); Serón, Francisco (7004349303) | E5: 57193159663; 53663722000; 7004349303 | F5: Inclusive Learning through Immersive Virtual Reality and Semantic Embodied Conversational Agent: A case study in children with autism; [Aprendizaje Inclusivo mediante Realidad Virtual Inmersiva y Agente Conversacional Semántico Encarnado: Un caso de estudio en niños con autismo] | G5: 2023 | H5: Journal of Computer Science and Technology(Argentina) | I5: 6 | J5: 10.24215/16666038.23.e09 | K5: https://www.scopus.com/inward/record.uri?eid=2-s2.0-85175262404&doi=10.24215%2f16666038.23.e09&partnerID=40&md5=0ca6877443268c3ffee6318a6d34bd7f | L5: Laboratorio de Computación Gráfica, Universidad Nacional de San Luis, Argentina; Instituto de Física Aplicada, CONICET, Universidad Nacional de San Luis, Argentina; Instituto de Investigación de Ingeniería de Aragón, Grupo GIGA, Universidad de Zaragoza, Spain | M5: Alvarado Y., Laboratorio de Computación Gráfica, Universidad Nacional de San Luis, Argentina, Instituto de Física Aplicada, CONICET, Universidad Nacional de San Luis, Argentina; Guerrero R., Laboratorio de Computación Gráfica, Universidad Nacional de San Luis, Argentina; Serón F., Instituto de Investigación de Ingeniería de Aragón, Grupo GIGA, Universidad de Zaragoza, Spain | N5: Sustainable Development Goal 4 from the United Nations 2030 Agenda, focus on ensuring inclusive and equitable quality education and promoting lifelong learning opportunities for all. Inclusive education is a key component of sustainable development goal 4, and assistive technology is a critical factor in achieving it. In this context, this paper introduces the development of an immersive virtual reality system with conversational skills for inclusive learning processes. The idea of this work is to provide an assistive technology to motivate, educate, and train students with disabilities in a more inclusive way. In order to improve the user experience, the system was developed to work in a CAVE-like immersive environment using Natural Language Processing through a Semantic Embodied Conversational Agent. This work highlights that assistive technology can promote educational, psychological, and social benefits for students with disabilities. The use of assistive technology can enable academic engagement and social participation and be transformative from a psychological perspective. A case study was conducted on children with autism, which showed encouraging results of the system as an assistive technology for teaching and learning. © 2023, Facultad de Informatica, Universidad Nacional de La Plata. All rights reserved. | O5: Assistive Technologies; Autism; Immersive Virtual Reality; Inclusive Education; Natural Language Processing | Q5: Facultad de Informatica, Universidad Nacional de La Plata | R5: English | S5: Article | T5: Final | U5: All Open Access; Gold Open Access | V5: Scopus | W5: Accepted | X5: Relevant | Y5: Basic education | Z5: Ahsan | AA5: Joao | AC5: Check | AD5: Device used: CAVE-like immersive VR environment​ : Room with three screens and three projectors. Powerful PC with multi-GPU output. Type of XR: Immersive Virtual Reality + Semantic Embodied Conversational Agent (SECA)​ . | AE5: Emotional Response Measurement: Adapted Self-Assessment Manikin (SAM) scale with visual "Lore" numbers​ . Learning Assessment: Home spelling tests with parents using customized name cards​ | AF5: Students: Children with autism showed positive emotional responses (average emotional score 3.73/5)​ . Improved learning outcomes (average 74.6% correct in spelling names)​ . No major discomforts reported; careful preparation helped (photos of lab, researcher, etc.). Teachers and parents: Not evaluated formally, but parents were involved in post-test assessment and supported the study. | AG5: Metrics: Lore Emotional Scale (adapted from SAM)​ . Learning success rate (percentage of correctly spelled letters)​ . Results: Emotional average: 3.73/5. Learning average: 74.6% correct. | AH5: Software/Platform: Multi-VRMedia platform for CAVE environment management​ . Dbpedia for semantic knowledge for conversational agent​ . Hardware: CAVE-like setup: 3 screens, 3 short-throw projectors, powerful PC​ . Input devices: Wireless microphone, special keyboard (modified for children)​ . Interaction Tech: Natural Language Processing (NLP) for real-time dialogue​ . Speech-to-Text (ASR) and Text-to-Speech (TTS) modules​ . | AL5: Special Education | AM5: Pedro | AN5: Check | AO5: Joao | AR5: Argentina | AS5: South America | AT5: Mixed K-12 | AU5: SEN – autism (ages 3–7) | AV5: Generic programmes (literacy) | AW5: Spelling / name literacy | AX5: VR | AY5: CAVE / projection | AZ5: CAVE / projection | BA5: None | BB5: + | BC5: Not measured | BD5: Not measured | BE5: Emotional (liking) response M = 3.73/5 (SD 0.70; min 3); name-spelling accuracy 74.6% (51–97%) at home post-test | BF5: Descriptive only | BG5: Not reported | BH5: Lore Emotional Scale (adapted Self-Assessment Manikin); parent-administered spelling test | BI5: Adapted | BJ5: Case study | BK5: Single group, post-test only | BL5: Quantitative descriptive | BM5: 10 children (ages 3–7) | BN5: One encounter: 3 × ~2 min | BO5: =IF(COUNTIF('MMAT Appraisal'!$A$2:$A$60,A5)=0,"",INDEX('MMAT Appraisal'!$K$2:$K$60,MATCH(A5,'MMAT Appraisal'!$A$2:$A$60,0))) -> 2 | BP5: =IF(OR(BF5="No empirical data",ISNUMBER(SEARCH("RETRACTED",BV5))),"Not rated",IF(AND(ISNUMBER(BO5),BO5<=2),"Low",IF(AND(OR(BJ5="RCT",BJ5="Quasi-experimental with control"),LEFT(BF5,11)="Inferential",OR(BI5="Yes",BI5="Partly"),OR(BO5="",BO5>=4)),"High",IF(OR(BA5<>"None",LEFT(BF5,11)="Inferential"),"Moderate","Low")))) -> Low | BQ5: None reported; pre-visit preparation needed to reduce sensory sensitivity | BR5: Explicitly none observed | BS5: Core | BT5: Basic-education learners with empirical E/M/S data | BU5: Verified (full text) | BV5: Engagement coded from emotional response (SAM); no baseline, parent-assessed learning outcome
A6: 5 | C6: Chandra A.Y.; Prasetyaningrum P.T.; Suria O.; Santosa P.I.; Nugroho L.E.; Pratama I. | D6: Chandra, Albert Yakobus (57223975090); Prasetyaningrum, Putri Taqwa (57213688916); Suria, Ozzi (57223985787); Santosa, Paulus Insap (9636895500); Nugroho, Lukito Edi (6507794445); Pratama, Irfan (57205570140) | E6: 57223975090; 57213688916; 57223985787; 9636895500; 6507794445; 57205570140 | F6: Evaluation User Acceptance of Mobile Virtual Reality Application for English Learning | G6: 2022 | H6: 2022 1st International Conference on Information System and Information Technology, ICISIT 2022 | I6: 1 | J6: 10.1109/ICISIT54091.2022.9872873 | K6: https://www.scopus.com/inward/record.uri?eid=2-s2.0-85138707720&doi=10.1109%2fICISIT54091.2022.9872873&partnerID=40&md5=8ae1c292061e4c48976330bee99704e2 | L6: Universitas Mercu Buana Yogyakarta, Department of Information System, Faculty of Information Technology, Indonesia; Universitas Gadjah Mada, Department of Electrical Engineering and Information Technology, Faculty of Engineering, Yogyakarta, Indonesia | M6: Chandra A.Y., Universitas Mercu Buana Yogyakarta, Department of Information System, Faculty of Information Technology, Indonesia; Prasetyaningrum P.T., Universitas Mercu Buana Yogyakarta, Department of Information System, Faculty of Information Technology, Indonesia; Suria O., Universitas Mercu Buana Yogyakarta, Department of Information System, Faculty of Information Technology, Indonesia; Santosa P.I., Universitas Gadjah Mada, Department of Electrical Engineering and Information Technology, Faculty of Engineering, Yogyakarta, Indonesia; Nugroho L.E., Universitas Gadjah Mada, Department of Electrical Engineering and Information Technology, Faculty of Engineering, Yogyakarta, Indonesia; Pratama I., Universitas Mercu Buana Yogyakarta, Department of Information System, Faculty of Information Technology, Indonesia | N6: This research develops virtual reality that integrates media elements such as sound, animation, and video with virtual world to create an immersive user experience. It is aimed to provide more interactivities and interesting features in supporting learning activities, such as using Cardboard to observe the virtual world and interact with virtual objects. Previously, a prototype was built to evaluate (high school) students' interests in using virtual reality technology as a supporting media to learn English language subject at high schools in Yogyakarta. Earlier research shows that students agreed to use of virtual reality prototype had been useful to support their learning activities. In this present research, a mobile application prototype is developed and evaluated using TAM methodology in order to understand the user behavior towards the application. The application of TAM in the field of learning and teaching for various learning domains implemented to understand the acceptance from the users while using Virtual Reality-based learning media. The TAM model It is a model can explain that the user's point of view will determine their attitude in accepting Virtual Reality-based learning applications. The evaluation results from this study showed that respondent is enjoyable to use this application (4.37 mean point) and 3.98 (mean point) feels that Virtual reality application is useful for learning English. © 2022 IEEE. | O6: Learning Evaluation; Mobile Application; Virtual Reality | P6: Acceptability; Application; Education; English; Evaluation; Media; Research; Technology; Behavioral research; E-learning; Mobile computing; Software prototyping; English Learning; Immersive; Interactivity; Learning Activity; Learning evaluations; Mobile applications; Users' acceptance; Users' experiences; Virtual objects; Virtual worlds; Virtual reality | Q6: Institute of Electrical and Electronics Engineers Inc. | R6: English | S6: Conference paper | T6: Final | V6: Scopus | W6: Accepted | X6: Relevant | Y6: Basic education | Z6: Ahsan | AA6: Joao | AC6: Check | AD6: Device used: Android smartphones with Google Cardboard​ . Type of XR: Mobile-based Virtual Reality (VR)​ | AE6: Technology Acceptance Model (TAM)​ : Measured: Personal Innovativeness, Perceived Enjoyment, Perceived Ease of Use, Perceived Usefulness, Intention to Use. | AF6: Students: Reported high enjoyment (mean 4.43/5)​ . Found the app easy to use (mean 4.37/5) and useful (mean 3.89/5)​ . Expressed interest in continuing to use the VR application for learning (mean 4.19/5)​ . Teachers: Not directly evaluated, but the VR system is proposed as an additional tool for classroom activities​ | AG6: Metrics from TAM model: Personal Innovativeness (PI): 4.14/5. Perceived Enjoyment (PE): 4.43/5. Perceived Ease of Use (PEOU): 4.37/5. Perceived Usefulness (PU): 3.89/5. Intention to Use (ITU): 4.19/5​ | AH6: Software/Platform: VR mobile app developed based on a game storyboard​ . Hardware: Android smartphones + Google Cardboard​ . Backend: API integration for dynamic question delivery into the VR world​ . | AL6: English Language | AM6: Ahsan | AN6: Check | AO6: Lamarck | AR6: Indonesia | AS6: Asia | AT6: Upper secondary | AU6: Typical learners (high school, Yogyakarta) | AV6: Arts & humanities (languages) | AW6: English as a foreign language | AX6: VR | AY6: HMD (immersive) | AZ6: HMD – mobile (Cardboard) | BA6: None | BB6: Not measured | BC6: + | BD6: Not measured | BE6: 'Motivated me to learn English' M = 3.93; 'app appeals to me' M = 4.43; PI 4.14; PEOU ≈ 4.37 (/5) | BF6: Descriptive only | BG6: Not reported | BH6: TAM questionnaire, 11 items (adopted from prior validated studies; no reliability reported) | BI6: Adapted | BJ6: Single-group post-test only | BK6: Single group, post-test only | BL6: Quantitative descriptive | BM6: 30 high-school students | BN6: Single trial (duration NR) | BO6: =IF(COUNTIF('MMAT Appraisal'!$A$2:$A$60,A6)=0,"",INDEX('MMAT Appraisal'!$K$2:$K$60,MATCH(A6,'MMAT Appraisal'!$A$2:$A$60,0))) -> 2 | BP6: =IF(OR(BF6="No empirical data",ISNUMBER(SEARCH("RETRACTED",BV6))),"Not rated",IF(AND(ISNUMBER(BO6),BO6<=2),"Low",IF(AND(OR(BJ6="RCT",BJ6="Quasi-experimental with control"),LEFT(BF6,11)="Inferential",OR(BI6="Yes",BI6="Partly"),OR(BO6="",BO6>=4)),"High",IF(OR(BA6<>"None",LEFT(BF6,11)="Inferential"),"Moderate","Low")))) -> Low | BQ6: Not reported | BR6: Not reported | BS6: Core | BT6: Basic-education learners with empirical E/M/S data | BU6: Verified (full text) | BV6: Motivation rests on single items
A7: 6 | C7: Cha S.; Tian Y.; Shaalan M.; Hyun J.; Lee K.H. | D7: Cha, Sangwhan (57215595531); Tian, Yunze (57468830700); Shaalan, Majid (57215597624); Hyun, Jeongwoo (57468060800); Lee, Ki H. (57468366200) | E7: 57215595531; 57468830700; 57215597624; 57468060800; 57468366200 | F7: Implementation of Prototype Environment of Virtual Reality Platform for Virtual Lab (Use case of ESL) | G7: 2021 | H7: Proceedings - 2021 IEEE International Conference on Big Data, Big Data 2021 | I7: 1 | J7: 10.1109/BigData52589.2021.9671565 | K7: https://www.scopus.com/inward/record.uri?eid=2-s2.0-85125346674&doi=10.1109%2fBigData52589.2021.9671565&partnerID=40&md5=3262ab5eaab21d93720caab5df6984db | L7: Harrisburg University of Science and Technology, Computer Information Science, Harrisburg, United States; Cornell University, Computer Science, New York, NY, United States | M7: Cha S., Harrisburg University of Science and Technology, Computer Information Science, Harrisburg, United States; Tian Y., Harrisburg University of Science and Technology, Computer Information Science, Harrisburg, United States; Shaalan M., Harrisburg University of Science and Technology, Computer Information Science, Harrisburg, United States; Hyun J., Cornell University, Computer Science, New York, NY, United States; Lee K.H., Harrisburg University of Science and Technology, Computer Information Science, Harrisburg, United States | N7: Virtual learning platforms have extended the learning experience beyond the constraints of space and time. Learning new language skills in virtual environments is becoming more and more convenient and efficient. In this work, learning English as a second language (ESL) is tested. Initial results showed that it is not only efficient to learn ESL with this tool, but it also helped users to develop good interaction skills with the computer-generated 3D world without any fear or shyness. Current virtual learning platforms suffers from distraction inherited by designing learning activities that requires user interaction, such as pressing the keyboard and clicking the mouse to control the avatar and background. In our research work, we employed a new software implementation stack that include a unity virtual environment, an applied Speech Recognition (SR) capability, and a Natural Language Processing (NLP) component to overcome these distractions and improve the Human-Computer Interaction (HCI) capability without the need for a keyboard and mouse for the dynamic avatar's movement and backgrounds. © 2021 IEEE. | O7: Natural Language Processing; Speech Recognition; Unity; Virtual Education; Virtual Reality | P7: E-learning; Human computer interaction; Natural language processing systems; Space platforms; Speech recognition; User interfaces; English as a second languages (ESL); Learn+; Learning English; Learning experiences; Learning platform; Space and time; Unity; Virtual education; Virtual lab; Virtual learning; Virtual reality | Q7: Institute of Electrical and Electronics Engineers Inc. | R7: English | S7: Conference paper | T7: Final | V7: Scopus | W7: Accepted | X7: Relevant | Y7: Basic education | Z7: Ahsan | AA7: Joao | AC7: Check | AD7: Device used: PC-based VR system using Unity environments​ . Type of XR: Fully immersive VR environment. Not specified as a commercial device like Oculus or CAVE, but assumed PC and screen setup​ . | AE7: No formal survey like SUS or TAM. Evaluation Method: Scenario-based observation: measuring reaction time and system responsiveness​ . | AF7: Students: Reported more efficient language learning. Felt more natural communication without keyboards/mouse. Improved engagement and reduction of shyness​ . Teachers: Acted as participants in conversations but not formally evaluated. | AG7: Metrics: System reaction time (latency from command to avatar movement)​ . User qualitative feedback on naturalness of conversation and interaction. | AH7: Software/Platform: Unity for 3D virtual environment​ . Python with Natural Language Toolkit (NLTK) for processing speech​ . Speech Recognition libraries to interpret voice commands​ . MySQL database for event and command logging​ . Hardware: PC setup (no specific VR headset detailed)​ | AL7: English Language | AM7: Joao | AN7: Check - No specified commercial VR device | AO7: Pedro | AR7: USA | AS7: North America | AT7: Not reported | AU7: None (two researchers acting as teacher/student) | AV7: Arts & humanities (languages) | AW7: English as a second language | AX7: VR | AY7: Desktop | AZ7: Desktop VR (Unity on PC screen; speech input) | BA7: None | BB7: Not measured | BC7: Not measured | BD7: Not measured | BE7: Only avatar latency to voice commands tested in predefined scenarios | BF7: No empirical data | BG7: Not reported | BH7: None | BI7: N/A | BJ7: Technical prototype evaluation | BK7: No empirical learner study | BL7: Not appraisable (no empirical learner study) | BM7: 0 learners | BN7: N/A | BO7: =IF(COUNTIF('MMAT Appraisal'!$A$2:$A$60,A7)=0,"",INDEX('MMAT Appraisal'!$K$2:$K$60,MATCH(A7,'MMAT Appraisal'!$A$2:$A$60,0))) | BP7: =IF(OR(BF7="No empirical data",ISNUMBER(SEARCH("RETRACTED",BV7))),"Not rated",IF(AND(ISNUMBER(BO7),BO7<=2),"Low",IF(AND(OR(BJ7="RCT",BJ7="Quasi-experimental with control"),LEFT(BF7,11)="Inferential",OR(BI7="Yes",BI7="Partly"),OR(BO7="",BO7>=4)),"High",IF(OR(BA7<>"None",LEFT(BF7,11)="Inferential"),"Moderate","Low")))) -> Not rated | BQ7: Not reported | BR7: Not reported | BS7: Excluded | BT7: E2: No learner data (technical latency test only) | BU7: Verified (full text) | BV7: No learner data; 'efficient learning / less shyness' claims in abstract are not supported by any study
A8: 7 | C8: Ali A.; Shahid Z.; Mirza N.M.; Iqbal S. | D8: Ali, Adnan (57468833300); Shahid, Zainab (57215306478); Mirza, Nada Masood (59109801800); Iqbal, Saqib (57212034484) | E8: 57468833300; 57215306478; 59109801800; 57212034484 | F8: Comparison and enhancement of VR water cycle guide applications | G8: 2021 | H8: 2021 22nd International Arab Conference on Information Technology, ACIT 2021 | I8: 0 | J8: 10.1109/ACIT53391.2021.9677136 | K8: https://www.scopus.com/inward/record.uri?eid=2-s2.0-85125306776&doi=10.1109%2fACIT53391.2021.9677136&partnerID=40&md5=16472fef46bf1b3d20d096e99bcc434b | L8: IT Center, Al Ain University, Al Ain, United Arab Emirates; Al Ain, United Arab Emirates; University College, United Arab Emirates University, Al Ain, United Arab Emirates; College of Engineering, Al Ain University, Al Ain, United Arab Emirates | M8: Ali A., IT Center, Al Ain University, Al Ain, United Arab Emirates; Shahid Z., Al Ain, United Arab Emirates; Mirza N.M., University College, United Arab Emirates University, Al Ain, United Arab Emirates; Iqbal S., College of Engineering, Al Ain University, Al Ain, United Arab Emirates | N8: Humankind has witnessed magnificent outcomes since technology has become part of education at all levels. This paper discusses the application of a newly hyped technology in education called Virtual Reality (VR). Virtual reality is a blend of technologies to provide an interface with a virtual environment. This technology is becoming a vital part of educational applications because educators always tend to lean towards anything which can be beneficial in bringing ease in the explanation of certain topics. It will also not be wrong to say that the usage of such kind of technology is now imperative in comprehending abstract and complex concepts of the present modules of education. In this article, a discussion and comparison have been presented on existing VR-based educational applications, along with a discussion on the development of a new VR application. The purpose of this study was to amplify the structure of the virtual way of explaining concepts to the younger students. The newly developed application improves upon the existing applications and presents an enhanced learning platform. According to the survey conducted from the application users, it can be easily deduced that the developed application had a better rating in the user interface as compared to the already existing ones, and its clearly visible that the VR has made it very simple for the younger kids to view and understand the overall concept of water cycle easily. © 2021 IEEE. | O8: E-learning; Virtual reality; Water cycle | P8: Abstracting; Engineering education; User interfaces; Virtual reality; Developed applications; E - learning; Educational Applications; Enhanced learning; Learning platform; Simple++; Technology in educations; Water cycle; E-learning | Q8: Institute of Electrical and Electronics Engineers Inc. | R8: English | S8: Conference paper | T8: Final | V8: Scopus | W8: Accepted | X8: Relevant | Y8: Basic education | Z8: Ahsan | AA8: Joao | AC8: Check | AD8: Device used: Mobile VR headsets (e.g., Google Cardboard, or similar VR viewers for smartphones)​ . Type of XR: Mobile-based Virtual Reality (VR)​ | AE8: User Survey: Questions evaluated fun, comfort, clarity of text, perception of sounds/visuals, and intent to reuse the app​ | AF8: Students: Reported having fun, enjoying visuals/sounds, and feeling comfortable using VR​ . Easier understanding of the water cycle compared to traditional learning​ . Teachers: Not formally assessed, but VR is suggested as a tool to enhance teaching. | AG8: Metrics: User experience survey with yes/no/don't know options. Evaluated engagement, understanding, and comfort level​ | AH8: Software/Platform: Custom-built VR app with Unity3D​ . Hardware: Smartphones + Google Cardboard or similar VR devices​ . Special Features: Robot Companion acting as a guide through the VR environment​ . Text explanations, animations, and a mini educational game​ | AL8: General Education | AM8: Lamarck | AN8: Check | AO8: Ahsan | AR8: United Arab Emirates | AS8: Asia | AT8: Not reported | AU8: School children ('younger kids'; age NR) | AV8: Natural sciences, mathematics & statistics | AW8: Earth science (water cycle) | AX8: VR | AY8: Not reported | AZ8: VR app; headset type not stated | BA8: None | BB8: Not measured | BC8: + | BD8: + | BE8: ≈90% 'had fun', ≈95% saw/heard something entertaining; ≈95% would use again; only ≈50% found text clear | BF8: Descriptive only | BG8: Not reported | BH8: Author-made 6-item yes / don't know / no survey | BI8: No | BJ8: Single-group post-test only | BK8: Single group, post-test only | BL8: Quantitative descriptive | BM8: Not reported (survey in 'multiple schools') | BN8: Single use (duration NR) | BO8: =IF(COUNTIF('MMAT Appraisal'!$A$2:$A$60,A8)=0,"",INDEX('MMAT Appraisal'!$K$2:$K$60,MATCH(A8,'MMAT Appraisal'!$A$2:$A$60,0))) -> 0 | BP8: =IF(OR(BF8="No empirical data",ISNUMBER(SEARCH("RETRACTED",BV8))),"Not rated",IF(AND(ISNUMBER(BO8),BO8<=2),"Low",IF(AND(OR(BJ8="RCT",BJ8="Quasi-experimental with control"),LEFT(BF8,11)="Inferential",OR(BI8="Yes",BI8="Partly"),OR(BO8="",BO8>=4)),"High",IF(OR(BA8<>"None",LEFT(BF8,11)="Inferential"),"Moderate","Low")))) -> Low | BQ8: Text hard to read for many | BR8: Usability, behavioural or safety issues only | BS8: Core | BT8: Basic-education learners with empirical E/M/S data | BU8: Verified (full text) | BV8: Comparison with other apps is a feature table, not a learner comparison; results only as bar chart %; N not reported
A9: 8 | C9: Carruth D.W.; Hudson C.; Fox A.A.A.; Deb S. | D9: Carruth, Daniel W. (6506142566); Hudson, Christopher (57193952917); Fox, Amelia A. A. (54787700100); Deb, Shuchisnigdha (58973314700) | E9: 6506142566; 57193952917; 54787700100; 58973314700 | F9: User Interface for an Immersive Virtual Reality Greenhouse for Training Precision Agriculture | G9: 2020 | H9: Lecture Notes in Computer Science (including subseries Lecture Notes in Artificial Intelligence and Lecture Notes in Bioinformatics) | I9: 9 | J9: 10.1007/978-3-030-49698-2_3 | K9: https://www.scopus.com/inward/record.uri?eid=2-s2.0-85089164020&doi=10.1007%2f978-3-030-49698-2_3&partnerID=40&md5=7860795cd09e9cb1eea31b3127280326 | L9: Mississippi State University, 39762, MS, United States; The University of Texas at Arlington, Arlington, 76019, TX, United States | M9: Carruth D.W., Mississippi State University, 39762, MS, United States; Hudson C., Mississippi State University, 39762, MS, United States; Fox A.A.A., Mississippi State University, 39762, MS, United States; Deb S., The University of Texas at Arlington, Arlington, 76019, TX, United States | N9: In the past 50 years, farm producers have increased use of electronic control systems for controlled environment agriculture in greenhouses and animal production. These systems use environmental sensors to automate environmental management of greenhouses and can lead to significantly larger yields. However, mismanagement of a CEA system can also lead to loss of entire crops. Due to the sensitivity of crops in CEA and potential losses, students are rarely allowed to work directly with CEA systems. In order to increase opportunities for students to interact with CEA systems, an immersive virtual greenhouse simulation was created. Implementing realistic interfaces for physical tasks and for the CEA system provides students with ‘hands-on’ training in the virtual greenhouse. However, there are challenges that limit implementation of physical actions and realistic interfaces in virtual reality. We consider interfaces for three types of interactions: system interactions, physical greenhouse interactions, and interactions with the CEA system. Potential interface designs are presented with a discussion of the benefits and costs associated with each design. © 2020, Springer Nature Switzerland AG. | O9: Design issues; Education; User interaction in VR and MR; Virtual reality applications | P9: Agricultural robots; Crops; E-learning; Electronics industry; Environmental management; Greenhouses; Human computer interaction; Mixed reality; Precision agriculture; Students; Benefits and costs; Controlled environment agricultures; Electronic control systems; Environmental sensor; Immersive virtual reality; Interface designs; Realistic interfaces; System interactions; User interfaces | Q9: Springer | R9: English | S9: Conference paper | T9: Final | V9: Scopus | W9: Accepted | X9: Relevant | Y9: Basic education | Z9: Ahsan | AA9: Joao | AC9: Check | AD9: Device used: PC-based VR system with standard VR headsets (e.g., Oculus Rift, HTC Vive — specific model not mentioned)​ . Type of XR: Immersive Virtual Reality (VR)​ | AE9: Scenario-based evaluations: Student performance judged by success in greenhouse tasks (e.g., planting, environmental control, pest management)​ . No formal survey like SUS or TAM was applied. | AF9: Students: Gained practical skills in managing complex agricultural systems. Allowed safe practice with environmental control settings​ . Teachers: Act as assignment supervisors through the LMS; no direct evaluation of their experience was reported​ . | AG9: Metrics: Success in plant growth management. Detection of pest infestations. Achievement of production targets (biomass and profit)​ . Evaluation: Based on completion of learning assignments and accuracy in simulation tasks​ . | AH9: Software/Platform: Unity3D for VR development​ . Learning Management System (LMS) integration​ . Hardware: VR headset (unspecified model) + VR-capable PC​ . Special Features: Skeuomorphic UI: realistic physical interactions (planting, watering). Electronic Control System (ECS) simulation: managing virtual climate and crop development​ . Options for different ECS interfaces (wall-mounted, tablet-based, floating panel)​ | AL9: Agriculture | AM9: Pedro | AN9: Check. For RQ2 an LMS records student activities but does not mention specific user assessment tools or instruments. | AO9: Joao | AR9: USA | AS9: North America | AT9: Higher education | AU9: None (design paper) | AV9: Agriculture | AW9: Precision agriculture (greenhouse) | AX9: VR | AY9: HMD (immersive) | AZ9: HMD – PC-tethered | BA9: None | BB9: Not measured | BC9: Not measured | BD9: Not measured | BE9: Interface design options only; no user testing | BF9: No empirical data | BG9: Not reported | BH9: None | BI9: N/A | BJ9: Design/development only | BK9: No empirical learner study | BL9: Not appraisable (no empirical learner study) | BM9: 0 | BN9: N/A | BO9: =IF(COUNTIF('MMAT Appraisal'!$A$2:$A$60,A9)=0,"",INDEX('MMAT Appraisal'!$K$2:$K$60,MATCH(A9,'MMAT Appraisal'!$A$2:$A$60,0))) | BP9: =IF(OR(BF9="No empirical data",ISNUMBER(SEARCH("RETRACTED",BV9))),"Not rated",IF(AND(ISNUMBER(BO9),BO9<=2),"Low",IF(AND(OR(BJ9="RCT",BJ9="Quasi-experimental with control"),LEFT(BF9,11)="Inferential",OR(BI9="Yes",BI9="Partly"),OR(BO9="",BO9>=4)),"High",IF(OR(BA9<>"None",LEFT(BF9,11)="Inferential"),"Moderate","Low")))) -> Not rated | BQ9: Not reported | BR9: Not reported | BS9: Excluded | BT9: E2: No learner data (interface design paper) | BU9: Verified (full text) | BV9: No learner outcome data – design paper
A10: 9 | C10: Brenner C.; Desportes K.; Hendrix J.O.; Holford M. | D10: Brenner, Corinne (57203360592); Desportes, Kayla (57189295760); Hendrix, Jessica Ochoa (59158102800); Holford, Mande (6603644816) | E10: 57203360592; 57189295760; 59158102800; 6603644816 | F10: Work-in-Progress-GeoForge: Integrating Virtual Reality and a Personalized Website to Foster Collaboration in Middle School Science | G10: 2020 | H10: Proceedings of 6th International Conference of the Immersive Learning Research Network, iLRN 2020 | I10: 1 | J10: 10.23919/iLRN47897.2020.9155098 | K10: https://www.scopus.com/inward/record.uri?eid=2-s2.0-85091671712&doi=10.23919%2fiLRN47897.2020.9155098&partnerID=40&md5=c435c67f50260aa89dae3b470ab8e747 | L10: Director of Learning Killer Snails, New York, United States; New York University, Educational Comm. and Tech, New York, United States; Killer Snails, New York, United States | M10: Brenner C., Director of Learning Killer Snails, New York, United States; Desportes K., New York University, Educational Comm. and Tech, New York, United States; Hendrix J.O., Killer Snails, New York, United States; Holford M., Killer Snails, New York, United States | N10: Virtual reality (VR) has the potential to foster collaborative science learning, but guidelines for designing in this medium are lacking. This work-in-progress paper explores this gap in the literature through analysis of GeoForge, a multiple-player VR/digital learning experience where users collaboratively explore planetary systems. A mixed-methods study at 3 middle schools used teacher interviews, student survey responses, and student work to examine how GeoForge encouraged information exchange and reflection within small student groups. Our findings indicate students shared ideas and resources, engaged in co-construction, and teachers recognized high student engagement throughout the experience. © 2020 Immersive Learning Research Network. | O10: collaborative learning; Google cardboard; middle school; STEM education; virtual reality | P10: User experience; Virtual reality; Information exchanges; Learning experiences; Middle school science; Planetary system; Science learning; Student engagement; Student surveys; Work in progress; Students | Q10: Institute of Electrical and Electronics Engineers Inc. | R10: English | S10: Conference paper | T10: Final | V10: Scopus | W10: Accepted | X10: Relevant | Y10: Basic education | Z10: Ahsan | AA10: Joao | AC10: Should WIP pappers be accepted? | AD10: Device used: Google Cardboard VR headsets (cheap, mobile VR)​ . Type of XR: Mobile-based Virtual Reality + web-based Digital Science Journal (DSJ)​ | AE10: Post-experience student survey: 5-point Likert scale on engagement, collaboration, learning experience​ . Teacher interviews​ . Analysis of student journal entries (content analysis for idea sharing and co-construction)​ | AF10: Students: Showed higher engagement and collaborative behaviors​ . Practiced sharing ideas, problem solving, and exploration in the VR world. Teachers: Noted increased interest and better classroom dynamics, even among students who usually struggled​ . | AG10: Survey results: Mean scores around 3.9–4.0 (out of 5) for collaborative behaviors​ . Content analysis of student responses (sharing, co-construction of knowledge). | AH10: Software/Platform: Custom VR app built to run with Google Cardboard​ . Personalized Digital Science Journal (DSJ) on a web platform​ . Hardware: Smartphones + Google Cardboard​ | AL10: STEM | AM10: Ahsan | AN10: Check | AO10: Lamarck | AR10: USA | AS10: North America | AT10: Mixed K-12 | AU10: Typical learners, grades 5–8 (3 schools) + 5 teachers | AV10: Natural sciences, mathematics & statistics | AW10: Earth & space science (planetary systems) | AX10: VR | AY10: HMD (immersive) | AZ10: HMD – mobile (Cardboard) | BA10: None | BB10: + | BC10: + | BD10: Not measured | BE10: Collaborative behaviours M = 3.12–3.98/5; all teachers reported high engagement/interest (incl. usually disengaged students) | BF10: Descriptive only | BG10: Not reported | BH10: Post-survey with items adapted from 'What Happened in the Groups'; teacher interviews (1 coder); journal entries | BI10: Adapted | BJ10: Mixed methods (single group) | BK10: Single group, mixed methods / DBR | BL10: Qualitative | BM10: 220 students; 5 teachers | BN10: One class period (~45 min) | BO10: =IF(COUNTIF('MMAT Appraisal'!$A$2:$A$60,A10)=0,"",INDEX('MMAT Appraisal'!$K$2:$K$60,MATCH(A10,'MMAT Appraisal'!$A$2:$A$60,0))) -> 4 | BP10: =IF(OR(BF10="No empirical data",ISNUMBER(SEARCH("RETRACTED",BV10))),"Not rated",IF(AND(ISNUMBER(BO10),BO10<=2),"Low",IF(AND(OR(BJ10="RCT",BJ10="Quasi-experimental with control"),LEFT(BF10,11)="Inferential",OR(BI10="Yes",BI10="Partly"),OR(BO10="",BO10>=4)),"High",IF(OR(BA10<>"None",LEFT(BF10,11)="Inferential"),"Moderate","Low")))) -> Low | BQ10: Students reluctant to read instructions | BR10: Usability, behavioural or safety issues only | BS10: Core | BT10: Basic-education learners with empirical E/M/S data | BU10: Verified (full text) | BV10: Engagement/motivation evidence is teacher-reported (interviews); convenience sample of 3 schools; work-in-progress
A11: 10 | C11: Bozzelli G.; Raia A.; Ricciardi S.; De Nino M.; Barile N.; Perrella M.; Tramontano M.; Pagano A.; Palombini A. | D11: Bozzelli, Guido (57211374072); Raia, Antonio (57211377379); Ricciardi, Stefano (9734702300); De Nino, Maurizio (23026644900); Barile, Nicola (57500936500); Perrella, Marco (57211377331); Tramontano, Marco (57211376728); Pagano, Alfonsina (55547435300); Palombini, Augusto (56080829100) | E11: 57211374072; 57211377379; 9734702300; 23026644900; 57500936500; 57211377331; 57211376728; 55547435300; 56080829100 | F11: An integrated VR/AR framework for user-centric interactive experience of cultural heritage: The ArkaeVision project | G11: 2019 | H11: Digital Applications in Archaeology and Cultural Heritage | I11: 103 | J11: 10.1016/j.daach.2019.e00124 | K11: https://www.scopus.com/inward/record.uri?eid=2-s2.0-85073688888&doi=10.1016%2fj.daach.2019.e00124&partnerID=40&md5=2d25bfe8c53a320588b58857c7b316dd | L11: Digitalcomoedia, Naples, IT, Italy; CNR, Institute of Technologies applied to Cultural Heritage, Rome, IT, Italy; Department of Biosciences and Territory (DiBT) - University of Molise, Italy | M11: Bozzelli G., Digitalcomoedia, Naples, IT, Italy; Raia A., Digitalcomoedia, Naples, IT, Italy; Ricciardi S., Department of Biosciences and Territory (DiBT) - University of Molise, Italy; De Nino M., Digitalcomoedia, Naples, IT, Italy; Barile N., Digitalcomoedia, Naples, IT, Italy; Perrella M., Digitalcomoedia, Naples, IT, Italy; Tramontano M., Digitalcomoedia, Naples, IT, Italy; Pagano A., CNR, Institute of Technologies applied to Cultural Heritage, Rome, IT, Italy; Palombini A., CNR, Institute of Technologies applied to Cultural Heritage, Rome, IT, Italy | N11: The ArkaeVision project is aimed at enabling a new way of enjoying Cultural Heritage through a more engaging and culturally-qualified user experience. The main goal is the creation of a technological infrastructure for the permanent enhancement of cultural resources. Hence, ArkaeVision represents a user-centric integrated system able to offer different modalities of exploitation of Cultural Heritage assets, including virtual representations of monuments, works of art and objects, as well as the stories associated to them. ArkaeVision therefore introduces a new communication paradigm, made of game-alike exploration of a 3D environment, virtually reconstructed, with elements of digital fiction and an engaging stortytelling, applied to two case studies: the exploration of the Hera II Temple of Paestum with Virtual Reality (VR) technology, and the exploration of the slab of the Swimmer Tomb with Augmented Reality (AR). The emotional component is fundamental in ArkaeVision, because it generates the motivation and leads people to use immersive viewers, as the HTC Vive, which allow the learning process to be activated more quickly, as many cognitivists and psychologists reported in the latest researches. Also the involvement of users through gamification is well expressed in ArkaeVision. This model of action (and interaction) designed for the public allows to emphasize the role of users through a system that is “guided” by their choices and times, in order to increase users’ engagement within the virtual exploration, and favour the content understanding by direct experience. Evaluations conducted on a preliminary prototype suggested that the communicative approach is very promising for education and engagement into cultural heritage experiences. © 2019 | O11: Augmented reality; Digital storytelling; Gamification; User experience design; Virtual reality | Q11: Elsevier Ltd | R11: English | S11: Article | T11: Final | V11: Scopus | W11: Accepted | X11: Relevant | Y11: Basic education | Z11: Ahsan | AA11: Joao | AC11: Not Graduate level or Basic Education level metioned | AD11: Devices used: HTC Vive VR headset (for immersive VR at archaeological sites)​ . Mobile devices (smartphones/tablets) for AR experiences​ . Type of XR: Immersive Virtual Reality (VR). Augmented Reality (AR)​ | AE11: User Experience (UX) evaluations: Observations during usage​ . Paper-based questionnaires assessing engagement, usability, and knowledge​ . No formal scales like SUS or TAM mentioned, but structured feedback collection was applied. | AF11: Users (general public and students): Expressed high engagement and positive emotional response​ . Enjoyed the interactive storytelling and immersive exploration​ . Participants showed increased interest in historical knowledge​ . Teachers: Teachers and museum staff supported the educational value but were not directly assessed. | AG11: Metrics: Observational analysis (comfort, interaction fluency). Questionnaire data on preferences (e.g., favorite elements like storytelling, visuals)​ . Engagement scores based on participation and exploration behaviors. | AH11: Software/Platform: Custom-built platform ("ArkaeVision"). Unity 3D for VR/AR experiences​ . Real-time engines, gesture recognition, cybernetic glove interaction​ . Hardware: HTC Vive for VR​ . Smartphones/tablets for AR​ . Interaction tech: Behavior trees and finite-state machines for dynamic interaction​ . Gamification mechanics (rewards, points, challenges) integrated into the platform​ | AL11: History and Cultural | AM11: Joao | AO11: Pedro | AR11: Italy | AS11: Europe | AT11: Informal / general public | AU11: Museum visitors (mean age ≈30; from high schools & universities) | AV11: Arts & humanities (history/heritage) | AW11: Cultural heritage / archaeology | AX11: VR | AY11: HMD (immersive) | AZ11: HMD – PC-tethered (HTC Vive) | BA11: None | BB11: + | BC11: + | BD11: + | BE11: 89% stayed for the full experience; 98% felt emotionally involved; overall rating 9/10; interaction natural 88% | BF11: Descriptive only | BG11: Not reported | BH11: Author-made paper questionnaire + observation protocol | BI11: No | BJ11: Single-group post-test only | BK11: Single group, post-test only | BL11: Quantitative descriptive | BM11: 70 visitors | BN11: Single short demo session | BO11: =IF(COUNTIF('MMAT Appraisal'!$A$2:$A$60,A11)=0,"",INDEX('MMAT Appraisal'!$K$2:$K$60,MATCH(A11,'MMAT Appraisal'!$A$2:$A$60,0))) -> 3 | BP11: =IF(OR(BF11="No empirical data",ISNUMBER(SEARCH("RETRACTED",BV11))),"Not rated",IF(AND(ISNUMBER(BO11),BO11<=2),"Low",IF(AND(OR(BJ11="RCT",BJ11="Quasi-experimental with control"),LEFT(BF11,11)="Inferential",OR(BI11="Yes",BI11="Partly"),OR(BO11="",BO11>=4)),"High",IF(OR(BA11<>"None",LEFT(BF11,11)="Inferential"),"Moderate","Low")))) -> Low | BQ11: Motion sickness noted as a limitation | BR11: Cybersickness / physical discomfort reported | BS11: Sensitivity | BT11: Outside basic education: Adult museum visitors (mean age ≈ 30) | BU11: Verified (full text) | BV11: Informal museum setting, mostly adults; only the VR part was evaluated (AR not tested)
A12: 11 | C12: Daineko Y.; Ipalakova M.; Tsoy D.; Shaipiten A.; Bolatov Z.; Chinibayeva T. | D12: Daineko, Yevgeniya (36060995800); Ipalakova, Madina (56912288100); Tsoy, Dana (57203037057); Shaipiten, Akmedi (57203040710); Bolatov, Zhiger (57194322791); Chinibayeva, Tolganay (57203033842) | E12: 36060995800; 56912288100; 57203037057; 57203040710; 57194322791; 57203033842 | F12: Development of practical tasks in physics with elements of augmented reality for secondary educational institutions | G12: 2018 | H12: Lecture Notes in Computer Science (including subseries Lecture Notes in Artificial Intelligence and Lecture Notes in Bioinformatics) | I12: 10 | J12: 10.1007/978-3-319-95270-3_34 | K12: https://www.scopus.com/inward/record.uri?eid=2-s2.0-85050366011&doi=10.1007%2f978-3-319-95270-3_34&partnerID=40&md5=f6918b1700b8658fed0824b136db3094 | L12: Department of Computer Engineering and Telecommunication, International IT University, Almaty, 050040, Kazakhstan | M12: Daineko Y., Department of Computer Engineering and Telecommunication, International IT University, Almaty, 050040, Kazakhstan; Ipalakova M., Department of Computer Engineering and Telecommunication, International IT University, Almaty, 050040, Kazakhstan; Tsoy D., Department of Computer Engineering and Telecommunication, International IT University, Almaty, 050040, Kazakhstan; Shaipiten A., Department of Computer Engineering and Telecommunication, International IT University, Almaty, 050040, Kazakhstan; Bolatov Z., Department of Computer Engineering and Telecommunication, International IT University, Almaty, 050040, Kazakhstan; Chinibayeva T., Department of Computer Engineering and Telecommunication, International IT University, Almaty, 050040, Kazakhstan | N12: The current work demonstrates the use of augmented reality technology for the development of an application that can be employed as an additional teaching tool within physics in secondary educational institutions in Kazakhstan. The application contains a set of problem tasks in “Mechanics”. The physical processes within tasks are visualized with help of augmented reality and this helps pupils to imagine and understand deeper the studied phenomena. One of the advantages and distinctive features of the developed application is that it provides the user interface in Kazakh, Russian and English languages. This corresponds to the multilingual policy adopted by the government of the country. In the article the existing analogs worldwide are presented, development software is described and the main results of the project are discussed. © Springer International Publishing AG, part of Springer Nature 2018. | O12: Augmented reality; Physics; Secondary education | P12: Physics; User interfaces; Virtual reality; Augmented reality technology; Developed applications; Educational institutions; English languages; Kazakhstan; Physical process; Teaching tools; Augmented reality | Q12: Springer Verlag | R12: English | S12: Conference paper | T12: Final | V12: Scopus | W12: Accepted | X12: Relevant | Y12: Basic education | Z12: Ahsan | AA12: Joao | AC12: Check | AD12: Augmented Reality (AR) via mobile or webcam-based systems. No VR headsets or CAVE VR systems were used. Marker-based AR using Vuforia with camera input and Unity 3D. | AE12: Survey of 20 ninth-grade students: Question: “Is the AR application effective as a supplementary learning tool for physics?” Results: 89% said it was "rather effective" or "very effective". | AF12: Effects on students: Increased motivation and interest in physics. Improved visual comprehension of complex concepts. Ability to manipulate parameters and observe real-time results increased involvement. Effects on teachers (implied): Supplementary tool for teaching difficult physics concepts. Facilitates multilingual education (app supports Kazakh, Russian, and English). | AG12: Qualitative survey results: Effectiveness perception by students. Observations: Use of AR during task simulations and interaction with variables like velocity and angle. No quantitative learning outcome metrics reported (e.g., test scores). | AH12: Technologies used: Unity 3D: for AR environment and interface development. Vuforia: for AR marker recognition and 3D object anchoring. C# and Blender: for scripting behavior and 3D modeling. Interactive 3D components: Sliders, variable inputs, visual arrows for forces and trajectories. | AL12: STEM | AM12: Lamarck | AO12: Ahsan | AP12: Yevgeniya | AQ12: yevgeniyadaineko@gmail.com | AR12: Kazakhstan | AS12: Asia | AT12: Lower secondary | AU12: Typical learners | AV12: Natural sciences, mathematics & statistics | AW12: Physics (mechanics), grade 9 | AX12: AR | AY12: Desktop | AZ12: Computer application with AR (camera type not stated) | BA12: None | BB12: Not measured | BC12: + | BD12: Not measured | BE12: Perceived effectiveness: 61.6% very, 27.4% rather effective | BF12: Descriptive only | BG12: Not reported | BH12: Single interview question on effectiveness | BI12: No | BJ12: Development + single-group survey | BK12: Single group, post-test only | BL12: Quantitative descriptive | BM12: 20 pupils (grade 9) | BN12: NR | BO12: =IF(COUNTIF('MMAT Appraisal'!$A$2:$A$60,A12)=0,"",INDEX('MMAT Appraisal'!$K$2:$K$60,MATCH(A12,'MMAT Appraisal'!$A$2:$A$60,0))) -> 1 | BP12: =IF(OR(BF12="No empirical data",ISNUMBER(SEARCH("RETRACTED",BV12))),"Not rated",IF(AND(ISNUMBER(BO12),BO12<=2),"Low",IF(AND(OR(BJ12="RCT",BJ12="Quasi-experimental with control"),LEFT(BF12,11)="Inferential",OR(BI12="Yes",BI12="Partly"),OR(BO12="",BO12>=4)),"High",IF(OR(BA12<>"None",LEFT(BF12,11)="Inferential"),"Moderate","Low")))) -> Low | BQ12: Not reported | BR12: Not reported | BS12: Core | BT12: Basic-education learners with empirical E/M/S data | BU12: Verified (full text) | BV12: Reported % (e.g., 1.2%, 3.7%) impossible with n = 20 – data inconsistency; motivation = pupils' remarks only
A13: 12 | C13: Stachurska W.; Witoszek-Kubicka A.; Igras-Cybulska M. | D13: Stachurska, Weronika (59139485400); Witoszek-Kubicka, Aleksandra (57218579927); Igras-Cybulska, Magdalena (55658516800) | E13: 59139485400; 57218579927; 55658516800 | F13: Virtual Reality in Music Education: A Qualitative User Study of HarmosphereVR | G13: 2024 | H13: CEUR Workshop Proceedings | I13: 0 | K13: https://www.scopus.com/inward/record.uri?eid=2-s2.0-85196053652&partnerID=40&md5=1b278a73ddc1dbe6730ffbc1504386fd | L13: AGH University of Krakow, Krakow, Poland; Cracow University of Economics, Krakow, Poland | M13: Stachurska W., AGH University of Krakow, Krakow, Poland; Witoszek-Kubicka A., Cracow University of Economics, Krakow, Poland; Igras-Cybulska M., AGH University of Krakow, Krakow, Poland | N13: Harmony is considered one of the most challenging and rigorous subjects in music education. This study focuses on the qualitative evaluation of HarmosphereVR, a virtual reality (VR) prototype designed to support the self-learning of harmony through immersive interactive exercises. The methodology included usability testing, reaction cards, and in-depth interviews to collect comprehensive feedback on the application’s effectiveness and user experience. The evaluation engaged six participants (four male and two female participants); half had previously participated in an exploratory interview to identify challenges and needs in learning harmony at music schools before the application was designed, while the rest of the participants were not acquainted with the project. The findings suggest that VR can serve as an auxiliary tool in music education, providing an engaging and effective platform for mastering complex theoretical concepts. © 2022 Copyright for this paper by its authors. | O13: Harmony; Music Education; Qualitative Evaluation; Reaction cards; User-centered Design; Virtual Reality | P13: E-learning; Music; User centered design; Harmony; Immersive; In-depth interviews; Interactive exercise; Music education; Qualitative evaluations; Reaction card; Self-learning; Usability testing; User study; Virtual reality | Q13: CEUR-WS | R13: English | S13: Conference paper | T13: Final | V13: Scopus | W13: Accepted | X13: InOurScope | Y13: Basic Education | Z13: João | AA13: Lamarck | AB13: Musical Education context | AD13: Technology used: Meta Quest 2 VR headset. 6DOF (six degrees of freedom) VR environment. No use of CAVE VR or desktop/AR environments—this is fully immersive VR. | AE13: Usability testing (observations and interaction logging). Reaction cards (participants selected adjectives to describe their experience). In-depth interviews with structured follow-up questions. Data clustered into themes for qualitative analysis. | AF13: Effects on students: Participants (mostly first-time VR users) had a positive reaction, noting the experience was engaging and easy to learn. Improved conceptual grasp of harmony via immersive sound-visual feedback. Suggested gamification (scores, challenges) could further improve engagement. Effects on teachers (indirect): Offers a complementary tool to traditional methods. Helps address the lack of interactive harmony-focused resources in education. | AG13: Adjective choice frequency (from 39 reaction cards) — e.g., “understandable,” “useful,” “intuitive.” Thematic clustering of feedback from interviews. Observational metrics: time to adapt to controls, task completion, user behavior. No formal numerical scores or knowledge tests reported. | AH13: Technologies used: Unity engine (for application development). Meta Quest 2 (hardware). VR piano keyboard with visual music staff and real-time audio feedback. Smooth locomotion + vignette to reduce motion sickness. | AL13: STEAM | AM13: Ahsan | AP13: Weronika | AQ13: weronasta@student.agh.edu.pl | AR13: Poland | AS13: Europe | AT13: Mixed (secondary + post-secondary) | AU13: Music-school students & recent graduates, ages 18–22 | AV13: Arts & humanities (arts) | AW13: Music (harmony) | AX13: VR | AY13: HMD (immersive) | AZ13: HMD – standalone | BA13: None | BB13: + | BC13: + | BD13: + | BE13: Reaction cards: 'understandable', 'interesting', 'captivating', 'useful'; wanted to use longer; no discomfort | BF13: Qualitative only | BG13: Not reported | BH13: Reaction cards; interviews; observation | BI13: N/A | BJ13: Qualitative user study | BK13: Qualitative | BL13: Qualitative | BM13: 6 participants (ages 18–22) | BN13: One session, ~45 min | BO13: =IF(COUNTIF('MMAT Appraisal'!$A$2:$A$60,A13)=0,"",INDEX('MMAT Appraisal'!$K$2:$K$60,MATCH(A13,'MMAT Appraisal'!$A$2:$A$60,0))) -> 2 | BP13: =IF(OR(BF13="No empirical data",ISNUMBER(SEARCH("RETRACTED",BV13))),"Not rated",IF(AND(ISNUMBER(BO13),BO13<=2),"Low",IF(AND(OR(BJ13="RCT",BJ13="Quasi-experimental with control"),LEFT(BF13,11)="Inferential",OR(BI13="Yes",BI13="Partly"),OR(BO13="",BO13>=4)),"High",IF(OR(BA13<>"None",LEFT(BF13,11)="Inferential"),"Moderate","Low")))) -> Low | BQ13: None (no discomfort reported) | BR13: Explicitly none observed | BS13: Sensitivity | BT13: Outside basic education: Participants aged 18–22 (music-school students/graduates) | BU13: Verified (full text) | BV13: Snowball sample of young adults; qualitative only
A14: 13 | C14: Sui Q.; Sui L. | D14: Sui, Qiao (57575969700); Sui, Li (57576400400) | E14: 57575969700; 57576400400 | F14: Research on the Impact of Interactive Experience and Perceived Value on User Satisfaction in VR Education | G14: 2024 | H14: 2024 13th International Conference on Educational and Information Technology, ICEIT 2024 | I14: 0 | J14: 10.1109/ICEIT61397.2024.10540855 | K14: https://www.scopus.com/inward/record.uri?eid=2-s2.0-85195683071&doi=10.1109%2fICEIT61397.2024.10540855&partnerID=40&md5=867d699250877711546b4e45774bd3d8 | L14: Quzhou University, Dept. College of Teacher Education, Quzhou, China; Dept. Huaiyin Middle School, Huaian, China | M14: Sui Q., Quzhou University, Dept. College of Teacher Education, Quzhou, China; Sui L., Dept. Huaiyin Middle School, Huaian, China | N14: With the continuous advancement of science and technology, the application of virtual reality (VR) technology in the field of education has become increasingly attractive. This study explores the impact mechanisms of interactive experiences and perceived value on user satisfaction in VR education. An experimental study of ninth-grade students at Huaiyin Middle School found that an excellent interactive experience and perceived value significantly impact user satisfaction. In terms of interactive experience, users can more easily engage in learning activities and improve subject understanding and skill mastery by designing a more immersive and engaging interaction mode. In terms of perceived value, users' perception of the actual value and benefits of virtual learning is directly related to satisfaction and learning effectiveness. These findings provide empirical support for optimizing the design of VR education systems. By in-depth studying the impact mechanism of interactive experience and perceived value on user satisfaction, this study aims to provide helpful guidance and inspiration for designing and implementing VR education systems and promote the development and application of virtual learning in education. © 2024 IEEE. | O14: interactive experience; perceived value; user satisfaction; VR education | P14: E-learning; Engineering education; Learning systems; User interfaces; Education systems; Experience values; Impact mechanism; Interactive experience; Perceived value; Science and Technology; Users' satisfactions; Virtual learning; Virtual reality education; Virtual reality technology; Virtual reality | Q14: Institute of Electrical and Electronics Engineers Inc. | R14: English | S14: Conference paper | T14: Final | V14: Scopus | W14: Accepted | X14: InOurScope | Y14: Basic Education | Z14: João | AA14: Lamarck | AD14: The study specifically used: A VR system: "Science Science Exhibition of VR Animal Evolution" developed by Beijing Huirui Viewpoint. No mention of CAVE VR (CAVE = Cave Automatic Virtual Environment) systems — only head-mounted VR devices were implied. The VR system had gesture recognition and controller feedback features for interaction. | AE14: he paper used questionnaires with Likert scales to assess: Interactive experience (immersion, participation, friendliness) Perceived value (content usefulness, novelty, application) Learning effects (knowledge absorption, skill mastery) Overall satisfaction and willingness to continue using VR Data analysis tools: SPSS (for descriptive statistics, reliability, validity) AMOS (for Structural Equation Modeling - SEM) | AF14: Effects on students: Higher engagement and immersion during learning activities. Improved understanding, memory, and skills related to the subject. Increased satisfaction and willingness to continue using VR for education. Effects on teachers (implied, not directly studied): Potential to design more effective and customized educational content. Need to consider personalization for different student groups based on their feedback. | AG14: Metrics included: Immersion (subjective feeling of being in the environment) Participation (level of active involvement) Interface friendliness (ease of interaction) Perceived content value (usefulness, novelty, application) Learning outcomes (knowledge absorption, skill mastery) Overall satisfaction (likelihood of reuse and recommendation) Measurement scale: 1 to 5 Likert scale (1=very poor to 5=very good) | AH14: Technologies mentioned: Virtual Reality (VR) platforms (not Augmented or Mixed Reality in this case) Gesture recognition Controller feedback systems Immersive virtual environments designed for education-specific content. | AL14: Education | AM14: Joao | AN14: Check, but could'nt validade REQ1 and REQ5 | AR14: China | AS14: Asia | AT14: Lower secondary | AU14: Typical learners (grade 9, mean age 15) | AV14: Natural sciences, mathematics & statistics | AW14: Biology (animal evolution), grade 9 | AX14: VR | AY14: Not reported | AZ14: VR system; headset not stated | BA14: None | BB14: Unclear | BC14: Not measured | BD14: Unclear | BE14: Authors report positive association of interactive experience & perceived value with satisfaction; no item means or path coefficients reported | BF14: Inferential, no effect size | BG14: Not reported (only CFA fit: χ²/df = 2.13, RMSEA = .071, CFI = .95) | BH14: Author-made 15-item questionnaire (α = .79–.92; KMO = .875; CFA) | BI14: Partly | BJ14: Cross-sectional survey (SEM) | BK14: Cross-sectional survey | BL14: Quantitative descriptive | BM14: 225 valid questionnaires (230 sampled from 17 classes) | BN14: NR | BO14: =IF(COUNTIF('MMAT Appraisal'!$A$2:$A$60,A14)=0,"",INDEX('MMAT Appraisal'!$K$2:$K$60,MATCH(A14,'MMAT Appraisal'!$A$2:$A$60,0))) -> 3 | BP14: =IF(OR(BF14="No empirical data",ISNUMBER(SEARCH("RETRACTED",BV14))),"Not rated",IF(AND(ISNUMBER(BO14),BO14<=2),"Low",IF(AND(OR(BJ14="RCT",BJ14="Quasi-experimental with control"),LEFT(BF14,11)="Inferential",OR(BI14="Yes",BI14="Partly"),OR(BO14="",BO14>=4)),"High",IF(OR(BA14<>"None",LEFT(BF14,11)="Inferential"),"Moderate","Low")))) -> Moderate | BQ14: Not reported | BR14: Not reported | BS14: Core | BT14: Basic-education learners with empirical E/M/S data | BU14: Verified (full text) | BV14: Satisfaction level and hypothesis tests not reported; '120 distributed, 225 collected' inconsistency; associational design
A15: 14 | C15: Tan B.S.; Ong S.H.; Andrew K.H.T.; Wong T.L.; Bai P.S.; Rao A.P. | D15: Tan, Bee Sian (58908987500); Ong, Shen Hoi (59380620800); Andrew, Khin Huat Tan (59380927800); Wong, Thein Lai (57440950200); Bai, P Sharimila (59380316000); Rao, AP Pandurenga (59380777200) | E15: 58908987500; 59380620800; 59380927800; 57440950200; 59380316000; 59380777200 | F15: Usability Study of GenAI for English Learning in VR | G15: 2024 | H15: Pakistan Journal of Life and Social Sciences | I15: 0 | J15: 10.57239/PJLSS-2024-22.2.00556 | K15: https://www.scopus.com/inward/record.uri?eid=2-s2.0-85207260177&doi=10.57239%2fPJLSS-2024-22.2.00556&partnerID=40&md5=22c640bcbf6a9c19da4eb3c263bc5617 | L15: Tunku Abdul Rahman University of Management and Technology, Kuala Lumpur, Malaysia | M15: Tan B.S., Tunku Abdul Rahman University of Management and Technology, Kuala Lumpur, Malaysia; Ong S.H., Tunku Abdul Rahman University of Management and Technology, Kuala Lumpur, Malaysia; Andrew K.H.T., Tunku Abdul Rahman University of Management and Technology, Kuala Lumpur, Malaysia; Wong T.L., Tunku Abdul Rahman University of Management and Technology, Kuala Lumpur, Malaysia; Bai P.S., Tunku Abdul Rahman University of Management and Technology, Kuala Lumpur, Malaysia; Rao A.P., Tunku Abdul Rahman University of Management and Technology, Kuala Lumpur, Malaysia | N15: Traditional English learning environments in university often hindered by outdated focus on reading and writing, limited textbook content, insufficient speaking practice opportunities, and pre-programmed artificial intelligence (AI) in English speaking practice. This study explores the potential of leveraging VR technologies and generative AI (GenAI) to overcome these barriers. EasyEnglish is a real-time conversation game with GenAI non-player character (NPC)s. This game utilizes voice input recognition, large language model (LLM) for language assessment and text-to-speech (TTS) for NPC lip-sync animation. The content validity was assessed by 3 experts to evaluate the conversation quality. A usability test was conducted using a purposive sampling method with 7 undergraduate non-native English speakers who have less than 1 year experience in using VR technology. This study employed System Usability Scale (SUS) and Content Validity Index (CVI) metrics for assessment. The CVI result showed satisfactory agreement in conversation quality but highlighted areas for improvement in learning objectives. The SUS result revealed satisfaction in consistency of user interface (UI) and learnability of EasyEnglish, while also highlighting the need for improvement in UI, setup, and visual cues. The significance of the study lies in the GenAI's ability to provide diverse response, avoid repetitive dialogue and speak using gestures to undergraduate students. GenAI effectively identify and assess irrelevant words in conversation, provide immediate grammar and vocabulary correction and suggestion of conversation improvement accurately. Future research should focus on improving accessibility, include more multimodal interactions, and mapping learning objectives with the soft skills emphasized by the World Economic Forum (WEF). © (2024), (Elite Scientific Publications). All rights reserved. | O15: Education; Educational Technology; English Language; Generative Artificial Intelligence; Virtual Reality | Q15: Elite Scientific Publications | R15: English | S15: Article | T15: Final | V15: Scopus | W15: Accepted | X15: InOurScope | Y15: Basic Education | Z15: João | AA15: Lamarck | AD15: Device used: Meta Quest 2 VR headset (fully immersive VR). No CAVE or AR systems were involved. | AE15: System Usability Scale (SUS): Collected from 7 university students. Content Validity Index (CVI): From 3 expert raters assessing grammar, vocabulary, coherence, relevance, audience appropriateness, and overall quality. Open-ended interviews and observation: Provided additional qualitative insight. | AF15: Effects on students: Reported realism and engagement in NPC interaction. Learned grammar and vocabulary through feedback and in-world tasks. Found UI complex at times and suffered from motion sickness, indicating the need for better UX. Effects on teachers: Can design personalized lessons using AI prompts. Can track learner performance and adapt content, but setup and design process needs refinement. | AG15: SUS score: 50.71 out of 100 (moderate usability). I-CVI, S-CVI/Ave, S-CVI/UA: Assessed content validity (average ~0.89). Qualitative feedback on: UI complexity Confidence in using the app Game feedback cues (e.g., visual/auditory signals for progress) | AH15: Technologies mentioned: Unity 3D (VR development) OpenAI’s ChatGPT (language processing and error correction) Whisper API (speech-to-text) TTS-1 API (text-to-speech with lip sync) Oculus Lip Sync (NPC animation) Ready Player Me (custom avatars) C# REST APIs for integrating GenAI into the game environment | AL15: Language Learning | AM15: Lamarck | AP15: Bee Sian | AQ15: tanbs@tarc.edu.my | AR15: Malaysia | AS15: Asia | AT15: Higher education | AU15: Typical learners (undergraduates, ages 18–25) | AV15: Arts & humanities (languages) | AW15: English speaking (GenAI NPCs) | AX15: VR | AY15: HMD (immersive) | AZ15: HMD – standalone | BA15: None | BB15: Not measured | BC15: + | BD15: Not measured | BE15: SUS = 50.71 (marginal); neutral on using it frequently; majority found the game interesting; CVI S-CVI/Ave = .89 | BF15: Descriptive only | BG15: Not reported | BH15: SUS (standard); Content Validity Index (3 experts); interviews | BI15: Yes | BJ15: Single-group usability study | BK15: Single group, post-test only | BL15: Quantitative descriptive | BM15: 7 students; 3 experts | BN15: Single session, 10–15 min | BO15: =IF(COUNTIF('MMAT Appraisal'!$A$2:$A$60,A15)=0,"",INDEX('MMAT Appraisal'!$K$2:$K$60,MATCH(A15,'MMAT Appraisal'!$A$2:$A$60,0))) -> 3 | BP15: =IF(OR(BF15="No empirical data",ISNUMBER(SEARCH("RETRACTED",BV15))),"Not rated",IF(AND(ISNUMBER(BO15),BO15<=2),"Low",IF(AND(OR(BJ15="RCT",BJ15="Quasi-experimental with control"),LEFT(BF15,11)="Inferential",OR(BI15="Yes",BI15="Partly"),OR(BO15="",BO15>=4)),"High",IF(OR(BA15<>"None",LEFT(BF15,11)="Inferential"),"Moderate","Low")))) -> Low | BQ15: Motion sickness with continuous locomotion; UI frustration | BR15: Cybersickness / physical discomfort reported | BS15: Sensitivity | BT15: Outside basic education: Undergraduate students | BU15: Verified (full text) | BV15: Undergraduates – outside basic education; motivation evidence is qualitative
A16: 15 | C16: Vashisht S. | D16: Vashisht, Sanchit (58222197000) | E16: 58222197000 | F16: StellarScape: Explore the Solar System with AR Cube | G16: 2024 | H16: 2nd International Conference on Intelligent Cyber Physical Systems and Internet of Things, ICoICI 2024 - Proceedings | I16: 0 | J16: 10.1109/ICoICI62503.2024.10696244 | K16: https://www.scopus.com/inward/record.uri?eid=2-s2.0-85207206514&doi=10.1109%2fICoICI62503.2024.10696244&partnerID=40&md5=0255c9a51708a670f46842ecb6f29ed3 | L16: Chitkara University Institute of Engineering and Technology, Chitkara University, Department of Computer Science and Engineering, Punjab, India | M16: Vashisht S., Chitkara University Institute of Engineering and Technology, Chitkara University, Department of Computer Science and Engineering, Punjab, India | N16: In a captivating and immersive environment, StellarScape users may explore the solar system's depths with the aid of state-of-the-art augmented reality technology. Using AR cubes, users may explore our solar system's planets, moons, and other celestial bodies in three dimensions and learn more about their unique traits, lifestyles, and historical significance. StellarScape was created following a comprehensive analysis of the solar system, ensuring the precision and depth of the program's expertise. The development team chose the content for StellarScape, consulting with renowned experts in education and astronomy. The content features enticing images, captivating narrative audio, and educational text. This increased the instructional value of the application. The user interface and experience (UI/UX) of StellarScape have been created to be simple, easy to use, and entertaining for people of all ages and backgrounds. Usability and accessibility have received a lot of our attention. The AR cubes become interactive markers when seen through a device that supports augmented reality (AR). This allows users to engage with virtual material relevant to each celestial body, promoting exploration and learning through hands-on experiences. An innovative educational platform called StellarScape uses augmented reality to spark users' interest, make learning easier, and encourage a passion for science research that lasts a lifetime. As augmented reality technology develops, programs like StellarScape may have a significant impact on education. StellarScape gives us new opportunity to learn about the solar system and beyond through immersive and interactive experiences. This creates an opportunity for an educational setting where conventional boundaries are dismantled and the limitless possibilities of augmented reality are fully realized. © 2024 IEEE. | O16: Augmented Reality; Education; Immersive technologies; Mixed Reality; Science; Virtual Reality | P16: Augmented reality; Mixed reality; Virtual environments; Augmented reality technology; Celestial bodies; Immersive environment; Immersive technologies; Learn+; Mixed reality; Science; Solar system planets; State of the art; Three dimensions; Solar system | Q16: Institute of Electrical and Electronics Engineers Inc. | R16: English | S16: Conference paper | T16: Final | V16: Scopus | W16: Accepted | X16: InOurScope | Y16: Basic Education | Z16: João | AA16: Lamarck | AD16: AR Cube System: Physical cubes with markers that trigger augmented reality models (viewed through smartphones/tablets). No use of CAVE VR (Cave Automatic Virtual Environment) was mentioned. The focus is purely on Augmented Reality (AR) using handheld devices. | AE16: In this paper, no formal user assessment tool (like surveys, SEM, SPSS analysis) was applied yet. The study is more focused on development and design of the StellarScape app. Related studies cited show that other AR studies used surveys to assess comprehension, motivation, critical thinking, and user satisfaction (based on previous research, not StellarScape yet). | AF16: Effects on students: Boosted engagement with scientific subjects (like astronomy). Deepened understanding of planetary systems and cosmic phenomena. Increased motivation, curiosity, and enjoyment in learning science. Improved collaboration through group interactions using AR cubes. Effects on teachers (implied): Teachers can customize AR content according to curriculum needs. Provides new creative methods for explaining abstract concepts. | AG16: In this case: No experiments or metrics reported yet for StellarScape directly. However, referenced research used metrics like: Engagement levels. Retention and comprehension scores. Critical thinking ability. Student motivation and interest. | AH16: Technologies mentioned: Unity 3D: Game engine for AR app development. Vuforia: AR development SDK for recognizing markers and overlaying content. Blender 3D: 3D modeling for planets, moons, and asteroids. Adobe Photoshop: For creating and editing textures and images. Devices: Smartphones and tablets with AR capabilities (cameras and sensors). | AL16: STEAM | AM16: Pedro | AN16: Check. For RQ2 the article does not describe assessment tools used, but presents a survey of related works that measured. | AR16: India | AS16: Asia | AT16: Not reported | AU16: None (development paper) | AV16: Natural sciences, mathematics & statistics | AW16: Astronomy (solar system) | AX16: AR | AY16: Handheld (mobile/tablet) | AZ16: Mobile/tablet – marker-based AR | BA16: None | BB16: Not measured | BC16: Not measured | BD16: Not measured | BE16: Development only | BF16: No empirical data | BG16: Not reported | BH16: None | BI16: N/A | BJ16: Design/development only | BK16: No empirical learner study | BL16: Not appraisable (no empirical learner study) | BM16: 0 | BN16: N/A | BO16: =IF(COUNTIF('MMAT Appraisal'!$A$2:$A$60,A16)=0,"",INDEX('MMAT Appraisal'!$K$2:$K$60,MATCH(A16,'MMAT Appraisal'!$A$2:$A$60,0))) | BP16: =IF(OR(BF16="No empirical data",ISNUMBER(SEARCH("RETRACTED",BV16))),"Not rated",IF(AND(ISNUMBER(BO16),BO16<=2),"Low",IF(AND(OR(BJ16="RCT",BJ16="Quasi-experimental with control"),LEFT(BF16,11)="Inferential",OR(BI16="Yes",BI16="Partly"),OR(BO16="",BO16>=4)),"High",IF(OR(BA16<>"None",LEFT(BF16,11)="Inferential"),"Moderate","Low")))) -> Not rated | BQ16: Not reported | BR16: Not reported | BS16: Excluded | BT16: E2: No learner data (development paper) | BU16: Verified (full text) | BV16: No evaluation; country = author affiliation (India); old RQ5–7 data for this row (USA, K-8) was wrong
A17: 16 | C17: Vaze A.; Morris A.; Clarke I. | D17: Vaze, Aaditya (58261905300); Morris, Alexis (57213247008); Clarke, Ian (58261163700) | E17: 58261905300; 57213247008; 58261163700 | F17: CuriosityXR: Context-aware Education Experiences with Mixed Reality and Conversation AI | G17: 2024 | H17: Proceedings - 2024 IEEE International Conference on Artificial Intelligence and eXtended and Virtual Reality, AIxVR 2024 | I17: 0 | J17: 10.1109/AIxVR59861.2024.00013 | K17: https://www.scopus.com/inward/record.uri?eid=2-s2.0-85187231317&doi=10.1109%2fAIxVR59861.2024.00013&partnerID=40&md5=6890cd9ac39d85f3dbe3537ca00ffd1c | L17: Ocad University, Adaptive Context Environments Lab, Toronto, Canada; Ocad University, Faculty of Arts and Science, Toronto, Canada | M17: Vaze A., Ocad University, Adaptive Context Environments Lab, Toronto, Canada; Morris A., Ocad University, Adaptive Context Environments Lab, Toronto, Canada; Clarke I., Ocad University, Faculty of Arts and Science, Toronto, Canada | N17: The educational landscape is undergoing a fundamental shift towards a learner-centric model, emphasizing engagement, interaction, and personalization in the learning process. This study investigates new technologies that enable immersive, self-guided, and curiosity-driven educational experiences, addressing these crucial elements. The research delves into Mixed Reality (MR) as a tool for constructing a context-aware system that nurtures learners' inquisitiveness while enhancing memory retention. The paper presents the design and development of "Curiosity XR,"an MR headset application created using a research-through-design methodology, acting as a platform for educators to develop contextual and multi-modal interactive mini-lessons. Learners can engage with these lessons and also benefit from AI-supported learning content. The evaluation of this design involves a user participant study and subsequent interviews, revealing greater engagement levels, increased curiosity to learn, and improved visual content retention among participants. This work aims to encourage further exploration within the MR domain and promote the integration of MR and AI for the advancement of curiosity-driven education. © 2024 IEEE. | O17: Artificial Intelligence; Education; Human-computer Interaction; Mixed Reality | P17: Artificial intelligence; Human computer interaction; Learning systems; User interfaces; Context-Aware; Context-aware systems; Design and Development; Design Methodology; Educational experiences; Immersive; Learning process; Memory retention; Mixed reality; Personalizations; Mixed reality | Q17: Institute of Electrical and Electronics Engineers Inc. | R17: English | S17: Conference paper | T17: Final | V17: Scopus | W17: Accepted | X17: InOurScope | Y17: Basic Education | Z17: João | AA17: Lamarck | AD17: Devices used: Microsoft HoloLens 2 (Mixed Reality headset) Meta Quest Pro (with color passthrough capabilities for Mixed Reality) No CAVE VR environment was used — focus was purely on head-mounted MR devices. | AE17: Pre-session and post-session surveys (knowledge and experience assessments). User interviews to collect qualitative feedback. Recall tests (after a week) to measure knowledge retention. Evaluation criteria included learning effectiveness, engagement, ease of use, rated 1-5. | AF17: Effects on students: Higher engagement and immersion during lessons. Better knowledge retention and higher curiosity. Minor challenges: issues with gesture and voice recognition affected ease of use. Effects on teachers: The MR system allows easy lesson creation (through templates). Enables customization based on real-world objects and user interests. Offers a new interaction model where learning is user-driven rather than teacher-driven. | AG17: Learning effectiveness (scale 1–5) User engagement level (scale 1–5) Ease of use (scale 1–5) Knowledge retention (assessed via a recall test after one week) Curiosity support (assessed through participant feedback) | AH17: Technologies used: Unity (for MR app development). Oculus SDK (for Meta Quest). Zed Mini depth sensor (for 3D object detection and spatial mapping). Wit.ai (for speech recognition and intent detection). GPT-3 AI (for generating dynamic lesson content based on objects). Multimodal Interaction (gaze, gestures, speech, tactile interaction). Cloud-based context-aware agents (for real-time scene understanding and learning adaptation). | AL17: STEAM | AM17: Ahsan | AN17: Check | AR17: Canada | AS17: North America | AT17: Higher education | AU17: University participants (age NR) | AV17: Generic / multi-subject | AW17: Plant cells mini-lesson (science) | AX17: MR | AY17: HMD (immersive) | AZ17: HMD – MR (HoloLens 2 / Quest Pro) | BA17: Non-immersive digital | BB17: + | BC17: Unclear | BD17: Not measured | BE17: Per-participant engagement ratings ≈4–5/5 (figure); perceived effectiveness M = 3.5/5; authors: no definitive conclusion on curiosity or recall | BF17: Descriptive only | BG17: Not reported | BH17: Author-made 1–5 ratings from 'questionnaire transcription notes'; recall test; interviews | BI17: No | BJ17: Within-subject comparison | BK17: Within-subject comparison | BL17: Quantitative non-randomised | BM17: 6 participants | BN17: One 40-min MR session + 15-min recall session 1 week later | BO17: =IF(COUNTIF('MMAT Appraisal'!$A$2:$A$60,A17)=0,"",INDEX('MMAT Appraisal'!$K$2:$K$60,MATCH(A17,'MMAT Appraisal'!$A$2:$A$60,0))) -> 0 | BP17: =IF(OR(BF17="No empirical data",ISNUMBER(SEARCH("RETRACTED",BV17))),"Not rated",IF(AND(ISNUMBER(BO17),BO17<=2),"Low",IF(AND(OR(BJ17="RCT",BJ17="Quasi-experimental with control"),LEFT(BF17,11)="Inferential",OR(BI17="Yes",BI17="Partly"),OR(BO17="",BO17>=4)),"High",IF(OR(BA17<>"None",LEFT(BF17,11)="Inferential"),"Moderate","Low")))) -> Low | BQ17: Voice and gesture recognition failures | BR17: Usability, behavioural or safety issues only | BS17: Sensitivity | BT17: Outside basic education: University participants | BU17: Verified (full text) | BV17: MR then laptop in fixed order, comparison results not reported; university context – outside basic education
A18: 17 | C18: Xia X.; Liang J.; Zhao R.; Zhao Z.; Wu M.; Li Y.; Liang H.-N. | D18: Xia, Xuansheng (58774881400); Liang, Jiachen (58237520000); Zhao, Ruixiang (58775077600); Zhao, Ziyue (58260678900); Wu, Mingze (58774832200); Li, Yue (57205203447); Liang, Hai-Ning (8636386200) | E18: 58774881400; 58237520000; 58775077600; 58260678900; 58774832200; 57205203447; 8636386200 | F18: Cross-Reality Interaction and Collaboration in Museums, Education, and Rehabilitation | G18: 2023 | H18: Proceedings - 2023 IEEE International Symposium on Mixed and Augmented Reality Adjunct, ISMAR-Adjunct 2023 | I18: 3 | J18: 10.1109/ISMAR-Adjunct60411.2023.00180 | K18: https://www.scopus.com/inward/record.uri?eid=2-s2.0-85180371809&doi=10.1109%2fISMAR-Adjunct60411.2023.00180&partnerID=40&md5=4f363c3f1f8bfaf0057047a27ec19a7d | L18: Xi'an Jiaotong-Liverpool University, School of Advanced Technology, China | M18: Xia X., Xi'an Jiaotong-Liverpool University, School of Advanced Technology, China; Liang J., Xi'an Jiaotong-Liverpool University, School of Advanced Technology, China; Zhao R., Xi'an Jiaotong-Liverpool University, School of Advanced Technology, China; Zhao Z., Xi'an Jiaotong-Liverpool University, School of Advanced Technology, China; Wu M., Xi'an Jiaotong-Liverpool University, School of Advanced Technology, China; Li Y., Xi'an Jiaotong-Liverpool University, School of Advanced Technology, China; Liang H.-N., Xi'an Jiaotong-Liverpool University, School of Advanced Technology, China | N18: With Virtual Reality Head-Mounted Displays (VR HMDs) establishing themselves as a potent platform for collaborative tasks, their cross-reality capability and cross-domain applicability remain largely unexplored. This study intends to assess the effectiveness of cross-reality collaboration systems using a VR HMD and a desktop PC across three disparate sectors: museum visiting, chemical education, and assisted rehabilitation. The systems were designed to support social interactions and scenario-specific collaborative tasks. Evaluation of the systems showed above-average system usability and user experience. By probing into these varied environments, our study offers a comprehensive understanding of the applicability of such collaborative cross-reality systems in real scenarios, potentially fostering more immersive, efficient, and enriching multi-field applications of cross-reality technologies. © 2023 IEEE. | O18: education; museums; rehabilitation; virtual reality | P18: E-learning; Helmet mounted displays; User interfaces; Average system; Chemical education; Collaboration systems; Collaborative tasks; Cross-domain; Head-mounted-displays; Social interactions; Social scenarios; System usability; Users' experiences; Virtual reality | Q18: Institute of Electrical and Electronics Engineers Inc. | R18: English | S18: Conference paper | T18: Final | V18: Scopus | W18: Accepted | X18: InOurScope | Y18: Basic Education | Z18: João | AA18: Lamarck | AD18: Devices used: Meta Quest 2 VR headset (Virtual Reality HMD) Desktop PCs (non-immersive version) No use of CAVE VR; focus is on VR headsets + regular PCs. Systems developed in Unity 2021.3.6, supporting synchronized VR-PC experiences. | AE18: System Usability Scale (SUS) questionnaire (standard UX measure). User Experience Questionnaire Short version (UEQ-S). Paired t-tests used for statistical analysis. Participants rated usability, pragmatic quality, and hedonic quality after sessions. | AF18: Effects on students (VR users): Highly immersive experience during chemistry experiments. Better engagement and understanding of practical tasks. Collaborative experience improved learning satisfaction. Effects on teachers/instructors (PC users): Ability to guide and support remotely. PC users had a slightly lower user experience rating compared to VR users (felt less immersive/fun). System design allowed dynamic role management (instructor/experimenter). | AG18: System Usability Scale (SUS) score (threshold 68 for good usability — all scenarios exceeded it). UEQ-S for user experience: Pragmatic quality (ease of use, task support) Hedonic quality (fun, stimulation, creativity) Qualitative feedback during and after experiments. | AH18: Technologies used: Unity (for developing VR/PC applications). Meta Quest 2 (for VR user). High-end PC hardware (Intel i7-12700K CPU, RTX 3080 GPU). Cross-platform synchronization between VR and PC users. Teleport locomotion and 3D object manipulation (grab, rotate, scale) in VR and PC environments. | AL18: STEAM | AM18: Pedro | AN18: Check | AR18: China | AS18: Asia | AT18: Higher education | AU18: Young adults aged 21–24 (M = 22.3) | AV18: Natural sciences, mathematics & statistics | AW18: Chemistry lab (acid–base titration) + museum + rehabilitation | AX18: VR | AY18: HMD (immersive) | AZ18: HMD – standalone (Quest 2) vs desktop PC | BA18: Non-immersive digital | BB18: Not measured | BC18: Not measured | BD18: + | BE18: SUS > 68 in all 3 scenarios; UEQ-S overall higher for VR than PC in chemistry lab, t(5) = 3.107, p = .027 | BF18: Inferential, no effect size | BG18: dz ≈ 1.27 (computed by reviewer from t(5) = 3.107, n = 6; UEQ-S overall, chemistry) | BH18: SUS; UEQ-S | BI18: Yes | BJ18: Within-subject comparison | BK18: Within-subject comparison | BL18: Quantitative non-randomised | BM18: 6 participants (36 SUS/UEQ sets) | BN18: One session, ~50 min (3 scenarios) | BO18: =IF(COUNTIF('MMAT Appraisal'!$A$2:$A$60,A18)=0,"",INDEX('MMAT Appraisal'!$K$2:$K$60,MATCH(A18,'MMAT Appraisal'!$A$2:$A$60,0))) -> 3 | BP18: =IF(OR(BF18="No empirical data",ISNUMBER(SEARCH("RETRACTED",BV18))),"Not rated",IF(AND(ISNUMBER(BO18),BO18<=2),"Low",IF(AND(OR(BJ18="RCT",BJ18="Quasi-experimental with control"),LEFT(BF18,11)="Inferential",OR(BI18="Yes",BI18="Partly"),OR(BO18="",BO18>=4)),"High",IF(OR(BA18<>"None",LEFT(BF18,11)="Inferential"),"Moderate","Low")))) -> Moderate | BQ18: Complex interactions confusing on PC side | BR18: Usability, behavioural or safety issues only | BS18: Sensitivity | BT18: Outside basic education: Young adults aged 21–24 | BU18: Verified (full text) | BV18: Adults, not school learners; multi-domain study (only chemistry scenario is educational); satisfaction coded from UEQ-S overall UX
A19: 18 | C19: Wu L.; Chen K.B.; Sekelsky B.; Peterson M.; Harper-Gampp T.; Delgado C. | D19: Wu, Linfeng (58035928900); Chen, Karen B. (56340607100); Sekelsky, Brian (58261079000); Peterson, Matthew (57189226800); Harper-Gampp, Tyler (58262313200); Delgado, Cesar (23093747600) | E19: 58035928900; 56340607100; 58261079000; 57189226800; 58262313200; 23093747600 | F19: Shrink or grow the kids? Scale cognition in an immersive virtual environment for K-12 summer camp | G19: 2023 | H19: Proceedings - 2023 IEEE Conference on Virtual Reality and 3D User Interfaces Abstracts and Workshops, VRW 2023 | I19: 1 | J19: 10.1109/VRW58643.2023.00203 | K19: https://www.scopus.com/inward/record.uri?eid=2-s2.0-85159690491&doi=10.1109%2fVRW58643.2023.00203&partnerID=40&md5=ee7e78367713c54e3c9603ae2f96ad97 | L19: Industrial and Systems Engineering, North Carolina State University, United States; Graphic and Experience Design, North Carolina State University, United States; Science, Technology, Engineering, and Mathematics Education, North Carolina State University, United States | M19: Wu L., Industrial and Systems Engineering, North Carolina State University, United States; Chen K.B., Industrial and Systems Engineering, North Carolina State University, United States; Sekelsky B., Graphic and Experience Design, North Carolina State University, United States; Peterson M., Graphic and Experience Design, North Carolina State University, United States; Harper-Gampp T., Science, Technology, Engineering, and Mathematics Education, North Carolina State University, United States; Delgado C., Science, Technology, Engineering, and Mathematics Education, North Carolina State University, United States | N19: Virtual reality (VR) has been widely used for education and affords embodied learning experiences. Here we describe: Scale Worlds (SW), an immersive virtual environment to allow users to shrink or grow by powers of ten (10X) and experience entities from molecular to astronomical levels; and students' impressions and outcomes from experiencing SW in a CAVE (Figure 1) during experiential summer outreach sessions. Data collected from post-visit surveys of 69 students, and field observations, revealed that VR technologies: enabled interactive learning experiences; encouraged active engagement and discussions among participating students; enhanced the understanding of size and scale; and increased interest in STEM careers. © 2023 IEEE. | O19: CAVE; education application; scale cognition; User experience; virtual reality; Virtual reality (VR) | P19: Caves; E-learning; Students; User interfaces; Education application; Field observations; Immersive virtual environments; Learning experiences; Power; Scale cognition; Students' observations; Summer camp; Users' experiences; Virtual reality; Virtual reality | Q19: Institute of Electrical and Electronics Engineers Inc. | R19: English | S19: Conference paper | T19: Final | V19: Scopus | W19: Accepted | X19: InOurScope | Y19: Basic Education | Z19: João | AA19: Lamarck | AB19: CaveVR | AD19: Device used: CAVE (Cave Automatic Virtual Environment), a large immersive VR environment. Active 3D glasses (tracked) for one student at a time; other students wore passive 3D glasses. Application: Scale Worlds (SW), an interactive VR platform to explore scaling from molecular to astronomical sizes. | AE19: Post-visit survey for 69 students: 4 Likert-scale questions (enjoyment, learning, VR effectiveness, understanding of scale) 1 multiple-choice question about interest in STEM careers 4 short-answer qualitative questions (awe, sense of scale, object learned, engagement aspects) | AF19: Effects on students: 97% enjoyed the experience. 87% agreed VR is an effective way to learn about scale. 70% became more interested in STEM careers. Most students felt like they were physically growing or shrinking, confirming embodied learning. Experiences of awe and wonder were reported by 91% of students. Effects on teachers (implied): Teachers/facilitators could observe active engagement and better understanding among students. | AG19: Likert-scale responses for engagement, perceived learning, VR effectiveness, and STEM interest. Qualitative responses categorized to assess experience-driven vs. knowledge-driven interest in STEM. Proportion of students feeling “shrink/grow” experience vs. object-size change experience. | AH19: Technologies mentioned: CAVE VR environment (large room-scale virtual projection). Active shutter 3D glasses (tracked) + Passive 3D glasses (untracked). Scale Worlds (SW) immersive software. VR controllers (wand) for interaction with virtual objects and scaling interface. | AL19: STEAM | AM19: Joao | AN19: Check. Couldn't validate the effect perception on teachers (RQ3) | AR19: USA | AS19: North America | AT19: Mixed K-12 | AU19: Underserved summer-camp students: 41 elementary + 28 middle school | AV19: Natural sciences, mathematics & statistics | AW19: Scale & size (STEM) | AX19: VR | AY19: CAVE / projection | AZ19: CAVE / projection | BA19: None | BB19: + | BC19: + | BD19: Not measured | BE19: 97% enjoyed; 91% felt awe; 70% more interested in STEM careers; 77% learned something; 73% better understanding of scale | BF19: Descriptive only | BG19: Not reported | BH19: Author-made survey: 4 Likert items, 1 multiple choice, 4 open questions; field observation | BI19: No | BJ19: Single-group post-test only | BK19: Single group, post-test only | BL19: Quantitative descriptive | BM19: 69 students (41 elementary, 28 middle) | BN19: Single CAVE visit (duration NR); one tracked viewer at a time | BO19: =IF(COUNTIF('MMAT Appraisal'!$A$2:$A$60,A19)=0,"",INDEX('MMAT Appraisal'!$K$2:$K$60,MATCH(A19,'MMAT Appraisal'!$A$2:$A$60,0))) -> 3 | BP19: =IF(OR(BF19="No empirical data",ISNUMBER(SEARCH("RETRACTED",BV19))),"Not rated",IF(AND(ISNUMBER(BO19),BO19<=2),"Low",IF(AND(OR(BJ19="RCT",BJ19="Quasi-experimental with control"),LEFT(BF19,11)="Inferential",OR(BI19="Yes",BI19="Partly"),OR(BO19="",BO19>=4)),"High",IF(OR(BA19<>"None",LEFT(BF19,11)="Inferential"),"Moderate","Low")))) -> Low | BQ19: Not reported | BR19: Not reported | BS19: Core | BT19: Basic-education learners with empirical E/M/S data | BU19: Verified (full text) | BV19: Informal outreach setting; single-item measures; 100% response
A20: 19 | C20: Sooraj N.N.; Manoj S.; Mahalakshmi P. | D20: Sooraj, Nived N (58680963400); Manoj, Sidharth (59642701400); Mahalakshmi, P. (57216001944) | E20: 58680963400; 59642701400; 57216001944 | F20: WEBARIO: A Web based Portal with Revolutionary Virtual Classroom and Augmented Reality Integration for Enhanced Learning | G20: 2023 | H20: Proceedings of the 4th International Conference on Smart Electronics and Communication, ICOSEC 2023 | I20: 0 | J20: 10.1109/ICOSEC58147.2023.10275853 | K20: https://www.scopus.com/inward/record.uri?eid=2-s2.0-85175731110&doi=10.1109%2fICOSEC58147.2023.10275853&partnerID=40&md5=2f7575977bb29fcd6c40daa2998c5b22 | L20: Srm Institute of Science and Technology, Department of Networking and Communication, Kattankulathur, India | M20: Sooraj N.N., Srm Institute of Science and Technology, Department of Networking and Communication, Kattankulathur, India; Manoj S., Srm Institute of Science and Technology, Department of Networking and Communication, Kattankulathur, India; Mahalakshmi P., Srm Institute of Science and Technology, Department of Networking and Communication, Kattankulathur, India | N20: webARio is a web-based portal designed to enhance the process of learning by streamlining visualization using a revolutionary virtual classroom setup with 3D models and augmented reality integration. In this study, the authors present the development of the webARio platform, its architecture, and the implementation of its key features. Proposed system offers a user-friendly interface that allows users to access the platform from any device with internet access. The revolutionary virtual classroom setup uses 3D models to facilitate learning, enabling users to visualize complex concepts in a more engaging and interactive way. Additionally, the integration of augmented reality enhances the user experience, allowing users to visualize 3D models in the real world. The webARio platform has the potential to revolutionize the way students learn by offering an innovative and effective way to visualize and understand complex concepts. This study presents a detailed analysis of the webARio platform, its features, and its potential impact on the education sector. © 2023 IEEE. | O20: 3-Dimensional; Augmented Reality; virtual reality; Visualization | P20: Computer aided instruction; E-learning; Integration; Learning systems; Portals; Three dimensional computer graphics; Virtual reality; Visualization; 3-dimensional; 3D models; 3d-modeling; Enhanced learning; ITS architecture; Key feature; Process of learning; User friendly interface; Virtual Classroom; Web-based portal; Augmented reality | Q20: Institute of Electrical and Electronics Engineers Inc. | R20: English | S20: Conference paper | T20: Final | V20: Scopus | W20: Accepted | X20: InOurScope | Y20: Basic Education | Z20: João | AA20: Lamarck | AD20: Technologies used: Augmented Reality (AR) via web browsers (WebAR). 3D models integrated into virtual classrooms. No VR headsets or CAVE systems were required — just any device with internet access (PC, tablet, mobile phone). Web platform: webARio accessible through browsers. | AE20: No experimental evaluation yet reported (i.e., no user tests, surveys, or experiments completed at this stage). Authors emphasize future research is needed to assess usability, student engagement, and learning outcomes. The paper is mainly focused on platform design and architecture, not experimental validation. | AF20: Based on expected outcomes (no experimental users yet): Teachers: Can upload and manage 3D models, create virtual classrooms, host sessions. Enhance teaching of STEM topics with visual 3D support. Students: Can join sessions, interact with 3D models, and explore concepts visually. Even young children have a version for early learning (alphabet-based objects). Overall, system is expected to increase motivation, engagement, and concept understanding. | AG20: No metrics or experimental data yet reported. Future work suggested to assess: Student engagement levels. Learning outcomes improvement. Usability and scalability of the system. | AH20: Technologies mentioned: ARJS for AR model rendering in browsers. Agora.io API for virtual classroom meeting rooms. Firebase for user authentication and database storage. Web-based portal (responsive for various devices). 3D models for educational content (e.g., interactive models for physics, biology, math). | AM20: Lamarck | AN20: No evaluation make, think need be romove | AR20: India | AS20: Asia | AT20: Not reported | AU20: None (development paper) | AV20: Generic / multi-subject | AW20: Virtual classroom with 3D/AR models | AX20: AR | AY20: Web-based | AZ20: Web/browser AR | BA20: None | BB20: Not measured | BC20: Not measured | BD20: Not measured | BE20: Development only | BF20: No empirical data | BG20: Not reported | BH20: None | BI20: N/A | BJ20: Design/development only | BK20: No empirical learner study | BL20: Not appraisable (no empirical learner study) | BM20: 0 | BN20: N/A | BO20: =IF(COUNTIF('MMAT Appraisal'!$A$2:$A$60,A20)=0,"",INDEX('MMAT Appraisal'!$K$2:$K$60,MATCH(A20,'MMAT Appraisal'!$A$2:$A$60,0))) | BP20: =IF(OR(BF20="No empirical data",ISNUMBER(SEARCH("RETRACTED",BV20))),"Not rated",IF(AND(ISNUMBER(BO20),BO20<=2),"Low",IF(AND(OR(BJ20="RCT",BJ20="Quasi-experimental with control"),LEFT(BF20,11)="Inferential",OR(BI20="Yes",BI20="Partly"),OR(BO20="",BO20>=4)),"High",IF(OR(BA20<>"None",LEFT(BF20,11)="Inferential"),"Moderate","Low")))) -> Not rated | BQ20: Not reported | BR20: Not reported | BS20: Excluded | BT20: E2: No learner data (platform development; evaluation left to future work) | BU20: Verified (full text) | BV20: No evaluation – authors state effectiveness and usability are future work
A21: 20 | C21: Steynberg J.; van Biljon J.; Pilkington C. | D21: Steynberg, Johanna (57220746542); van Biljon, Judy (23393877200); Pilkington, Colin (26031725800) | E21: 57220746542; 23393877200; 26031725800 | F21: Virtual learner experience (VLX): A new dimension of virtual reality environments for the assessment of knowledge transfer | G21: 2023 | H21: South African Computer Journal | I21: 0 | J21: 10.18489/sacj.v35i2.17442 | K21: https://www.scopus.com/inward/record.uri?eid=2-s2.0-85184477574&doi=10.18489%2fsacj.v35i2.17442&partnerID=40&md5=92924614954f8f47f1529439bd00e823 | L21: University of South Africa, South Africa | M21: Steynberg J., University of South Africa, South Africa; van Biljon J., University of South Africa, South Africa; Pilkington C., University of South Africa, South Africa | N21: Science educators need tools to assess to what extent learners’ knowledge can be transferred to novel real-world situations. Virtual reality learning environments (VRLEs) offer the possibility of creating authentic tools where situated learning and assessment can take place, but there is a lack of evidence-based guidelines to inform the design and development of the VRLEs focussing on the user, that is the learner experience, especially for secondary schools. Drawing on theoretical premises and guidelines from user experience, usability, and technologically enabled assessment literature, we designed, developed, evaluated, and refined a VRLE prototype for the authentic assessment of knowledge transfer in the secondary school science classroom as guided by the design science research approach. Lessons learnt from the implementation and iterative evaluation of the prototype are presented as a set of literature-based, empirically validated guidelines to support and guide educational designers and developers to create VRLEs focused on supporting the learner experience. The contribution of this study is a VRLE design model with the learner at its core, the definition of VLX to include learner-specific aspects of immersive environments, and guidelines for the development of an effective and efficient virtual reality environment for the assessment of knowledge transfer in science education. © The author(s); published under a Creative Commons NonCommercial 4.0 License | O21: 21st-century abilities; Augmented and virtual reality; Human-computer interface; Learner experience; Virtual reality learning environments | Q21: South African Institute of Computer Scientists and Information Technologists | R21: English | S21: Article | T21: Final | U21: All Open Access; Gold Open Access | V21: Scopus | W21: Accepted | X21: InOurScope | Y21: Basic Education | Z21: João | AA21: Lamarck | AD21: Devices used: Oculus Rift VR headset (full immersive VR). Desktop computer (Windows 10, high-end specs for VR rendering). No mention of CAVE VR systems — focus on head-mounted VR (HMD) | AE21: Likert-item questionnaires (effectiveness, efficiency, satisfaction). Thematic analysis of open-ended interviews. Observation of users interacting with the VRLE. Stealth assessments (built into the VR system to measure task performance). | AF21: Effects on students: Strong emotional experiences: enjoyment, immersion, interest. Improved motivation and desire for more interactive learning. Minor adaptation challenges (adjusting to VR navigation). Minimal side effects (very little motion sickness). Effects on teachers: Provides authentic, real-world style assessments. Requires new design strategies to create VR environments that match learner profiles (age, experience). | AG21: Effectiveness (spatial characteristics, visual authenticity, data consistency). Efficiency (navigation ease, interaction with virtual objects). Satisfaction (physical comfort, user frustration, attitude, motivation). Mean scores calculated for each dimension. Qualitative codes for emotional experiences, locomotion issues, educational impact, and real-world simulation feedback. | AH21: Technologies mentioned: Oculus Rift VR headset + hand controllers. Unreal Engine 4.22 (for VRLE development). Desktop PC (Intel i7 CPU, RTX 2070 GPU, 64GB RAM). VRLE Design guided by: Content-pedagogy-technology synergy model. Finite-State Machine programming (for event-driven interactions). Emphasis on motion sickness mitigation, personal space respect, and natural movement. | AL21: STEAM | AM21: Pedro | AN21: Check | AR21: South Africa | AS21: Africa | AT21: Secondary (unspecified) | AU21: Secondary-school science learners (convenience sample) + 3 general users and 2 experts (iteration 1) | AV21: Natural sciences, mathematics & statistics | AW21: Science (assessment of knowledge transfer) | AX21: VR | AY21: HMD (immersive) | AZ21: HMD – PC-tethered | BA21: None | BB21: + | BC21: + | BD21: + | BE21: Satisfaction section M = 4.71/5 (SD 0.78; incl. attitude & motivation); efficiency lowest M = 3.87; all learners reported enjoyment | BF21: Descriptive only | BG21: Not reported | BH21: Author-made Likert items (effectiveness, efficiency, satisfaction) in 1-to-1 interviews; open questions | BI21: No | BJ21: Design-based research | BK21: Single group, mixed methods / DBR | BL21: Quantitative descriptive | BM21: 10 secondary-school learners (iteration 2) | BN21: Single session (duration NR) | BO21: =IF(COUNTIF('MMAT Appraisal'!$A$2:$A$60,A21)=0,"",INDEX('MMAT Appraisal'!$K$2:$K$60,MATCH(A21,'MMAT Appraisal'!$A$2:$A$60,0))) -> 2 | BP21: =IF(OR(BF21="No empirical data",ISNUMBER(SEARCH("RETRACTED",BV21))),"Not rated",IF(AND(ISNUMBER(BO21),BO21<=2),"Low",IF(AND(OR(BJ21="RCT",BJ21="Quasi-experimental with control"),LEFT(BF21,11)="Inferential",OR(BI21="Yes",BI21="Partly"),OR(BO21="",BO21>=4)),"High",IF(OR(BA21<>"None",LEFT(BF21,11)="Inferential"),"Moderate","Low")))) -> Low | BQ21: Navigation speed problems; minimal motion sickness | BR21: Cybersickness / physical discomfort reported | BS21: Core | BT21: Basic-education learners with empirical E/M/S data | BU21: Verified (full text) | BV21: Convenience sample of 10
A22: 21 | C22: Varinlioglu G.; Afshar S.V.; Eshaghi S.; Balaban Ö.; Nagakura T. | D22: Varinlioglu, Guzden (36919637100); Afshar, Sepehr Vaez (57456114000); Eshaghi, Sarvin (57455172900); Balaban, Özgün (56026427000); Nagakura, Takehiko (15819787000) | E22: 36919637100; 57456114000; 57455172900; 56026427000; 15819787000 | F22: GIS-BASED EDUCATIONAL GAME THROUGH LOW-COST VIRTUAL TOUR EXPERIENCE Khan Game | G22: 2022 | H22: Proceedings of the International Conference on Computer-Aided Architectural Design Research in Asia | I22: 9 | J22: 10.52842/conf.caadria.2022.1.069 | K22: https://www.scopus.com/inward/record.uri?eid=2-s2.0-85171859846&doi=10.52842%2fconf.caadria.2022.1.069&partnerID=40&md5=bbf991dd49c7e6803b71cb8e791cdcf8 | L22: Department of Architecture, Izmir University of Economics; Massachusetts Institute of Technology, United States; Istanbul Technical University, Turkey; Delft University of Technology, Netherlands; Department of Architecture, Massachusetts Institute of Technology, United States | M22: Varinlioglu G., Department of Architecture, Izmir University of Economics; Massachusetts Institute of Technology, United States; Afshar S.V., Istanbul Technical University, Turkey; Eshaghi S., Istanbul Technical University, Turkey; Balaban Ö., Delft University of Technology, Netherlands; Nagakura T., Department of Architecture, Massachusetts Institute of Technology, United States | N22: The pandemic brought new norms and techniques of pedagogical strategies in formal education. The synchronous/ asynchronous video streaming brought an emphasis on virtual and augmented realities, which are rapidly replacing textbooks as the main medium for learning and teaching. This transformation requires more extensive online and interactive content with simpler user interfaces. The aim of this study is to report on the design, implementation, and testing of a game based on low-cost and user-friendly content for digital cultural heritage. In this project, a game aimed at inclusive and equitable education was developed using 360° images of the targeted architectural heritage geographically distributed in a pilot site. We promote lifelong learning opportunities for all, following the SDG4, aiming for quality education with the easy-to-use online platform and easy access to immersive education through mobile platforms. Towards a post-carbon future without the need for travel, computational design methods such as using 360° videos and images in combination with virtual reality (VR) headsets allow a low-cost approach to remotely experiencing cultural heritage. We propose developing and testing a GIS-based educational game using a low-cost 360° virtual tour of architectural heritage, more specifically, caravanserais of Anatolia. © 2022, The Association for Computer-Aided Architectural Design Research in Asia. All rights reserved. | O22: 360° Images; Caravanserais; Digital Heritage; Educational Games; SDG 4 | P22: Architectural design; Augmented reality; Costs; E-learning; Geographic information systems; Virtual reality; 360° image; Architectural heritage; Caravanserai; Digital heritage; Educational game; Gis-based; Low-costs; Pedagogical strategies; SDG 4; Virtual tour; User interfaces | Q22: The Association for Computer-Aided Architectural Design Research in Asia | R22: English | S22: Conference paper | T22: Final | U22: All Open Access; Bronze Open Access; Green Open Access | V22: Scopus | W22: Accepted | X22: InOurScope | Y22: Basic Education | Z22: João | AA22: Lamarck | AD22: Uses 360° panoramic photography and web-based VR tours. Compatible with mobile and desktop platforms, with optional VR headset support (but not required). No use of CAVE VR systems. | AE22: User analytics tracking: Google Analytics for click tracking and session data. Custom script logging of scores, quiz performance, and game progression. No formal questionnaires or surveys—data focused on interaction behavior and game analytics. | AF22: Effects on students: Increased immersion, motivation, and content retention through puzzle-solving and exploration. Allowed students to navigate cultural content in a story-rich, non-linear format. Effects on teachers: Enabled creation of interactive learning modules using 360° media without needing advanced game development skills. Facilitated data-driven improvements to content via web analytics. | AG22: Score tracking per caravanserai and game module. Health points (as a gamified way to track error rate or time violations). Heatmap data on site visitation and activity completion. | AH22: Technologies used: 3DVista Virtual Tour PRO: To create interactive 360° VR scenes. Mapbox GL JS + GeoJSON: For GIS-based map and navigation. GoPro Max: For 360° image capture. Firebase: For real-time database of user interactions. Google Analytics: To track behavior and engagement. | AL22: History | AM22: Ahsan | AN22: Check | AP22: Guzden | AQ22: guzden@mit.edu | AR22: Turkey | AS22: Asia | AT22: Not reported | AU22: 30 students (level NR) in a playtest | AV22: Arts & humanities (history/heritage) | AW22: Architectural heritage (Anatolian caravanserais) | AX22: VR (360°) | AY22: HMD (immersive) | AZ22: 360° web tour on computers and mobiles (no HMD in playtest) | BA22: None | BB22: Not measured | BC22: Not measured | BD22: Not measured | BE22: Playtest with 30 students logged by Google Analytics; no outcome results reported | BF22: No empirical data | BG22: Not reported | BH22: Web analytics; score logs | BI22: N/A | BJ22: Design + pilot (analytics) | BK22: No empirical learner study | BL22: Not appraisable (no empirical learner study) | BM22: 30 students (no results reported) | BN22: One playtest session (Nov 2021) | BO22: =IF(COUNTIF('MMAT Appraisal'!$A$2:$A$60,A22)=0,"",INDEX('MMAT Appraisal'!$K$2:$K$60,MATCH(A22,'MMAT Appraisal'!$A$2:$A$60,0))) | BP22: =IF(OR(BF22="No empirical data",ISNUMBER(SEARCH("RETRACTED",BV22))),"Not rated",IF(AND(ISNUMBER(BO22),BO22<=2),"Low",IF(AND(OR(BJ22="RCT",BJ22="Quasi-experimental with control"),LEFT(BF22,11)="Inferential",OR(BI22="Yes",BI22="Partly"),OR(BO22="",BO22>=4)),"High",IF(OR(BA22<>"None",LEFT(BF22,11)="Inferential"),"Moderate","Low")))) -> Not rated | BQ22: Not reported | BR22: Not reported | BS22: Excluded | BT22: E2: No learner outcome data reported (playtest analytics only) | BU22: Verified (full text) | BV22: Engagement/motivation claims not supported by reported data
A23: 22 | C23: Tian X.; Cui S. | D23: Tian, Xingjiang (57992989300); Cui, Shujing (57993479300) | E23: 57992989300; 57993479300 | F23: The Application of Scientific Games by Artificial Intelligence in Preschool Education under the Smart City | G23: 2022 | H23: Security and Communication Networks | I23: 4 | J23: 10.1155/2022/7483566 | K23: https://www.scopus.com/inward/record.uri?eid=2-s2.0-85143344739&doi=10.1155%2f2022%2f7483566&partnerID=40&md5=1504091351c43d941d37a4276a939c60 | L23: Chongqing University of Arts and Sciences, Chongqing, 402160, China | M23: Tian X., Chongqing University of Arts and Sciences, Chongqing, 402160, China; Cui S., Chongqing University of Arts and Sciences, Chongqing, 402160, China | N23: The purpose is to explore the application and effect of scientific games based on artificial intelligence (AI) in preschool education under the smart city. An interactive scientific games model for children by virtual reality (VR) is constructed using the augmented reality (AR) technology in AI. This enables the product to continuously enrich its interactive functions in addition to realizing its own functional requirements, pay attention to user experience, and allow users to feel the pleasure and comfortable emotional communication brought by the product in the process of using it. The model mainly completes the interaction through gesture interaction and voice interaction, and it is further empirically analyzed by means of questionnaires and interviews. The results manifested that after the use of the intelligent interaction model of scientific games, 93.33% of the students in the experimental group were interested in scientific games, and 83.33% of the students in the experimental group had a clear understanding of scientific knowledge. Moreover, more students in the experimental group believed that they had received support from explanations, demonstrations, and guided conjectures, which was significantly different from the control group (P < 0.05). In the analysis of teacher interviews, it testified that the scientific values of preschool teachers and the reserve of basic scientific knowledge were still relatively weak, and their knowledge reserve could be improved in the future. Therefore, the research shows that the constructed model can improve the interest of scientific games and the ability of knowledge acquisition in preschool education, and provide an experimental reference for the development of intelligence and the improvement of teaching skills in the field of preschool education. © 2022 Xingjiang Tian and Shujing Cui. | P23: Artificial intelligence; Augmented reality; Education computing; Smart city; Surveys; Virtual reality; Augmented reality technology; Experimental groups; Functional requirement; Game models; Game-Based; Interactive functions; Preschool education; Scientific knowledge; Teachers'; Users' experiences; Students | Q23: Hindawi Limited | R23: English | S23: Article | T23: Final | U23: All Open Access; Gold Open Access | V23: Scopus | W23: Accepted | X23: InOurScope | Y23: Basic Education | Z23: João | AA23: Lamarck | AD23: Used VR-based models enhanced with AR elements. Gesture and voice recognition were central interaction methods. No mention of CAVE VR; mainly VR HMD-style setups or projection-based VR for children. | AE23: Questionnaires (for students' interest, knowledge clarity, and operational support). Teacher interviews (on support provided during scientific games). Statistical analysis: Cronbach Alpha for reliability. KMO tests for validity. Comparison with control groups (P<0.05 for significance). | AF23: Effects on students: 93.33% showed increased interest in science games. 83.33% demonstrated better clarity in scientific knowledge. Students were more engaged and better supported via demonstrations, explanations, and guided guessing. Effects on teachers: Teachers realized their own lack of scientific training. Noted that teaching skills and scientific knowledge reserves among preschool educators need improvement. | AG23: Interest levels in scientific games. Clarity of knowledge acquisition (clear/unclear understanding). Operational support provided (demonstration, explanation, guided discovery). Teacher feedback on education quality and needs. | AH23: Technologies mentioned: AR technology integrated with VR-based games. Gesture interaction: skeletal tracking for motion (e.g., waving detection). Voice interaction: speech recognition using Hidden Markov Models (HMM). Scientific Games Model designed with cognitive psychology principles (sensory perception, attention, memory, emotion). | AL23: STEAM | AM23: Joao | AN23: Check | AR23: China | AS23: Asia | AT23: Pre-primary | AU23: Typical learners + teachers | AV23: Natural sciences, mathematics & statistics | AW23: Early science games | AX23: VR + AR | AY23: Not reported | AZ23: Unspecified (gesture + voice) | BA23: Traditional teaching | BB23: + | BC23: + | BD23: Not measured | BE23: 93.3% interested; 83.3% clear understanding; p < .05 vs control | BF23: Inferential, no effect size | BG23: Not reported | BH23: Author-made questionnaire (α, KMO); teacher interviews | BI23: Partly | BJ23: Quasi-experimental with control | BK23: Between-group comparison (non-randomised) | BL23: Not appraisable (no empirical learner study) | BM23: Not reported | BO23: =IF(COUNTIF('MMAT Appraisal'!$A$2:$A$60,A23)=0,"",INDEX('MMAT Appraisal'!$K$2:$K$60,MATCH(A23,'MMAT Appraisal'!$A$2:$A$60,0))) | BP23: =IF(OR(BF23="No empirical data",ISNUMBER(SEARCH("RETRACTED",BV23))),"Not rated",IF(AND(ISNUMBER(BO23),BO23<=2),"Low",IF(AND(OR(BJ23="RCT",BJ23="Quasi-experimental with control"),LEFT(BF23,11)="Inferential",OR(BI23="Yes",BI23="Partly"),OR(BO23="",BO23>=4)),"High",IF(OR(BA23<>"None",LEFT(BF23,11)="Inferential"),"Moderate","Low")))) -> Not rated | BQ23: Not reported | BR23: Not reported | BS23: Excluded | BT23: E1: Retracted by the publisher (Hindawi, 9 Aug 2023) | BU23: Verified (full text) | BV23: RETRACTED by Hindawi (notice 9 Aug 2023, doi:10.1155/2023/9890345: systematic manipulation, peer-review manipulation). Exclude from the review.
A24: 23 | C24: Ruscanu A.-M.; Ciupe A.; Meza S.N. | D24: Ruscanu, Ana-Maria (57701767000); Ciupe, Aurelia (57105700600); Meza, Serban Nicolae (24829838400) | E24: 57701767000; 57105700600; 24829838400 | F24: arPcTECHture' - a gamified educational 3D virtual world for introductory concepts in computer architecture | G24: 2022 | H24: IEEE Global Engineering Education Conference, EDUCON | I24: 1 | J24: 10.1109/EDUCON52537.2022.9766679 | K24: https://www.scopus.com/inward/record.uri?eid=2-s2.0-85130484039&doi=10.1109%2fEDUCON52537.2022.9766679&partnerID=40&md5=71267bf685b69f91448badd57af0fbf7 | L24: Technical University of Cluj-Napoca, Multimedia Systems and Application Laboratory, Romania | M24: Ruscanu A.-M., Technical University of Cluj-Napoca, Multimedia Systems and Application Laboratory, Romania; Ciupe A., Technical University of Cluj-Napoca, Multimedia Systems and Application Laboratory, Romania; Meza S.N., Technical University of Cluj-Napoca, Multimedia Systems and Application Laboratory, Romania | N24: Gamified assessments have been mainly implemented for STEM education, focusing on motivational objectives and performance evaluation of teaching-learning processes. This paper presents a gamified educational 3D virtual world developed to provide a complementary tool for teaching software engineering students the fundamental concepts of computer hardware. The research design follows the needs identified across a focus group, but the prototype may also serve as support for K-12 with technical specializations. A beta-test has concluded that the learning outcome is improved when a gamification framework is provided. The engagement level has been assessed among engineering students, validating the prototype as a new complementary method for an Applied Informatics laboratory. © 2022 IEEE. | O24: computer hardware architecture; Gamification; serious game; user experience assessment | P24: Computer architecture; Computer hardware; E-learning; Software engineering; Students; Virtual reality; 3d virtual worlds; Complementary tools; Computer hardware architecture; Gamification; Hardware architecture; Objective evaluation; Performances evaluation; STEM education; Teaching-learning process; User experience assessments; Serious games | Q24: IEEE Computer Society | R24: English | S24: Conference paper | T24: Final | V24: Scopus | W24: Accepted | X24: InOurScope | Y24: Basic Education | Z24: João | AA24: Lamarck | AD24: In this paper: Desktop 3D Virtual Environment was used. Developed using Unity 3D Engine (not immersive VR or Cave VR specifically)​ . However, related works mentioned in the paper include immersive 3D virtual worlds in other studies​ . | AE24: User Experience Questionnaire (UEQ) 26 standardized items assessing Attractiveness, Perspicuity, Efficiency, Dependability, Stimulation, and Novelty. Plus 8 open-ended questions to collect improvement suggestions​ . | AF24: Positive Effects: Improved motivation and engagement. Easier skill acquisition through simulated practical experiences. Helped bridge the gap between theoretical and practical knowledge​ . Negative/Challenges: Some students wanted more innovative, dynamic, and challenging content. Slight issues with boredom after completing intuitive tasks​ . | AG24: Metrics based on UEQ: Attractiveness (general impression) Perspicuity (ease of learning) Efficiency (task completion without effort) Dependability (sense of control) Stimulation (excitement/motivation) Novelty (creativity/innovation) Quantitative data (graded from -3 to +3) and qualitative feedback were collected​ . | AH24: In this case: Unity 3D Engine for building the environment. Gamification elements: points, badges, quizzes, animated feedback, leaderboards​ . Related tools referenced: TestOut PC Pro (a simulator) PC Building Simulator (commercial game) EduCache (2D simulator for resource allocation) 3D environments simulating security threats​ . | AL24: STEAM | AM24: Lamarck | AN24: check | AR24: Romania | AS24: Europe | AT24: Higher education | AU24: First-year engineering students aged 18–20 | AV24: ICT | AW24: Computer architecture | AX24: Desktop 3D virtual world | AY24: Desktop | AZ24: Desktop VR (non-immersive) | BA24: None | BB24: Not measured | BC24: Mixed | BD24: + | BE24: UEQ: attractiveness 1.19 (above average), perspicuity 2.10 (excellent), stimulation 0.98 & novelty 0.67 (below average); authors: users 'lack enjoyment and get bored' | BF24: Descriptive only | BG24: Not reported | BH24: UEQ (26 items, Romanian version) + 8 open questions | BI24: Yes | BJ24: Single-group post-test only | BK24: Single group, post-test only | BL24: Quantitative descriptive | BM24: 12 respondents (of 200 invited) | BN24: Self-paced at home (.exe download) | BO24: =IF(COUNTIF('MMAT Appraisal'!$A$2:$A$60,A24)=0,"",INDEX('MMAT Appraisal'!$K$2:$K$60,MATCH(A24,'MMAT Appraisal'!$A$2:$A$60,0))) -> 3 | BP24: =IF(OR(BF24="No empirical data",ISNUMBER(SEARCH("RETRACTED",BV24))),"Not rated",IF(AND(ISNUMBER(BO24),BO24<=2),"Low",IF(AND(OR(BJ24="RCT",BJ24="Quasi-experimental with control"),LEFT(BF24,11)="Inferential",OR(BI24="Yes",BI24="Partly"),OR(BO24="",BO24>=4)),"High",IF(OR(BA24<>"None",LEFT(BF24,11)="Inferential"),"Moderate","Low")))) -> Low | BQ24: Boredom; tasks too easy | BR24: Usability, behavioural or safety issues only | BS24: Sensitivity | BT24: Outside basic education: First-year university students | BU24: Verified (full text) | BV24: 6% response rate; university students; non-immersive desktop 3D world
